Workbook

Sheet AplicQuest
A1: Processo | B1: DtDisp | C1: Juiz | D1: Vara | E1: Nome | F1: Local | G1: Sexo | H1: DN | I1: Cutis | J1: Cabelo | K1: Objetos | L1: Maconha | M1: Cocaína | N1: Crack | O1: Ecstasy | P1: LSD | Q1: Outras | R1: DenDrog | S1: DenOutros | T1: Aspectos | U1: Sentença | V1: ResDrogas | W1: ResOutros | X1: AvalNegPB | Y1: PenaBase | Z1: Agravantes33 | AA1: Atenuantes33 | AB1: Aumento33 | AC1: §4º | AD1: Pena33 | AE1: PenaDrogas | AF1: PenaOutros | AG1: TotPen | AH1: Substituição da pena | AI1: Regime inicial
A2: 00755542920168260050 | B2: 17/10/2017 | C2: Antonio Carlos de Campos Machado Junior | D2: 19ª Vara Criminal | E2: JUNIERE CASTRO DA SILVA | F2: Via Pública | G2: Masculino | H2: 34226 | I2: Parda | J2: Liso | K2: Pochete. Papéis . Celular. Dinheiro R$ 70,00 | L2: 20 porções. 17,9 g | M2: 33 porções. 16,6 g | N2: 27 porções. 3,95 g | O2: 0 | P2: 0 | Q2: 0 | R2: Art. 33 | S2: Não | T2: Divergências nos relatos dos policiais. Local de tráfico. Confissão informal. Preso no momento da sentença | U2: Procedente | V2: Art. 33 | W2: NA | X2: Não | Y2: 5a | Z2: Não | AA2: Não | AB2: Não | AC2: Sim total | AD2: 1a 8m | AE2: NA | AF2: NA | AG2: 1a 8m | AH2: Sim | AI2: NA
A3: 00646328920178260050 | B3: 19/10/2017 | C3: Antonio Carlos de Campos Machado Junior | D3: 19ª Vara Criminal | E3: VITOR CESAR DE OLIVEIRA ROCHA | F3: Favela - Viela | G3: Masculino | H3: 36283 | I3: Parda | J3: Outros | K3: Bolsa. Papéis. Dinheiro R$ 16,00 | L3: 67 porções. 180 g | M3: 155 porções. 198 g | N3: 0 | O3: 0 | P3: 0 | Q3: 0 | R3: Art. 33 | S3: Não | T3: Confissão. Local de tráfico. Preso no momento da sentença | U3: Procedente | V3: Art. 33 | W3: NA | X3: Não | Y3: 5a | Z3: Não | AA3: Não | AB3: Não | AC3: Sim parcial | AD3: 2a | AE3: NA | AF3: NA | AG3: 2a | AH3: Sim | AI3: NA
A4: 01006793320158260050 | B4: 14/03/2017 | C4: Antonio Carlos de Campos Machado Junior | D4: 19ª Vara Criminal | E4: ERIC RICARDO DA SILVA | F4: Via Pública | G4: Masculino | H4: 32120 | I4: Parda | J4: Não disponível | K4: Pochete | L4: 1 porção. 1 g | M4: 135 porções. 135 g | N4: 0 | O4: 0 | P4: 0 | Q4: 0 | R4: Art. 33 | S4: Não | T4: Divergências nos relatos dos policiais | U4: Desclassificação | V4: Art. 28 | W4: NA | X4: NA | Y4: NA | Z4: NA | AA4: NA | AB4: NA | AC4: NA | AD4: NA | AE4: Não | AF4: NA | AG4: NA | AH4: NA | AI4: NA
A5: 00198188920178260050 | B5: 06/06/2017 | C5: Antonio Carlos de Campos Machado Junior | D5: 19ª Vara Criminal | E5: ELENIDIO MESSIAS DE JESUS | F5: Via Pública | G5: Masculino | H5: 31345 | I5: Branca | J5: Calvície total | K5: Veículo | L5: 600 porções. 811,6 g | M5: 550 porções. 233,5 g | N5: 2800 porções. 604,6 g | O5: 0 | P5: 0 | Q5: Lança-perfume. 200 frascos. 1600 ml | R5: Art. 33 | S5: Não | T5: Confissão. Preso no momento da sentença | U5: Procedente | V5: Art. 33 | W5: NA | X5: Sim. Circunstâncias. Quantidade | Y5: 6a 3m | Z5: Não | AA5: Confissão | AB5: Não | AC5: Não cabimento | AD5: 6a 3m | AE5: NA | AF5: NA | AG5: 6a 3m | AH5: NA | AI5: Fechado
A6: 00243129420178260050 | B6: 20/09/2017 | C6: Antonio Carlos de Campos Machado Junior | D6: 19ª Vara Criminal | E6: Ivo Rodrigues de Lima | F6: Residência | G6: Masculino | H6: 28579 | I6: Branca | J6: Ondulado | K6: Peneira. Colher. Caixa térmica. Balança. Caderno. Celular. Faca. Bacia | L6: 4 sacos. 1 tijolo. 842,2 (total) | M6: 1 saco. 291,7 g | N6: 160 porções. 9 tijolos. 1961,4 g (total) | O6: 0 | P6: 0 | Q6: 0 | R6: Art. 33. Art. 35 | S6: Não | T6: Preso no momento da sentença. Denúncia | U6: Parcialmente procedente | V6: Art. 33 | W6: NA | X6: Não | Y6: 5a | Z6: Não | AA6: Não | AB6: Não | AC6: Sim parcial | AD6: 4a | AE6: NA | AF6: NA | AG6: 4a | AH6: Não | AI6: Fechado
A7: 00243129420178260050 | B7: 20/09/2017 | C7: Antonio Carlos de Campos Machado Junior | D7: 19ª Vara Criminal | E7: Marcelo Gomes de Sousa | F7: Residência | G7: Masculino | H7: 34806 | I7: Branca | J7: Ondulado | K7: Nada | L7: 4 sacos. 1 tijolo. 842,2 (total) | M7: 1 saco. 291,7 g | N7: 160 porções. 9 tijolos. 1961,4 g (total) | O7: 0 | P7: 0 | Q7: 0 | R7: Art. 33. Art. 35 | S7: Não | T7: Preso no momento da sentença | U7: Absolvição | V7: NA | W7: NA | X7: NA | Y7: NA | Z7: NA | AA7: NA | AB7: NA | AC7: NA | AD7: NA | AE7: NA | AF7: NA | AG7: NA | AH7: NA | AI7: NA
A8: 00850022620168260050 | B8: 24/01/2017 | C8: Antonio Carlos de Campos Machado Junior | D8: 19ª Vara Criminal | E8: Henrique dos Santos | F8: Residência | G8: Masculino | H8: 32087 | I8: Branca | J8: Não disponível | K8: Dinheiro R$ 370,00 | L8: 20 porções. 34,2 g | M8: 66 porções. 4,1 g | N8: 80 porções. 2,3 g | O8: 0 | P8: 0 | Q8: 0 | R8: Art. 33 | S8: Não | T8: Preso no momento da sentença | U8: Procedente | V8: Art. 33 | W8: NA | X8: Não | Y8: 5a | Z8: Não | AA8: Não | AB8: Não | AC8: Não cabimento | AD8: 5a | AE8: NA | AF8: NA | AG8: 5a | AH8: NA | AI8: Fechado
A9: 00199439120168260050 | B9: 30/03/2017 | C9: Vivian Brenner De Oliveira | D9: 11ª Vara Criminal | E9: TIAGO SILVA SOARES | F9: Área não ocupada | G9: Masculino | H9: 33476 | I9: Preta | J9: Carapinha | K9: Dinheiro R$ 24,00 | L9: 0 | M9: 0 | N9: 25 porções. 5,5 g | O9: 0 | P9: 0 | Q9: 0 | R9: Art. 33 | S9: Não | T9: Local de tráfico. Confissão. Confissão informal | U9: Procedente | V9: Art. 33 | W9: NA | X9: Não | Y9: 5a | Z9: Não | AA9: Não | AB9: Não | AC9: Sim parcial | AD9: 3a 4m | AE9: NA | AF9: NA | AG9: 3a 4m | AH9: Não | AI9: Fechado
A10: 00959728520168260050 | B10: 17/03/2017 | C10: Lizianne Marques Curto | D10: 11ª Vara Criminal | E10: RENATO DA SILVA GOMES | F10: Via Pública | G10: Masculino | H10: 32525 | I10: Parda | J10: Encaracolado | K10: Dinheiro R$ 39,00 | L10: 20 porções. 35,8 g | M10: 259 porções. 158,8 g | N10: 0 | O10: 0 | P10: 0 | Q10: 0 | R10: Art. 33 | S10: Não | T10: Local de tráfico. Preso no momento da sentença. Confissão informal | U10: Procedente | V10: Art. 33 | W10: NA | X10: Sim. Natureza. Quantidade | Y10: 6a | Z10: Reincidência | AA10: Não | AB10: Não | AC10: Não cabimento | AD10: 7a | AE10: NA | AF10: NA | AG10: 7a | AH10: NA | AI10: Fechado
A11: 00461275020178260050 | B11: 04/09/2017 | C11: Rejane Rodrigues Lage | D11: 11ª Vara Criminal | E11: RAFAEL SANTANA NUNES BEZERRA | F11: Residência | G11: Masculino | H11: 34009 | I11: Parda | J11: Não disponível | K11: Arma de fogo. Cartuchos. Capacete. Celular | L11: 0 | M11: 103 porções. 46,2 g | N11: 0 | O11: 0 | P11: 0 | Q11: 0 | R11: Art. 33 | S11: Art. 16 L10826 | T11: Preso no momento da sentença. Divergências nos relatos dos policiais | U11: Absolvição | V11: NA | W11: NA | X11: NA | Y11: NA | Z11: NA | AA11: NA | AB11: NA | AC11: NA | AD11: NA | AE11: NA | AF11: NA | AG11: NA | AH11: NA | AI11: NA
A12: 00607549320168260050 | B12: 21/03/2017 | C12: Vivian Brenner De Oliveira | D12: 11ª Vara Criminal | E12: ADEMIR LAMEU DA SILVA | F12: Via Pública | G12: Masculino | H12: 32784 | I12: Branca | J12: Encaracolado | K12: Dinheiro R$ 30,00 | L12: 0 | M12: 8 porções. 5,5 g | N12: 35 porções. 13,6 g | O12: 0 | P12: 0 | Q12: 0 | R12: Art. 33 | S12: Não | T12: Local de tráfico. Confissão informal | U12: Procedente | V12: Art. 33 | W12: NA | X12: Não | Y12: 5a | Z12: Não | AA12: Não | AB12: Não | AC12: Sim total | AD12: 1a 8m | AE12: NA | AF12: NA | AG12: 1a 8m | AH12: Não | AI12: Fechado
A13: 00116518320178260050 | B13: 04/07/2017 | C13: Tatiana Vieira Guerra | D13: 11ª Vara Criminal | E13: CICERO LEOPOLDINO DA SILVA | F13: Via Pública | G13: Masculino | H13: 26584 | I13: Preta | J13: Carapinha | K13: Papéis. Celular. Dinheiro R$ 628,25 | L13: 0 | M13: 51 porções. 39,6 g | N13: 0 | O13: 0 | P13: 0 | Q13: 0 | R13: Art. 33 | S13: Não | T13: Local de tráfico. Preso no momento da sentença. Confissão informal | U13: Procedente | V13: Art. 33 | W13: NA | X13: Não | Y13: 5a | Z13: Não | AA13: Não | AB13: Não | AC13: Não cabimento | AD13: 5a | AE13: NA | AF13: NA | AG13: 5a | AH13: NA | AI13: Fechado
A14: 00125207120168260635 | B14: 25/05/2017 | C14: Rejane Rodrigues Lage | D14: 11ª Vara Criminal | E14: RONALDO DO NASCIMENTO | F14: Via Pública | G14: Masculino | H14: 29853 | I14: Parda | J14: Não disponível | K14: Automóvel. Mochila. Sacos. Embalagens. Papéis. Dinheiro R$ 308,00 | L14: 0 | M14: 15 porções. 15 g | N14: 0 | O14: 0 | P14: 0 | Q14: 0 | R14: Art. 33. Art. 34 | S14: Não | T14: Preso no momento da sentença. Confissão informal | U14: Procedente | V14: Art. 33. Art. 34 | W14: NA | X14: Sim. Antecedentes | Y14: 5a 10m | Z14: Reincidência | AA14: Não | AB14: Não | AC14: Não cabimento | AD14: 6a 9m 20d | AE14: 4a 1m | AF14: NA | AG14: 10a 10m 20d | AH14: NA | AI14: Fechado
A15: 00894625620168260050 | B15: 04/09/2017 | C15: Vivian Brenner De Oliveira | D15: 11ª Vara Criminal | E15: ANDERSON BATISTA CRESPILHO | F15: Via Pública | G15: Masculino | H15: 33615 | I15: Branca | J15: Liso | K15: Celular. Dinheiro R$ 21,00 | L15: 17 porções. 51,5 g | M15: 156 porções. 111 g | N15: 0 | O15: 0 | P15: 0 | Q15: 0 | R15: Art. 33 | S15: Art. 180 CP | T15: Local de tráfico | U15: Procedente | V15: Art. 33 | W15: Art. 180 CP | X15: Não | Y15: 5a | Z15: Não | AA15: Não | AB15: Não | AC15: Sim parcial | AD15: 3a 4m | AE15: NA | AF15: 1a | AG15: 4a 4m | AH15: NA | AI15: Fechado
A16: 0031554-41.2016.8.26.0050 | B16: 42864 | C16: Carlos José Zulian | D16: 1ª Vara Criminal | E16: Klaus dos Santos Souza | F16: Via Pública | G16: Masculino | H16: 31815 | I16: Parda | J16: Carapinha | K16: Dinheiro R$ 100,00 | L16: 0 | M16: 21 porções. 5,8 g | N16: 0 | O16: 0 | P16: 0 | Q16: 0 | R16: Art. 33 | S16: Não | T16: Confissão | U16: Desclassificação | V16: Art. 28 | W16: NA | X16: NA | Y16: NA | Z16: NA | AA16: NA | AB16: NA | AC16: NA | AD16: NA | AE16: Não | AF16: NA | AG16: NA | AH16: NA | AI16: NA
A17: 0007839-58.2016.8.26.0635 | B17: 42871 | C17: MARIA PRISCILLA ERNANDES VEIGA OLIVEIRA | D17: 1ª Vara Criminal | E17: RINGLE DURVAL GLERIA | F17: Restaurante e afins | G17: Masculino | H17: 30746 | I17: Branca | J17: Liso | K17: Veículo. Mala. Celular. Dinheiro R$ 2404,00 | L17: 16 tijolos. 7816 g | M17: 0 | N17: 0 | O17: 0 | P17: 0 | Q17: 0 | R17: Art. 33. Art. 35 | S17: Não | T17: Preso no momento da sentença. Denúncia | U17: Procedente | V17: Art. 33. Art. 35 | W17: NA | X17: Não | Y17: 5a | Z17: Reincidência | AA17: Não | AB17: Não | AC17: Não cabimento | AD17: 6a 8m | AE17: 4a | AF17: NA | AG17: 10a 8m | AH17: NA | AI17: Fechado
A18: 0007839-58.2016.8.26.0635 | B18: 42871 | C18: MARIA PRISCILLA ERNANDES VEIGA OLIVEIRA | D18: 1ª Vara Criminal | E18: THIAGO TEIXEIRA DE LIMA | F18: Restaurante e afins | G18: Masculino | H18: 32255 | I18: Branca | J18: Não disponível | K18: Veículo. Mala. Celular. Dinheiro R$ 2404,00 | L18: 16 tijolos. 7816 g | M18: 0 | N18: 0 | O18: 0 | P18: 0 | Q18: 0 | R18: Art. 33. Art. 35 | S18: Não | T18: Preso no momento da sentença. Denúncia | U18: Procedente | V18: Art. 33. Art. 35 | W18: NA | X18: Não | Y18: 5a | Z18: Não | AA18: Não | AB18: Não | AC18: Não | AD18: 5a | AE18: 3a | AF18: NA | AG18: 8a | AH18: NA | AI18: Fechado
A19: 0007839-58.2016.8.26.0635 | B19: 42871 | C19: MARIA PRISCILLA ERNANDES VEIGA OLIVEIRA | D19: 1ª Vara Criminal | E19: JONATHAN ALVES PAIXÃO | F19: Restaurante e afins | G19: Masculino | H19: 34325 | I19: Branca | J19: Liso | K19: Veículo. Mala. Celular. Dinheiro R$ 2404,00 | L19: 16 tijolos. 7816 g | M19: 0 | N19: 0 | O19: 0 | P19: 0 | Q19: 0 | R19: Art. 33. Art. 35 | S19: Não | T19: Preso no momento da sentença. Denúncia | U19: Procedente | V19: Art. 33. Art. 35 | W19: NA | X19: Não | Y19: 5a | Z19: Não | AA19: Não | AB19: Não | AC19: Não | AD19: 5a | AE19: 3a | AF19: NA | AG19: 8a | AH19: NA | AI19: Fechado
A20: 0055873-39.2017.8.26.0050 | B20: 43069 | C20: Carlos José Zulian | D20: 1ª Vara Criminal | E20: ANDERSON RICARDO DE PAULA | F20: Via Pública | G20: Masculino | H20: 34118 | I20: Preta | J20: Não disponível | K20: Embalagens. Balança. Fermento em pó. Celular. Faca. Colher. Bacia. Liquidificador | L20: 1 tijolo. 189,5 g. 50 porções. 81,8 g | M20: 357 porções. 211,5 g | N20: 0 | O20: 0 | P20: 0 | Q20: 0 | R20: Art. 33 | S20: Não | T20: Preso no momento da sentença. Denúncia anônima | U20: Procedente | V20: Art. 33 | W20: NA | X20: Não | Y20: 5a | Z20: Não | AA20: Não | AB20: Não | AC20: Sim parcial | AD20: 3a | AE20: NA | AF20: NA | AG20: 3a | AH20: Sim | AI20: NA
A21: 0096963-61.2016.8.26.0050 | B21: 42958 | C21: Carlos José Zulian | D21: 1ª Vara Criminal | E21: GABRIEL SANCHEZ ORLANDO | F21: Via Pública | G21: Masculino | H21: 33993 | I21: Branca | J21: Liso | K21: Veículo. Balança. Celular. Dinheiro R$ 212,00 | L21: 1 tijolo. 488,4 g. 2 pés. 149,9 g | M21: 0 | N21: 0 | O21: 0 | P21: 0 | Q21: 0 | R21: Art. 33 | S21: Não | T21: Confissão informal. Denúncia | U21: Parcialmente procedente | V21: Art. 33 | W21: NA | X21: Não | Y21: 5a | Z21: Não | AA21: Não | AB21: Não | AC21: Não | AD21: 5a | AE21: NA | AF21: NA | AG21: 5a | AH21: NA | AI21: Fechado
A22: 0096963-61.2016.8.26.0050 | B22: 42958 | C22: Carlos José Zulian | D22: 1ª Vara Criminal | E22: Fernando Rodrigues Sevilhano | F22: Via Pública | G22: Masculino | H22: 34396 | I22: Branca | J22: Liso | K22: Dinheiro R$ 60,00 | L22: 1 tijolo. 2 vidros. 2372,2 g (total) | M22: 0 | N22: 0 | O22: 0 | P22: 0 | Q22: 0 | R22: Art. 33 | S22: Não | T22: Não há | U22: Procedente | V22: Art. 33 | W22: NA | X22: Não | Y22: 5a | Z22: Não | AA22: Não | AB22: Não | AC22: Não | AD22: 5a | AE22: NA | AF22: NA | AG22: 5a | AH22: NA | AI22: Fechado
A23: 0013747-96.2016.8.26.0635 | B23: 42930 | C23: Carlos José Zulian | D23: 1ª Vara Criminal | E23: SILVANIL CAMPANHA VIEIRA | F23: Via Pública | G23: Masculino | H23: 32988 | I23: Parda | J23: Carapinha | K23: Cachimbo. R$ 10,00 | L23: 0 | M23: 0 | N23: 1 porção. 0,2 g | O23: 0 | P23: 0 | Q23: 0 | R23: Art. 33 | S23: Não | T23: Preso no momento da sentença. Local de tráfico | U23: Procedente | V23: Art. 33 | W23: NA | X23: Sim. Antecedentes | Y23: 5a 10m | Z23: Reincidência | AA23: Não | AB23: Não | AC23: Não cabimento | AD23: 6a 9m 20d | AE23: NA | AF23: NA | AG23: 6a 9m 20d | AH23: NA | AI23: Fechado
A24: 0004370-76.2017.8.26.0050 | B24: 42934 | C24: Carlos José Zulian | D24: 1ª Vara Criminal | E24: OMIR TOME NETO | F24: Via Pública | G24: Masculino | H24: 34292 | I24: Branca | J24: Ondulado | K24: Dinheiro R$ 5,00 | L24: 20 porções. 17,6 g | M24: 21 porções. 15,2 g | N24: 3 porções. 3,7 g | O24: 0 | P24: 0 | Q24: 0 | R24: Art. 33 | S24: Não | T24: Preso no momento da sentença | U24: Absolvição | V24: NA | W24: NA | X24: NA | Y24: NA | Z24: NA | AA24: NA | AB24: NA | AC24: NA | AD24: NA | AE24: NA | AF24: NA | AG24: NA | AH24: NA | AI24: NA
A25: 0004434-23.2016.8.26.0050 | B25: 42765 | C25: Carlos José Zulian | D25: 1ª Vara Criminal | E25: JAILSON ANDRE DA SILVA | F25: Via Pública | G25: Masculino | H25: 32782 | I25: Parda | J25: Encaracolado | K25: Pochete. Papéis. Dinheiro R$ 60,00 | L25: 61 porções. 67 g | M25: 54 porções. 10 g | N25: 81 porções. 17 g | O25: 0 | P25: 0 | Q25: 0 | R25: Art. 33 | S25: Não | T25: Local de tráfico. Preso no momento da sentença | U25: Procedente | V25: Art. 33 | W25: NA | X25: Sim. Antecedentes | Y25: 5a 10m | Z25: Reincidência | AA25: Não | AB25: Não | AC25: Não cabimento | AD25: 6a 9m 20d | AE25: NA | AF25: NA | AG25: 6a 9m 20d | AH25: NA | AI25: Fechado
A26: 0012132-71.2016.8.26.0635 | B26: 43069 | C26: Carlos José Zulian | D26: 1ª Vara Criminal | E26: CAUE LEANDRO DA SILVA CEGARRA LYRA | F26: Via Pública | G26: Masculino | H26: 35694 | I26: Branca | J26: Não disponível | K26: Veículo. Dinheiro R$ 641,80 | L26: 2072,3 g | M26: 59,8 g | N26: 0 | O26: 0 | P26: 0 | Q26: 0 | R26: Art. 33 | S26: Não | T26: Preso no momento da sentença. Local de tráfico | U26: Procedente | V26: Art. 33 | W26: NA | X26: Não | Y26: 5a | Z26: Não | AA26: Não | AB26: Não | AC26: Não | AD26: 5a | AE26: NA | AF26: NA | AG26: 5a | AH26: NA | AI26: Fechado
A27: 0030299-48.2016.8.26.0050 | B27: 42807 | C27: Carlos José Zulian | D27: 1ª Vara Criminal | E27: ANUNCIATO MARCELINO DE OLIVEIRA NETO | F27: Via Pública | G27: Masculino | H27: 30612 | I27: Branca | J27: Encaracolado | K27: Veículo. Celular | L27: 0 | M27: 1 tijolo. 931,2 g | N27: 0 | O27: 0 | P27: 0 | Q27: 0 | R27: Art. 33. Art. 35 | S27: Não | T27: Preso no momento da sentença | U27: Absolvição | V27: NA | W27: NA | X27: NA | Y27: NA | Z27: NA | AA27: NA | AB27: NA | AC27: NA | AD27: NA | AE27: NA | AF27: NA | AG27: NA | AH27: NA | AI27: NA
A28: 00118686320168260050 | B28: 03/05/2017 | C28: Maria Cecília Leone | D28: 10ª Vara Criminal | E28: BRUNO DE OLIVEIRA CALACA | F28: Área não ocupada | G28: Masculino | H28: 34329 | I28: Parda | J28: Carapinha | K28: Celular. Dinheiro R$ 64,00 | L28: 13 porções. 18 g | M28: 16 porções. 1,1 g | N28: 0 | O28: 0 | P28: 0 | Q28: 0 | R28: Art. 33 | S28: Não | T28: Local de tráfico. Confissão informal | U28: Procedente | V28: Art. 33 | W28: NA | X28: Não | Y28: 5a | Z28: Não | AA28: Não | AB28: Não | AC28: Não | AD28: 5a | AE28: NA | AF28: NA | AG28: 5a | AH28: NA | AI28: Fechado
A29: 00097232520168260635 | B29: 27/04/2017 | C29: Maria Cecília Leone | D29: 10ª Vara Criminal | E29: GUSTAVO IAN DOS SANTOS | F29: Via Pública | G29: Masculino | H29: 35234 | I29: Parda | J29: Não disponível | K29: Colher. Peneira. Tubo. Invólucro. Papel filme | L29: 0 | M29: 7 porções. 16,8 g | N29: 53 porções. 18,6 g | O29: 0 | P29: 0 | Q29: 0 | R29: Art. 33 | S29: Não | T29: Confissão informal. Confissão. Preso no momento da sentença. Atitude suspeita | U29: Procedente | V29: Art. 33 | W29: NA | X29: Não | Y29: 5a | Z29: Não | AA29: Não | AB29: Não | AC29: Sim parcial | AD29: 2a 6m | AE29: NA | AF29: NA | AG29: 2a 6m | AH29: Não | AI29: Fechado
A30: 00132837220168260635 | B30: 17/07/2017 | C30: Marcelo Matias Pereira | D30: 10ª Vara Criminal | E30: ALBERTO DIEGO DOS REMEDIOS | F30: Via Pública | G30: Masculino | H30: 32339 | I30: Parda | J30: Liso | K30: Bolsa. Chave. Papel filme. Papel alumínio. Dinheiro R$ 102,00 | L30: 10 tijolos. 9903 g | M30: 0 | N30: 0 | O30: 0 | P30: 0 | Q30: 0 | R30: Art. 33 | S30: Não | T30: Confissão. Preso no momento da sentença | U30: Procedente | V30: Art. 33 | W30: NA | X30: Sim. Quantidade | Y30: 7a 6m | Z30: Reincidência | AA30: Confissão | AB30: Não | AC30: Não | AD30: 7a 6m | AE30: NA | AF30: NA | AG30: 7a 6m | AH30: NA | AI30: Fechado
A31: 00132837220168260635 | B31: 17/07/2017 | C31: Marcelo Matias Pereira | D31: 10ª Vara Criminal | E31: JAIRO ALVES DA SILVA | F31: Via Pública | G31: Masculino | H31: 31328 | I31: Parda | J31: Ondulado | K31: Bolsa. Chave. Papel filme. Papel alumínio. Dinheiro R$ 102,00 | L31: 10 tijolos. 9903 g | M31: 0 | N31: 0 | O31: 0 | P31: 0 | Q31: 0 | R31: Art. 33 | S31: Não | T31: Preso no momento da sentença | U31: Procedente | V31: Art. 33 | W31: NA | X31: Sim. Quantidade | Y31: 7a 6m | Z31: Não | AA31: Não | AB31: Não | AC31: Não | AD31: 7a 6m | AE31: NA | AF31: NA | AG31: 7a 6m | AH31: NA | AI31: Fechado
A32: 00473220720168260050 | B32: 09/05/2017 | C32: Daiane Saladini Monari | D32: 10ª Vara Criminal | E32: ISRAEL VIEIRA DOS SANTOS | F32: Residência | G32: Masculino | H32: 30801 | I32: Parda | J32: Não disponível | K32: Pochete. Dinheiro R$ 45,00 | L32: 41 porções. 66,3 g | M32: 18 porções. 17,8 g | N32: 54 porções. 11,7 g | O32: 0 | P32: 0 | Q32: 0 | R32: Art. 33 | S32: Não | T32: Confissão. Local de tráfico. Preso no momento da sentença | U32: Procedente | V32: Art. 33 | W32: NA | X32: Sim. Natureza | Y32: 5a 10m | Z32: Não | AA32: Confissão | AB32: Não | AC32: Não | AD32: 5a | AE32: NA | AF32: NA | AG32: 5a | AH32: NA | AI32: Fechado
A33: 00110475020168260635 | B33: 11/07/2017 | C33: Marcelo Matias Pereira | D33: 10ª Vara Criminal | E33: CRISTIANO DE JESUS SANTOS | F33: Via Pública | G33: Masculino | H33: 31129 | I33: Parda | J33: Carapinha | K33: Celular. Dinheiro R$ 92,00 | L33: 14 porções. 7 g | M33: 0 | N33: 44 porções. 15,8 g | O33: 0 | P33: 0 | Q33: 0 | R33: Art. 33 | S33: Não | T33: Confissão informal. Preso no momento da sentença | U33: Procedente | V33: Art. 33 | W33: NA | X33: Não | Y33: 5a | Z33: Não | AA33: Não | AB33: Não | AC33: Não | AD33: 5a | AE33: NA | AF33: NA | AG33: 5a | AH33: NA | AI33: Fechado
A34: 00182053420178260050 | B34: 09/08/2017 | C34: Maria Cecília Leone | D34: 10ª Vara Criminal | E34: IGOR LOPES FONTES SILVA | F34: Via Pública | G34: Masculino | H34: 35499 | I34: Branca | J34: Carapinha | K34: Mochila. Celular | L34: 190 porções. 1832,5 g | M34: 1003 porções. 187,2 g | N34: 0 | O34: 0 | P34: 0 | Q34: Lança-perfume. 40 frascos. 160 ml | R34: Art. 33 | S34: Não | T34: Confissão. Preso no momento da sentença | U34: Procedente | V34: Art. 33 | W34: NA | X34: Não | Y34: 5a | Z34: Não | AA34: Não | AB34: Não | AC34: Não | AD34: 5a | AE34: NA | AF34: NA | AG34: 5a | AH34: NA | AI34: Fechado
A35: 00058525020178260635 | B35: 24/10/2017 | C35: Marcelo Matias Pereira | D35: 10ª Vara Criminal | E35: GISELE APARECIDA RIBEIRO | F35: Via Pública | G35: Feminino | H35: 35584 | I35: Parda | J35: Não disponível | K35: Bilhete único. Celular. Dinheiro R$ 62,00 | L35: 14 porções. 20,8 g | M35: 27 porções. 20,6 g | N35: 0 | O35: 0 | P35: 0 | Q35: 0 | R35: Art. 33 | S35: Não | T35: Local de tráfico. Presa no momento da sentença | U35: Procedente | V35: Art. 33 | W35: NA | X35: Não | Y35: 5a | Z35: Não | AA35: Não | AB35: Adolescente | AC35: Sim parcial | AD35: 2a 11m | AE35: NA | AF35: NA | AG35: 2a 11m | AH35: Não | AI35: Fechado
A36: 00005711620178260635 | B36: 31/08/2017 | C36: Marcelo Matias Pereira | D36: 10ª Vara Criminal | E36: RONALDO AMARANTE DA SILVA | F36: Via Pública | G36: Masculino | H36: 29927 | I36: Parda | J36: Não disponível | K36: Papel. Rádio transmissor. Dinheiro R$ 34,00 | L36: 0 | M36: 55 porções. 26,5 g | N36: 0 | O36: 0 | P36: 0 | Q36: 0 | R36: Art. 33 | S36: Não | T36: Preso no momento da sentença | U36: Procedente | V36: Art. 33 | W36: NA | X36: Não | Y36: 5a | Z36: Reincidência | AA36: Não | AB36: Não | AC36: Não cabimento | AD36: 5a 10m | AE36: NA | AF36: NA | AG36: 5a 10m | AH36: NA | AI36: Fechado
A37: 01019426620168260050 | B37: 14/07/2017 | C37: Maria Cecília Leone | D37: 10ª Vara Criminal | E37: THAIS DOS SANTOS MIRANDA | F37: Via Pública | G37: Feminino | H37: 35336 | I37: Parda | J37: Não disponível | K37: Dinheiro R$ 262,00 | L37: 0 | M37: 36 porções. 28,9 g | N37: 0 | O37: 0 | P37: 0 | Q37: 0 | R37: Art. 33 | S37: Não | T37: Confissão | U37: Procedente | V37: Art. 33 | W37: NA | X37: Não | Y37: 5a | Z37: Não | AA37: Não | AB37: Adolescente | AC37: Sim parcial | AD37: 2a 11m | AE37: NA | AF37: NA | AG37: 2a 11m | AH37: Sim | AI37: NA
A38: 01059208520158260050 | B38: 13/01/2017 | C38: Maria Cecília Leone | D38: 10ª Vara Criminal | E38: WAGNER ROBERTO SOARES | F38: Via Pública | G38: Masculino | H38: 29819 | I38: Parda | J38: Carapinha | K38: Pochete. Dinheiro R$ 54,00 | L38: 0 | M38: 21 porções. 7,2 g | N38: 100 porções. 21,1 g | O38: 0 | P38: 0 | Q38: 0 | R38: Art. 33 | S38: Não | T38: Local de tráfico. Confissão informal. Preso no momento da sentença | U38: Procedente | V38: Art. 33 | W38: NA | X38: Sim. Antecedentes. Variedade | Y38: 5a 10m | Z38: Reincidência | AA38: Não | AB38: Não | AC38: Não cabimento | AD38: 6a 9m 20d | AE38: NA | AF38: NA | AG38: 6a 9m 20d | AH38: NA | AI38: Fechado
A39: 00085284820158260050 | B39: 03/05/2017 | C39: Marcos Fleury Silveira de Alvarenga | D39: 12ª Vara Criminal | E39: XIUYU HUANG | F39: Comércio e serviços | G39: Feminino | H39: Não disponível | I39: Amarela | J39: Liso | K39: Mochila. Dinheiro R$ 17369,00 | L39: 1 porção. 69,7 g | M39: 4 porções. 18,7 g | N39: 0 | O39: 0 | P39: 0 | Q39: 0 | R39: Art. 33 | S39: Não | T39: Nacionalidade | U39: Absolvição | V39: NA | W39: NA | X39: NA | Y39: NA | Z39: NA | AA39: NA | AB39: NA | AC39: NA | AD39: NA | AE39: NA | AF39: NA | AG39: NA | AH39: NA | AI39: NA
A40: 00934274220168260050 | B40: 12/07/2017 | C40: Marcos Fleury Silveira de Alvarenga | D40: 12ª Vara Criminal | E40: GUILHERME HENRIQUE DA SILVA ROCHA | F40: Via Pública | G40: Masculino | H40: 33304 | I40: Parda | J40: Não disponível | K40: Celular. Dinheiro R$ 172,00 | L40: 29 porções. 51,4 g | M40: 28 porções. 22 g | N40: 0 | O40: 0 | P40: 0 | Q40: 0 | R40: Art. 33 | S40: Não | T40: Confissão. Preso no momento da sentença. Atitude suspeita | U40: Procedente | V40: Art. 33 | W40: NA | X40: Não | Y40: 5a | Z40: Não | AA40: Não | AB40: Não | AC40: Sim total | AD40: 1a 8m | AE40: NA | AF40: NA | AG40: 1a 8m | AH40: Não | AI40: Aberto
A41: 00934274220168260050 | B41: 12/07/2017 | C41: Marcos Fleury Silveira de Alvarenga | D41: 12ª Vara Criminal | E41: WESLEY MARTINS DE OLIVEIRA | F41: Via Pública | G41: Masculino | H41: 33968 | I41: Parda | J41: Não disponível | K41: Celular. Dinheiro R$ 172,00 | L41: 29 porções. 51,4 g | M41: 28 porções. 22 g | N41: 0 | O41: 0 | P41: 0 | Q41: 0 | R41: Art. 33 | S41: Não | T41: Confissão. Preso no momento da sentença. Atitude suspeita | U41: Procedente | V41: Art. 33 | W41: NA | X41: Não | Y41: 5a | Z41: Não | AA41: Não | AB41: Não | AC41: Sim total | AD41: 1a 8m | AE41: NA | AF41: NA | AG41: 1a 8m | AH41: Não | AI41: Aberto
A42: 01019001720168260050 | B42: 04/04/2017 | C42: Marcos Fleury Silveira de Alvarenga | D42: 12ª Vara Criminal | E42: JOSÉ ALVES DE SOUSA VIANA | F42: Residência | G42: Masculino | H42: 30599 | I42: Branca | J42: Outros | K42: Prato. Colher. Balança. Celular. Dinheiro R$ 1.276,00 | L42: 0 | M42: 51 porções. 261,5 g | N42: 0 | O42: 0 | P42: 0 | Q42: 0 | R42: Art. 33 | S42: Não | T42: Preso no momento da sentença. Mandado | U42: Procedente | V42: Art. 33 | W42: NA | X42: Não | Y42: 5a | Z42: Não | AA42: Não | AB42: Não | AC42: Sim total | AD42: 1a 8m | AE42: NA | AF42: NA | AG42: 1a 8m | AH42: Não | AI42: Semiaberto
A43: 00004526420178260050 | B43: 03/08/2017 | C43: Marcos Fleury Silveira de Alvarenga | D43: 12ª Vara Criminal | E43: DANIEL DE FRANÇA SOUSA PEREIRA | F43: Comércio e serviços | G43: Masculino | H43: 32699 | I43: Branca | J43: Não disponível | K43: Celular. Dinheiro R$ 70,00 | L43: 2 porções. 1,8 g | M43: 11 porções. 10 g | N43: 36 porções. 4 g | O43: 0 | P43: 0 | Q43: 0 | R43: Art. 33 | S43: Não | T43: Divergências nos relatos dos policiais. Preso no momento da sentença. Atitude suspeita | U43: Absolvição | V43: NA | W43: NA | X43: NA | Y43: NA | Z43: NA | AA43: NA | AB43: NA | AC43: NA | AD43: NA | AE43: NA | AF43: NA | AG43: NA | AH43: NA | AI43: NA
A44: 00025095520178260050 | B44: 03/10/2017 | C44: Rodrigo Cesar Muller Valente | D44: 12ª Vara Criminal | E44: JONNATAN CORREIA CARDOSO | F44: Via Pública | G44: Masculino | H44: 31478 | I44: Parda | J44: Não disponível | K44: Dinheiro R$ 20,00 | L44: 0 | M44: 19 porções. 8,6 g | N44: 0 | O44: 0 | P44: 0 | Q44: 0 | R44: Art. 33 | S44: Não | T44: Não há | U44: Desclassificação | V44: Art. 28 | W44: NA | X44: NA | Y44: NA | Z44: NA | AA44: NA | AB44: NA | AC44: NA | AD44: NA | AE44: Não | AF44: NA | AG44: NA | AH44: NA | AI44: NA
A45: 00410384620178260050 | B45: 30/08/2017 | C45: Marcos Fleury Silveira de Alvarenga | D45: 12ª Vara Criminal | E45: ROBSON CHAVES CATARINO | F45: Via Pública | G45: Masculino | H45: 31904 | I45: Parda | J45: Não disponível | K45: Veículo. Celular. Dinheiro R$ 760,00 | L45: 89 porções. 150,1 g | M45: 600 porções. 334,4 g | N45: 854 porções. 256,1 g | O45: 0 | P45: 0 | Q45: 0 | R45: Art. 33 | S45: Não | T45: Confissão informal. Confissão. Preso no momento da sentença. Atitude suspeita | U45: Procedente | V45: Art. 33 | W45: NA | X45: Não | Y45: 5a | Z45: Não | AA45: Não | AB45: Não | AC45: Sim total | AD45: 1a 8m | AE45: NA | AF45: NA | AG45: 1a 8m | AH45: Não | AI45: Semiaberto
A46: 00370435920168260050 | B46: 18/10/2017 | C46: Marcos Fleury Silveira de Alvarenga | D46: 12ª Vara Criminal | E46: BARBARA THAMARIS GALVAO DE BARROS | F46: Via Pública | G46: Feminino | H46: 34053 | I46: Parda | J46: Não disponível | K46: Dinheiro R$ 324,60 | L46: 0 | M46: 7 porções. 15,40 g | N46: 0 | O46: 0 | P46: 0 | Q46: 0 | R46: Art. 33 | S46: Não | T46: Denúncia anônima | U46: Desclassificação | V46: Art. 28 | W46: NA | X46: NA | Y46: NA | Z46: NA | AA46: NA | AB46: NA | AC46: NA | AD46: NA | AE46: Não | AF46: NA | AG46: NA | AH46: NA | AI46: NA
A47: 00370435920168260050 | B47: 18/10/2017 | C47: Marcos Fleury Silveira de Alvarenga | D47: 12ª Vara Criminal | E47: DANIELA APARECIDA FERREIRA | F47: Via Pública | G47: Feminino | H47: 32836 | I47: Parda | J47: Não disponível | K47: Dinheiro R$ 10,00 | L47: 0 | M47: 7 porções. 15,40 g | N47: 0 | O47: 0 | P47: 0 | Q47: 0 | R47: Art. 33 | S47: Não | T47: Denúncia anônima | U47: Desclassificação | V47: Art. 28 | W47: NA | X47: NA | Y47: NA | Z47: NA | AA47: NA | AB47: NA | AC47: NA | AD47: NA | AE47: Não | AF47: NA | AG47: NA | AH47: NA | AI47: NA
A48: 00269908220178260050 | B48: 11/09/2017 | C48: Rodrigo Cesar Muller Valente | D48: 12ª Vara Criminal | E48: BRUNO DE MOURA MEIRELES | F48: Residência | G48: Masculino | H48: 31336 | I48: Branca | J48: Não disponível | K48: Veículo. Liquidificador. Galão. Balança. Munição. Caderno. Celular. Bule. Faca. Funil. Panela. Embalagens. Dinheiro R$ 16,00 | L48: 1 porção. 0,8 g | M48: 216 g | N48: 0 | O48: 0 | P48: 0 | Q48: Lança-perfume. 1 frasco. 50000 ml | R48: Art. 33 | S48: Art. 12 L10826 | T48: Confissão. Preso no momento da sentença. Denúncia | U48: Procedente | V48: Art. 33 | W48: Art. 12 L10826 | X48: Não | Y48: 5a | Z48: Reincidência | AA48: Confissão | AB48: Não | AC48: Não cabimento | AD48: 5a | AE48: NA | AF48: 1a | AG48: 6a | AH48: NA | AI48: Fechado
A49: 00978452320168260050 | B49: 07/02/2017 | C49: Claudia Carneiro Calbucci Renaux | D49: 13ª Vara Criminal | E49: DIEGO DOS SANTOS SOUZA | F49: Via Pública | G49: Masculino | H49: 34568 | I49: Parda | J49: Carapinha | K49: Nada | L49: 3 porções. 13,5 g | M49: 0 | N49: 33 porções. 5,7 g | O49: 0 | P49: 0 | Q49: 0 | R49: Art. 33 | S49: Não | T49: Local de tráfico. Atitude suspeita. Confissão informal | U49: Procedente | V49: Art. 33 | W49: NA | X49: Não | Y49: 5a | Z49: Não | AA49: Não | AB49: Não | AC49: Sim total | AD49: 1a 8m | AE49: NA | AF49: NA | AG49: 1a 8m | AH49: Sim | AI49: NA
A50: 00708608020178260050 | B50: 19/09/2017 | C50: José Roberto Cabral Longaretti | D50: 13ª Vara Criminal | E50: ALBERTO DANTAS DE OLIVEIRA | F50: Residência | G50: Masculino | H50: 30218 | I50: Branca | J50: Calvície parcial | K50: Nada | L50: 0 | M50: 5 porções. 1,8 g. 1 saco. 1170,4 g | N50: 0 | O50: 0 | P50: 0 | Q50: 0 | R50: Art. 33 | S50: Não | T50: Confissão informal. Preso no momento da sentença | U50: Procedente | V50: Art. 33 | W50: NA | X50: Sim. Antecedentes. Quantidade | Y50: 7a | Z50: Não | AA50: Não | AB50: Não | AC50: Não | AD50: 7a | AE50: NA | AF50: NA | AG50: 7a | AH50: NA | AI50: Fechado
A51: 00440645220178260050 | B51: 19/07/2017 | C51: José Roberto Cabral Longaretti | D51: 13ª Vara Criminal | E51: JULIO CESAR DA SILVA DONATO | F51: Via Pública | G51: Masculino | H51: 35522 | I51: Parda | J51: Não disponível | K51: Dinheiro R$ 64,00 | L51: 23 porções. 21 g | M51: 0 | N51: 0 | O51: 10 comprimidos. 3,2 g | P51: 0 | Q51: 0 | R51: Art. 33 | S51: Não | T51: Atitude suspeita. Confissão informal | U51: Procedente | V51: Art. 33 | W51: NA | X51: Não | Y51: 5a | Z51: Não | AA51: Não | AB51: Não | AC51: Não | AD51: 5a | AE51: NA | AF51: NA | AG51: 5a | AH51: NA | AI51: Fechado
A52: 00016165520178260635 | B52: 18/04/2017 | C52: Claudia Carneiro Calbucci Renaux | D52: 13ª Vara Criminal | E52: GABRIEL DA SILVA CONCEIÇÃO | F52: Via Pública | G52: Masculino | H52: 35969 | I52: Parda | J52: Não disponível | K52: Dinheiro R$ 425,05 | L52: 0 | M52: 79 porções. 68,5 g | N52: 1 porção. 0,05 g | O52: 0 | P52: 0 | Q52: 0 | R52: Art. 33 | S52: Não | T52: Preso no momento da sentença. Confissão informal | U52: Procedente | V52: Art. 33 | W52: NA | X52: Não | Y52: 5a | Z52: Não | AA52: Não | AB52: Não | AC52: Sim total | AD52: 1a 8m | AE52: NA | AF52: NA | AG52: 1a 8m | AH52: Sim | AI52: NA
A53: 00086724220178260635 | B53: 26/10/2017 | C53: José Roberto Cabral Longaretti | D53: 13ª Vara Criminal | E53: HELIO MACIEL BALDRAIA | F53: Via Pública | G53: Masculino | H53: 35679 | I53: Parda | J53: Carapinha | K53: Bolsa | L53: 50 porções. 74,9 g | M53: 45 porções. 25,4 g | N53: 0 | O53: 0 | P53: 0 | Q53: 0 | R53: Art. 33 | S53: Não | T53: Confissão. Prisão no momento da sentença | U53: Procedente | V53: Art. 33 | W53: NA | X53: Não | Y53: 5a | Z53: Não | AA53: Não | AB53: Não | AC53: Não | AD53: 5a | AE53: NA | AF53: NA | AG53: 5a | AH53: NA | AI53: Semiaberto
A54: 00663831420178260050 | B54: 07/11/2017 | C54: José Roberto Cabral Longaretti | D54: 13ª Vara Criminal | E54: NATALIA LOURENCO FRANCO | F54: Via Pública | G54: Feminino | H54: 35920 | I54: Parda | J54: Não disponível | K54: Celular. Dinheiro R$ 569,00 | L54: 222 porções. 537,0 g | M54: 221 porções. 27 g | N54: 140 porções. 126,6 g | O54: 0 | P54: 0 | Q54: 0 | R54: Art. 33 | S54: Não | T54: Preso no momento da sentença. Ponto de tráfico. Confissão informal. Confissão | U54: Procedente | V54: Art. 33 | W54: NA | X54: Não | Y54: 5a | Z54: Não | AA54: Não | AB54: Adolescente | AC54: Sim parcial | AD54: 3a 10m 20d | AE54: NA | AF54: NA | AG54: 3a 10m 20d | AH54: Sim | AI54: NA
A55: 00663831420178260050 | B55: 07/11/2017 | C55: José Roberto Cabral Longaretti | D55: 13ª Vara Criminal | E55: PAMELA TAVARES DE LIMA | F55: Via Pública | G55: Feminino | H55: 32002 | I55: Branca | J55: Não disponível | K55: Celular. Dinheiro R$ 257,05 | L55: 0 | M55: 0 | N55: 0 | O55: 0 | P55: 0 | Q55: 0 | R55: Art. 33 | S55: Não | T55: Local de tráfico | U55: Absolvição | V55: NA | W55: NA | X55: NA | Y55: NA | Z55: NA | AA55: NA | AB55: NA | AC55: NA | AD55: NA | AE55: NA | AF55: NA | AG55: NA | AH55: NA | AI55: NA
A56: 00657223520178260050 | B56: 19/09/2017 | C56: Wendell Lopes Barbosa de Souza | D56: 13ª Vara Criminal | E56: EDUARDO LUIZ SILVA | F56: Via Pública | G56: Masculino | H56: 35263 | I56: Branca | J56: Não disponível | K56: Veículo | L56: 2 tijolos. 1625,9 g | M56: 0 | N56: 0 | O56: 0 | P56: 0 | Q56: 0 | R56: Art. 33 | S56: Não | T56: Preso no momento da sentença | U56: Procedente | V56: Art. 33 | W56: NA | X56: Sim. Quantidade | Y56: 6a | Z56: Não | AA56: Não | AB56: Não | AC56: Não | AD56: 6a | AE56: NA | AF56: NA | AG56: 6a | AH56: NA | AI56: Fechado
A57: 00657223520178260050 | B57: 19/09/2017 | C57: Wendell Lopes Barbosa de Souza | D57: 13ª Vara Criminal | E57: LUCAS SEVERINO DE SOUZA | F57: Via Pública | G57: Masculino | H57: 34828 | I57: Branca | J57: Não disponível | K57: Veículo | L57: 2 tijolos. 1625,9 g | M57: 0 | N57: 0 | O57: 0 | P57: 0 | Q57: 0 | R57: Art. 33 | S57: Não | T57: Preso no momento da sentença. Confissão informal | U57: Procedente | V57: Art. 33 | W57: NA | X57: Sim. Quantidade | Y57: 6a | Z57: Não | AA57: Não | AB57: Não | AC57: Não | AD57: 6a | AE57: NA | AF57: NA | AG57: 6a | AH57: NA | AI57: Fechado
A58: 00055277520178260635 | B58: 12/09/2017 | C58: José Roberto Cabral Longaretti | D58: 13ª Vara Criminal | E58: CLAUDIO WASHINGTON MENDES DA SILVA | F58: Residência | G58: Masculino | H58: 33769 | I58: Preta | J58: Outros | K58: Celular. Dinheiro R$ 15000,00 | L58: 0 | M58: 0 | N58: 65 pacotes. 3334,6 g | O58: 0 | P58: 0 | Q58: 0 | R58: Art. 33 | S58: Art. 333 CP | T58: Confissão informal. Preso no momento da sentença | U58: Parcialmente procedente | V58: Art. 33 | W58: Não | X58: Sim. Quantidade | Y58: 8a | Z58: Reincidência | AA58: Não | AB58: Adolescente. Arma de fogo | AC58: Não cabimento | AD58: 11a 2m 12d | AE58: NA | AF58: NA | AG58: 11a 2m 12d | AH58: NA | AI58: Fechado
A59: 00828861320178260050 | B59: 31/10/2017 | C59: José Roberto Cabral Longaretti | D59: 13ª Vara Criminal | E59: BRUNO DOS SANTOS SILVA | F59: Via Pública | G59: Masculino | H59: 35526 | I59: Preta | J59: Não disponível | K59: Dinheiro R$ 20,00 | L59: 0 | M59: 22 sacos. 11,1 g | N59: 0 | O59: 0 | P59: 0 | Q59: 0 | R59: Art. 33 | S59: Não | T59: Atitude suspeita. Local de tráfico. Denúncia. Preso no momento da sentença | U59: Desclassificação | V59: Art. 28 | W59: NA | X59: NA | Y59: NA | Z59: NA | AA59: NA | AB59: NA | AC59: NA | AD59: NA | AE59: Não | AF59: NA | AG59: NA | AH59: NA | AI59: NA
A60: 00001815520178260050 | B60: 15/03/2017 | C60: José Roberto Cabral Longaretti | D60: 13ª Vara Criminal | E60: ANDERSON BARBOSA RODRIGUES | F60: Via Pública | G60: Masculino | H60: 29354 | I60: Parda | J60: Não disponível | K60: Simulacro de arma de fogo. Dinheiro R$ 40,00 | L60: 2 tijolos. 48,5 g | M60: 0 | N60: 0 | O60: 0 | P60: 0 | Q60: 0 | R60: Art. 33 | S60: Não | T60: Preso no momento da sentença. Local de tráfico | U60: Procedente | V60: Art. 33 | W60: NA | X60: Não | Y60: 5a | Z60: Reincidência | AA60: Não | AB60: Não | AC60: Não cabimento | AD60: 5a 10m | AE60: NA | AF60: NA | AG60: 5a 10m | AH60: NA | AI60: Fechado
A61: 00001815520178260050 | B61: 15/03/2017 | C61: José Roberto Cabral Longaretti | D61: 13ª Vara Criminal | E61: MAICON MARIO DA CUNHA | F61: Via Pública | G61: Masculino | H61: 31515 | I61: Parda | J61: Não disponível | K61: Dinheiro R$ 16,00 | L61: 17 porções. 20,9 g | M61: 0 | N61: 15 porções. 3,0 g | O61: 0 | P61: 0 | Q61: 0 | R61: Art. 33 | S61: Não | T61: Preso no momento da sentença. Local de tráfico | U61: Procedente | V61: Art. 33 | W61: NA | X61: Não | Y61: 5a | Z61: Reincidência | AA61: Não | AB61: Não | AC61: Não cabimento | AD61: 6a | AE61: NA | AF61: NA | AG61: 6a | AH61: NA | AI61: Fechado
A62: 00698682220178260050 | B62: 24/10/2017 | C62: Wendell Lopes Barbosa de Souza | D62: 13ª Vara Criminal | E62: JONATHAN CARDOSO | F62: Via Pública | G62: Masculino | H62: 32079 | I62: Branca | J62: Não disponível | K62: Dinheiro R$ 17,50 | L62: 13 porções. 39,3 g | M62: 42 porções. 27,4 g | N62: 0 | O62: 0 | P62: 0 | Q62: Lança-perfume. 4 frascos. 260 ml | R62: Art. 33 | S62: Não | T62: Preso no momento da sentença. Local de tráfico. Atitude suspeita | U62: Procedente | V62: Art. 33 | W62: NA | X62: Não | Y62: 5a | Z62: Reincidência | AA62: Não | AB62: Não | AC62: Não cabimento | AD62: 6a | AE62: NA | AF62: NA | AG62: 6a | AH62: NA | AI62: Fechado
A63: 01070345920158260050 | B63: 15/03/2017 | C63: José Roberto Cabral Longaretti | D63: 13ª Vara Criminal | E63: LUIZ RAFAEL IGNACZUK FRONZA | F63: Via Pública | G63: Masculino | H63: 32855 | I63: Branca | J63: Liso | K63: Nada | L63: 0 | M63: 0 | N63: 14 porções. 2,1 g | O63: 0 | P63: 0 | Q63: 0 | R63: Art. 33 | S63: Não | T63: Confissão informal | U63: Procedente | V63: Art. 33 | W63: NA | X63: Não | Y63: 5a | Z63: Não | AA63: Não | AB63: Não | AC63: Sim total | AD63: 1a 8m | AE63: NA | AF63: NA | AG63: 1a 8m | AH63: Sim | AI63: NA
A64: 00042996520178260635 | B64: 28/06/2017 | C64: Pedro Luiz Fernandes Nery Rafael | D64: 13ª Vara Criminal | E64: ANDRE KRISTMAN FARIA | F64: Residência | G64: Masculino | H64: 28439 | I64: Branca | J64: Não disponível | K64: Nada | L64: 8 tijolos. 674,4 g | M64: 0 | N64: 0 | O64: 29 comprimidos. 8,7 g | P64: 0 | Q64: Haxixe. 2 porções. 22,1 g | R64: Art. 33 | S64: Não | T64: Preso no momento da sentença. Denúncia anônima. Confissão informal | U64: Procedente | V64: Art. 33 | W64: NA | X64: Não | Y64: 5a | Z64: Reincidência | AA64: Não | AB64: Não | AC64: Não cabimento | AD64: 6a 8m | AE64: NA | AF64: NA | AG64: 6a 8m | AH64: NA | AI64: Fechado
A65: 00900047420168260050 | B65: 10/04/2017 | C65: Claudia Carneiro Calbucci Renaux | D65: 13ª Vara Criminal | E65: RODRIGO ANDRÉ MARTINS | F65: Via Pública | G65: Masculino | H65: 31837 | I65: Branca | J65: Liso | K65: Celular. Dinheiro R$ 30,00 | L65: 13 porções. 23,9 g | M65: 0 | N65: 0 | O65: 0 | P65: 0 | Q65: 0 | R65: Art. 33 | S65: Art. 329 CP | T65: Atitude suspeita | U65: Desclassificação | V65: Art. 28 | W65: Não | X65: NA | Y65: NA | Z65: NA | AA65: NA | AB65: NA | AC65: NA | AD65: NA | AE65: Não | AF65: NA | AG65: NA | AH65: NA | AI65: NA
A66: 00085755120178260050 | B66: 08/08/2017 | C66: VICENTE LUIZ ADUA | D66: 14ª Vara Criminal | E66: Ricardo Gomes dos Santos | F66: Via Pública | G66: Masculino | H66: 31416 | I66: Parda | J66: Não disponível | K66: Bolsa. Dinheiro R$ 25,0 | L66: 49 porções. 260,9 g | M66: 135 porções. 84,4 g | N66: 71 porções. 25,6 g | O66: 0 | P66: 0 | Q66: 0 | R66: Art. 33 | S66: Não | T66: Local de tráfico. Confissão informal. Preso no momento da sentença | U66: Procedente | V66: Art. 33 | W66: NA | X66: Sim. Natureza. Quantidade. Variedade | Y66: 6a 3m | Z66: Reincidência | AA66: Não | AB66: Não | AC66: Não cabimento | AD66: 7a 6m | AE66: NA | AF66: NA | AG66: 7a 6m | AH66: NA | AI66: Fechado
A67: 00101769220178260050 | B67: 21/03/2017 | C67: LEYLA MARIA DA SILVA LACAZ | D67: 14ª Vara Criminal | E67: KADRI GUNDUZ | F67: Via Pública | G67: Masculino | H67: 32801 | I67: Parda | J67: Encaracolado | K67: Veículo. Extrato. Passaporte. Envelope. Celular. Dinheiro U$ 2270,00. Dinheiro R$ 60,00 | L67: 0 | M67: 14 blocos. 14016,6 g | N67: 0 | O67: 0 | P67: 0 | Q67: 0 | R67: Art. 33. Art. 35 | S67: Não | T67: Nacionalidade. Preso no momento da sentença. Denúncia | U67: Parcialmente procedente | V67: Art. 33 | W67: NA | X67: Sim. Natureza. Quantidade | Y67: 8a | Z67: Não | AA67: Não | AB67: Não | AC67: Não | AD67: 8a | AE67: NA | AF67: NA | AG67: 8a | AH67: NA | AI67: Fechado
A68: 00064847620178260635 | B68: 19/10/2017 | C68: LEYLA MARIA DA SILVA LACAZ | D68: 14ª Vara Criminal | E68: ALEANDRO SANTOS DE MELO | F68: Via Pública | G68: Masculino | H68: 34042 | I68: Branca | J68: Encaracolado | K68: Veículo | L68: 44 porções. 150 g | M68: 0 | N68: 0 | O68: 0 | P68: 0 | Q68: 0 | R68: Art. 33 | S68: Não | T68: Confissão. Denúncia | U68: Procedente | V68: Art. 33 | W68: NA | X68: Não | Y68: 5a | Z68: Não | AA68: Não | AB68: Não | AC68: Sim total | AD68: 1a 8m | AE68: NA | AF68: NA | AG68: 1a 8m | AH68: Não | AI68: Aberto
A69: 00064847620178260635 | B69: 19/10/2017 | C69: LEYLA MARIA DA SILVA LACAZ | D69: 14ª Vara Criminal | E69: GILSON DE SOUZA MARTINS | F69: Via Pública | G69: Masculino | H69: 32828 | I69: Branca | J69: Liso | K69: Veículo | L69: 44 porções. 150 g | M69: 0 | N69: 0 | O69: 0 | P69: 0 | Q69: 0 | R69: Art. 33 | S69: Não | T69: Confissão. Denúncia | U69: Procedente | V69: Art. 33 | W69: NA | X69: Não | Y69: 5a | Z69: Não | AA69: Não | AB69: Não | AC69: Sim total | AD69: 1a 8m | AE69: NA | AF69: NA | AG69: 1a 8m | AH69: Não | AI69: Aberto
A70: 00727014720168260050 | B70: 02/10/2017 | C70: Marcela Dias De Abreu Pinto Coelho | D70: 14ª Vara Criminal | E70: CLAUDEMIR BISPO | F70: Via Pública | G70: Masculino | H70: 30725 | I70: Preta | J70: Não disponível | K70: Nada | L70: 0 | M70: 0 | N70: 0 | O70: 0 | P70: 0 | Q70: 0 | R70: Art. 33. Art. 35 | S70: Não | T70: Preso no momento da sentença. Denúncia anônima | U70: Absolvição | V70: NA | W70: NA | X70: NA | Y70: NA | Z70: NA | AA70: NA | AB70: NA | AC70: NA | AD70: NA | AE70: NA | AF70: NA | AG70: NA | AH70: NA | AI70: NA
A71: 00727014720168260050 | B71: 02/10/2017 | C71: Marcela Dias De Abreu Pinto Coelho | D71: 14ª Vara Criminal | E71: REINALDO MOURA PERES DA SILVA | F71: Via Pública | G71: Masculino | H71: 22780 | I71: Branca | J71: Não disponível | K71: Veículo. Papéis. Celular. Dinheiro R$ 80,00 | L71: 0 | M71: 20 tijolos. 19488 g | N71: 0 | O71: 0 | P71: 0 | Q71: 0 | R71: Art. 33. Art. 35 | S71: Não | T71: Confissão informal. Denúncia anônima | U71: Parcialmente procedente | V71: Art. 33 | W71: NA | X71: Sim. Natureza. Quantidade. Variedade | Y71: 5a 7m 15d | Z71: Não | AA71: Não | AB71: Interestadual | AC71: Não | AD71: 6a 6m 22d | AE71: NA | AF71: NA | AG71: 6a 6m 22d | AH71: NA | AI71: Fechado
A72: 00009965220178260050 | B72: 07/04/2017 | C72: LEYLA MARIA DA SILVA LACAZ | D72: 14ª Vara Criminal | E72: DIEGO PHELIPE DE OLIVEIRA | F72: Via Pública | G72: Masculino | H72: 33778 | I72: Parda | J72: Não disponível | K72: Nada | L72: 99 porções. 263 g | M72: 66 porções. 64,6 g | N72: 0 | O72: 0 | P72: 0 | Q72: 0 | R72: Art. 33 | S72: Não | T72: Local de tráfico. Preso no momento da sentença | U72: Procedente | V72: Art. 33 | W72: NA | X72: Sim. Antecedentes. Quantidade | Y72: 7a | Z72: Não | AA72: Não | AB72: Não | AC72: Não cabimento | AD72: 7a | AE72: NA | AF72: NA | AG72: 7a | AH72: NA | AI72: Fechado
A73: 00033288920178260050 | B73: 15/05/2017 | C73: ANA CAROLINA MUNHOZ DE ALMEIDA | D73: 14ª Vara Criminal | E73: ANDRE LUIS SOUSA NOVAES | F73: Residência | G73: Masculino | H73: 29627 | I73: Parda | J73: Liso | K73: Nada | L73: 4750 porções. 11293 g | M73: 2298 porções. 2051 g | N73: 896 porções. 273,67 g | O73: 0 | P73: 0 | Q73: 0 | R73: Art. 33 | S73: Não | T73: Confissão informal. Preso no momento da sentença. Denúncia anônima | U73: Procedente | V73: Art. 33 | W73: NA | X73: Sim. Natureza. Quantidade | Y73: 7a 6m | Z73: Não | AA73: Não | AB73: Não | AC73: Não | AD73: 7a 6m | AE73: NA | AF73: NA | AG73: 7a 6m | AH73: NA | AI73: Fechado
A74: 00289215720168260050 | B74: 16/01/2017 | C74: VICENTE LUIZ ADUA | D74: 14ª Vara Criminal | E74: ADEMILTON SILVA DOS SANTOS | F74: Via Pública | G74: Masculino | H74: 35247 | I74: Parda | J74: Ondulado | K74: Celular. Dinheiro R$ 10,00 | L74: 18 porções. 31,4 g | M74: 0 | N74: 10 porções. 2,5 g | O74: 0 | P74: 0 | Q74: 0 | R74: Art. 33 | S74: Não | T74: Local de tráfico. Confissão informal. Atitude suspeita | U74: Procedente | V74: Art. 33 | W74: NA | X74: Não | Y74: 5a | Z74: Não | AA74: Não | AB74: Estabelecimento | AC74: Não | AD74: 5a 10m | AE74: NA | AF74: NA | AG74: 5a 10m | AH74: NA | AI74: Fechado
A75: 00289215720168260050 | B75: 16/01/2017 | C75: VICENTE LUIZ ADUA | D75: 14ª Vara Criminal | E75: CAROLINE DIAS DA SILVA | F75: Via Pública | G75: Feminino | H75: 33792 | I75: Parda | J75: Carapinha | K75: Celular. Dinheiro R$ 10,00 | L75: 18 porções. 31,4 g | M75: 0 | N75: 10 porções. 2,5 g | O75: 0 | P75: 0 | Q75: 0 | R75: Art. 33 | S75: Não | T75: Local de tráfico. Confissão informal. Atitude suspeita | U75: Procedente | V75: Art. 33 | W75: NA | X75: Sim. Personalidade | Y75: 6a | Z75: Reincidência | AA75: Não | AB75: Estabelecimento | AC75: Não cabimento | AD75: 8a 4m 24d | AE75: NA | AF75: NA | AG75: 8a 4m 24d | AH75: NA | AI75: Fechado
A76: 00028472020178260635 | B76: 05/09/2017 | C76: LEYLA MARIA DA SILVA LACAZ | D76: 14ª Vara Criminal | E76: DOUGLAS CARDOSO DA SILVA | F76: Via Pública | G76: Masculino | H76: 33014 | I76: Preta | J76: Carapinha | K76: Estojo. CD player. Celular. Dinheiro R$ 1200,00 | L76: 0 | M76: 26 porções. 5,6 g | N76: 0 | O76: 0 | P76: 0 | Q76: 0 | R76: Art. 33 | S76: Não | T76: Preso no momento da sentença. Confissão informal. Local de tráfico | U76: Procedente | V76: Art. 33 | W76: NA | X76: Sim. Circunstâncias. Quantidade | Y76: 5a 6m | Z76: Não | AA76: Não | AB76: Não | AC76: Não cabimento | AD76: 5a 6m | AE76: NA | AF76: NA | AG76: 5a 6m | AH76: NA | AI76: Fechado
A77: 00757489220178260050 | B77: 11/10/2017 | C77: VICENTE LUIZ ADUA | D77: 14ª Vara Criminal | E77: Maria do Carmo Pereira de Lima | F77: Via Pública | G77: Feminino | H77: 31178 | I77: Parda | J77: Encaracolado | K77: Nada | L77: 13 porções. 71,6 g | M77: 15 porções. 6 g | N77: 0 | O77: 0 | P77: 0 | Q77: 0 | R77: Art. 33 | S77: Não | T77: Preso no momento da sentença | U77: Procedente | V77: Art. 33 | W77: NA | X77: Não | Y77: 5a | Z77: Não | AA77: Não | AB77: Não | AC77: Não | AD77: 5a | AE77: NA | AF77: NA | AG77: 5a | AH77: NA | AI77: Fechado
A78: 00558899020178260050 | B78: 17/10/2017 | C78: VICENTE LUIZ ADUA | D78: 14ª Vara Criminal | E78: Marcondes Batista de Moraes Junior | F78: Via Pública | G78: Masculino | H78: 35947 | I78: Branca | J78: Carapinha | K78: Celular. Dinheiro R$ 46,00 | L78: 60 porções. 41,6 g | M78: 87 porções. 99,6 g | N78: 0 | O78: 0 | P78: 0 | Q78: 0 | R78: Art. 33 | S78: Não | T78: Local de tráfico. Confissão informal | U78: Procedente | V78: Art. 33 | W78: NA | X78: Sim. Natureza. Quantidade. Variedade | Y78: 6a | Z78: Não | AA78: Confissão. Menoridade | AB78: Não | AC78: Não | AD78: 5a | AE78: NA | AF78: NA | AG78: 5a | AH78: NA | AI78: Fechado
A79: 01009336920168260050 | B79: 16/05/2017 | C79: Izabel Irlanda Castro Correia Araújo | D79: 15ª Vara Criminal | E79: PATRICIA AIRES DOS SANTOS | F79: Via Pública | G79: Feminino | H79: 31363 | I79: Branca | J79: Liso | K79: Dinheiro R$ 24,00 | L79: 0 | M79: 8 porções. 12,4 g | N79: 0 | O79: 0 | P79: 0 | Q79: 0 | R79: Art. 33 | S79: Não | T79: Preso no momento da sentença | U79: Desclassificação | V79: Art. 28 | W79: NA | X79: NA | Y79: NA | Z79: NA | AA79: NA | AB79: NA | AC79: NA | AD79: NA | AE79: Não | AF79: NA | AG79: NA | AH79: NA | AI79: NA
A80: 00552870220178260050 | B80: 30/10/2017 | C80: Izabel Irlanda Castro Correia Araújo | D80: 15ª Vara Criminal | E80: ERIK LUCAS SANTOS NOGUEIRA DE OLIVEIRA | F80: Via Pública | G80: Masculino | H80: 29831 | I80: Parda | J80: Encaracolado | K80: Veículo. Caixas de sabão em pó. Celular | L80: 0 | M80: 20 tijolos. 21500 g | N80: 0 | O80: 0 | P80: 0 | Q80: 0 | R80: Art. 33 | S80: Não | T80: Preso no momento da sentença. Denúncia anônima | U80: Procedente | V80: Art. 33 | W80: NA | X80: Sim. Conduta. Quantidade | Y80: 8a 6m | Z80: Não | AA80: Não | AB80: Não | AC80: Não | AD80: 8a 6m | AE80: NA | AF80: NA | AG80: 8a 6m | AH80: NA | AI80: Fechado
A81: 00533107220178260050 | B81: 22/11/2017 | C81: Celina Maria Macedo Stern | D81: 15ª Vara Criminal | E81: RONALD ROGER GRIFO | F81: Via Pública | G81: Masculino | H81: 32372 | I81: Branca | J81: Encaracolado | K81: Estojo. Dinheiro R$ 17,00 | L81: 60 porções. 116,1 g | M81: 14 porções. 7,7 g | N81: 100 porções. 12,6 g | O81: 0 | P81: 0 | Q81: 0 | R81: Art. 33 | S81: Art. 244-B ECA | T81: Preso no momento da sentença. Local de tráfico. Atitude suspeita | U81: Parcialmente procedente | V81: Art. 33 | W81: Não | X81: Sim. Natureza. Quantidade | Y81: 6a | Z81: Reincidência | AA81: Não | AB81: Adolescente | AC81: Não cabimento | AD81: 8a 2m | AE81: NA | AF81: NA | AG81: 8a 2m | AH81: NA | AI81: Fechado
A82: 00443229620168260050 | B82: 20/04/2017 | C82: Izabel Irlanda Castro Correia Araújo | D82: 15ª Vara Criminal | E82: ALLAN BONGESTAB DVORKIN | F82: Via Pública | G82: Masculino | H82: 34694 | I82: Branca | J82: Não disponível | K82: Celular. Dinheiro R$ 90,00 | L82: 0 | M82: 11 porções. 26,5 g | N82: 0 | O82: 0 | P82: 0 | Q82: 0 | R82: Art. 33 | S82: Não | T82: Confissão informal. Local de tráfico. Atitude suspeita | U82: Desclassificação | V82: Art. 28 | W82: NA | X82: NA | Y82: NA | Z82: NA | AA82: NA | AB82: NA | AC82: NA | AD82: NA | AE82: Não | AF82: NA | AG82: NA | AH82: NA | AI82: NA
A83: 00065627020178260635 | B83: 23/11/2017 | C83: CRISTINA ESCHER | D83: 15ª Vara Criminal | E83: JORLEI FERNANDO DOS SANTOS SILVA | F83: Restaurante e afins | G83: Masculino | H83: 35376 | I83: Parda | J83: Liso | K83: Celular. Dinheiro R$ 20,00 | L83: 0 | M83: 8 porções. 5,4 g | N83: 0 | O83: 0 | P83: 0 | Q83: 0 | R83: Art. 33 | S83: Art. 307 CP | T83: Confissão informal | U83: Desclassificação | V83: Art. 28 | W83: Art. 308 CP | X83: NA | Y83: NA | Z83: NA | AA83: NA | AB83: NA | AC83: NA | AD83: NA | AE83: Não | AF83: 4m | AG83: 4m | AH83: Sim | AI83: NA
A84: 00036702820168260635 | B84: 16/02/2017 | C84: Izabel Irlanda Castro Correia Araújo | D84: 15ª Vara Criminal | E84: LINCON DIAS DE OLIVEIRA | F84: Via Pública | G84: Masculino | H84: 32904 | I84: Parda | J84: Carapinha | K84: Veículo. Celular. Dinheiro R$ 1571,80 | L84: 2 tijolos. 864,3 g | M84: 0 | N84: 0 | O84: 0 | P84: 0 | Q84: 0 | R84: Art. 33 | S84: Não | T84: Confissão informal. Atitude suspeita | U84: Procedente | V84: Art. 33 | W84: NA | X84: Sim. Quantidade | Y84: 6a 3m | Z84: Reincidência | AA84: Não | AB84: Não | AC84: Não cabimento | AD84: 8a 4m | AE84: NA | AF84: NA | AG84: 8a 4m | AH84: NA | AI84: Fechado
A85: 00634950920168260050 | B85: 42849 | C85: Marcos Alexandre Coelho Zilli | D85: 15ª Vara Criminal | E85: HARRISON DIEGO DOS SANTOS | F85: Via Pública | G85: Masculino | H85: 34241 | I85: Preta | J85: Não disponível | K85: Dinheiro R$ 5,00 | L85: 10 porções. 0,9 g | M85: 296 porções. 61,7 g | N85: 0 | O85: 0 | P85: 0 | Q85: 0 | R85: Art. 33 | S85: Não | T85: Local de tráfico | U85: Procedente | V85: Art. 33 | W85: NA | X85: Sim. Natureza. Quantidade | Y85: 5a 10m | Z85: Reincidência | AA85: Não | AB85: Não | AC85: Não | AD85: 6a 9m 20d | AE85: NA | AF85: NA | AG85: 6a 9m 20d | AH85: NA | AI85: Fechado
A86: 00480002220168260050 | B86: 07/04/2017 | C86: Marcos Alexandre Coelho Zilli | D86: 15ª Vara Criminal | E86: JUDITE MACHIANE | F86: Terminal/Estação | G86: Feminino | H86: 27765 | I86: Preta | J86: Encaracolado | K86: Documentos. Ferramentas. Notebook. Estile. Necessaire. Itens de papelaria. Bicarbonato de sódio. Celular. Tecido. Chaves. Dinheiro R$443,00. Dinheiro U$ 200,00 | L86: 0 | M86: 20 porções. 3609,2 g | N86: 0 | O86: 0 | P86: 0 | Q86: 0 | R86: Art. 33. Art. 35 | S86: Não | T86: Nacionalidade. Confissão. Preso no momento da sentença. Denúncia anônima | U86: Parcialmente procedente | V86: Art. 33 | W86: NA | X86: Sim. Natureza. Quantidade | Y86: 6a 8m | Z86: Não | AA86: Confissão | AB86: Interestadual | AC86: Não | AD86: 6a 5m 23d | AE86: NA | AF86: NA | AG86: 6a 5m 23d | AH86: NA | AI86: Fechado
A87: 00480002220168260050 | B87: 07/04/2017 | C87: Marcos Alexandre Coelho Zilli | D87: 15ª Vara Criminal | E87: PETER LOUID OKEKE | F87: Terminal/Estação | G87: Masculino | H87: 27590 | I87: Preta | J87: Carapinha | K87: Documentos. Ferramentas. Notebook. Estile. Necessaire. Itens de papelaria. Bicarbonato de sódio. Celular. Tecido. Chaves. Dinheiro R$443,00. Dinheiro U$ 200,00 | L87: 0 | M87: 20 porções. 3609,2 g | N87: 0 | O87: 0 | P87: 0 | Q87: 0 | R87: Art. 33. Art. 35 | S87: Não | T87: Nacionalidade. Preso no momento da sentença. Denúncia anônima | U87: Parcialmente procedente | V87: Art. 33 | W87: NA | X87: Sim. Natureza. Quantidade | Y87: 6a 8m | Z87: Não | AA87: Confissão | AB87: Interestadual | AC87: Não | AD87: 7a 9m 10d | AE87: NA | AF87: NA | AG87: 7a 9m 10d | AH87: NA | AI87: Fechado
A88: 00092348520168260635 | B88: 42913 | C88: Maria Domitila Prado Manssur | D88: 16ª Vara Criminal | E88: MARCELO BARBOSA DA SILVA | F88: Via Pública | G88: Masculino | H88: 34342 | I88: Branca | J88: Não disponível | K88: Rádio transmissor | L88: 25 porções. 23,50 g | M88: 2180 porções. 1061 g | N88: 0 | O88: 0 | P88: 0 | Q88: 0 | R88: Art. 33. Art. 35 | S88: Não | T88: Denúncia anônima. Atitude suspeita. Preso no momento da sentença. Local de tráfico. Confissao informal. Confissão | U88: Procedente | V88: Art. 33. Art. 35 | W88: NA | X88: Não | Y88: 5a | Z88: Não | AA88: Não | AB88: Não | AC88: Não | AD88: 5a | AE88: 3a | AF88: NA | AG88: 8a | AH88: NA | AI88: Fechado
A89: 00092348520168260635 | B89: 42913 | C89: Maria Domitila Prado Manssur | D89: 16ª Vara Criminal | E89: ITALO PEREIRA PINHEIRO | F89: Via Pública | G89: Masculino | H89: 35563 | I89: Branca | J89: Não disponível | K89: Papéis | L89: 25 porções. 23,50 g | M89: 2180 porções. 1061 g | N89: 0 | O89: 0 | P89: 0 | Q89: 0 | R89: Art. 33. Art. 35 | S89: Não | T89: Preso no momento da sentença. Confissão informal | U89: Procedente | V89: Art. 33. Art. 35 | W89: NA | X89: Não | Y89: 5a | Z89: Não | AA89: Não | AB89: Não | AC89: Não | AD89: 5a | AE89: 3a | AF89: NA | AG89: 8a | AH89: NA | AI89: Fechado
A90: 00107158320168260635 | B90: 42878 | C90: Maria Domitila Prado Manssur | D90: 16ª Vara Criminal | E90: WELLINGTON DE PAULA JORGE | F90: Via Pública | G90: Masculino | H90: 28902 | I90: Preta | J90: Carapinha | K90: Papéis. Dinheiro R$ 44,00 | L90: 10 porções. 17,7 g | M90: 11 porções. 10,4 g | N90: 56 porções. 49,7 g | O90: 0 | P90: 0 | Q90: 0 | R90: Art. 33 | S90: Não | T90: Denúncia anônima. Preso no momento da sentença. Confissao informal | U90: Procedente | V90: Art. 33 | W90: NA | X90: Não | Y90: 5a | Z90: Reincidência | AA90: Não | AB90: Não | AC90: Não cabimento | AD90: 5a 10m | AE90: NA | AF90: NA | AG90: 5a 10m | AH90: NA | AI90: Fechado
A91: 00292905120168260050 | B91: 43017 | C91: Edison Tetsuzo Namba | D91: 16ª Vara Criminal | E91: MARILENE PINHEIRO DA ROCHA | F91: Repartição Pública | G91: Feminino | H91: 25190 | I91: Branca | J91: Liso | K91: Chinelo | L91: 1 porção. 25,2 g | M91: 0 | N91: 18 porções. 7 g | O91: 0 | P91: 0 | Q91: 0 | R91: Art. 33. Art. 35 | S91: Não | T91: Revista Vexatória. Confissão informal | U91: Parcialmente Procedente | V91: Art. 33 | W91: NA | X91: Não | Y91: 5a | Z91: Não | AA91: Não | AB91: Estabelecimento | AC91: Sim total | AD91: 1a 11m 10d | AE91: NA | AF91: NA | AG91: 1a 11m 10d | AH91: Sim | AI91: NA
A92: 00292905120168260050 | B92: 43017 | C92: Edison Tetsuzo Namba | D92: 16ª Vara Criminal | E92: EVERALDO SOUSA FONTES | F92: Repartição Pública | G92: Masculino | H92: Não disponível. 41 anos (TJ) | I92: Branca | J92: Não disponível | K92: Nada | L92: 1 porção. 25,2 g | M92: 0 | N92: 18 porções. 7 g | O92: 0 | P92: 0 | Q92: 0 | R92: Art. 33. Art. 35 | S92: Não | T92: Não há | U92: Desclassificação | V92: Art. 28 | W92: NA | X92: NA | Y92: NA | Z92: NA | AA92: NA | AB92: NA | AC92: NA | AD92: NA | AE92: Não | AF92: NA | AG92: NA | AH92: NA | AI92: NA
A93: 00976541220158260050 | B93: 43040 | C93: Maria Domitila Prado Manssur | D93: 16ª Vara Criminal | E93: JOHNNY GOMES DOS SANTOS | F93: Via Pública | G93: Masculino | H93: 35018 | I93: Parda | J93: Outros | K93: Papel. Dinheiro R$ 35,00 | L93: 32 porções. 57,1 g | M93: 16 porções. 13,7 g | N93: 23 porções. 3,3 g | O93: 0 | P93: 0 | Q93: 0 | R93: Art. 33 | S93: Não | T93: Atitude suspeita | U93: Absolvição | V93: NA | W93: NA | X93: NA | Y93: NA | Z93: NA | AA93: NA | AB93: NA | AC93: NA | AD93: NA | AE93: NA | AF93: NA | AG93: NA | AH93: NA | AI93: NA
A94: 00042827220168260050 | B94: 42801 | C94: Ana Lucia Fernandes Queiroga | D94: 16ª Vara Criminal | E94: MARCOS VINICIUS SOUZA ALEXANDRE | F94: Via Pública | G94: Masculino | H94: 35359 | I94: Preta | J94: Carapinha | K94: Bolsa | L94: 12 porções. 13,80 g | M94: 17 porções. 8,2 g | N94: 0 | O94: 0 | P94: 0 | Q94: 0 | R94: Art. 33 | S94: Não | T94: Denúncia anônima. Local de tráfico. Preso no momento da sentença | U94: Procedente | V94: Art. 33 | W94: NA | X94: Não | Y94: 5a | Z94: Não | AA94: Não | AB94: Não | AC94: Não | AD94: 5a | AE94: NA | AF94: NA | AG94: 5a | AH94: NA | AI94: Fechado
A95: 00120876720168260635 | B95: 42907 | C95: Ana Lucia Fernandes Queiroga | D95: 16ª Vara Criminal | E95: MARCUS VINICIUS GOMES DE SOUZA | F95: Residência | G95: Masculino | H95: 34355 | I95: Parda | J95: Não disponível | K95: Mochila. Moto. Cartuchos. Papéis | L95: 97,3 g | M95: 1150,2 g | N95: 170,6 g | O95: 0 | P95: 0 | Q95: 0 | R95: Art. 33. Art. 35 | S95: Art. 16 L10826. Art. 244-B ECA. Art. 329 CP | T95: Confissão informal | U95: Parcialmente procedente | V95: Art. 33 | W95: Art. 16 L10826. Art. 329 CP | X95: Sim. Conduta. Quantidade | Y95: 6a | Z95: Reincidência | AA95: Confissão | AB95: Não | AC95: Não | AD95: 6a 6m | AE95: NA | AF95: 4a 3m | AG95: 10a 9m | AH95: NA | AI95: Fechado
A96: 00065092620168260635 | B96: 42800 | C96: Ana Lucia Fernandes Queiroga | D96: 16ª Vara Criminal | E96: GUILHERME HENRIQUE TEOFILO DA SILVA | F96: Via Pública | G96: Masculino | H96: 34301 | I96: Preta | J96: Carapinha | K96: Sacola. Dinheiro R$ 85,00 | L96: 102,3 g | M96: 26,1 g | N96: 6,4 g | O96: 0 | P96: 0 | Q96: Lança-perfume. 8 frascos. 136 ml | R96: Art. 33 | S96: Não | T96: Local de tráfico. Denúncia anônima. Preso no momento da sentença. Confissão informal | U96: Procedente | V96: Art. 33 | W96: NA | X96: Não | Y96: 5a | Z96: Reincidência | AA96: Não | AB96: Não | AC96: Não cabimento | AD96: 6a | AE96: NA | AF96: NA | AG96: 6a | AH96: NA | AI96: Fechado
A97: 00557602220168260050 | B97: 42769 | C97: Ana Lucia Fernandes Queiroga | D97: 16ª Vara Criminal | E97: ALEXANDRE SANTANA CONCEICAO | F97: Via Pública | G97: Masculino | H97: 35082 | I97: Parda | J97: Não disponível | K97: Cigarro | L97: 0 | M97: 0 | N97: 19 potções. 3,8 g | O97: 0 | P97: 0 | Q97: 0 | R97: Art. 33 | S97: Não | T97: Denáncia anônima. Atitude suspeita. Preso no momento da sentença. Confissão informal | U97: Procedente | V97: Art. 33 | W97: NA | X97: Sim. Antecedentes. Conduta. Personalidade | Y97: 5a 6m | Z97: Não | AA97: Confissão | AB97: Não | AC97: Não | AD97: 5a | AE97: NA | AF97: NA | AG97: 5a | AH97: NA | AI97: Fechado
A98: 00493140320168260050 | B98: 42758 | C98: Ana Lucia Fernandes Queiroga | D98: 16ª Vara Criminal | E98: MARCOS PAULO DIAS VICENTE | F98: Via Pública | G98: Masculino | H98: 33875 | I98: Parda | J98: Não disponível | K98: Celular. Dinheiro R$ 25,00 | L98: 2900,5g | M98: 0 | N98: 0 | O98: 0 | P98: 0 | Q98: 0 | R98: Art. 33 | S98: Não | T98: Atitude suspeita. Preso no momento da sentença | U98: Procedente | V98: Art. 33 | W98: NA | X98: Sim. Antecedentes. Conduta. Personalidade | Y98: 5a 6m | Z98: Não | AA98: Não | AB98: Não | AC98: Não | AD98: 5a 6m | AE98: NA | AF98: NA | AG98: 5a 6m | AH98: NA | AI98: Fechado
A99: 00872185720168260050 | B99: 43013 | C99: Maria Domitila Prado Manssur | D99: 16ª Vara Criminal | E99: DANILO PEREIRA DA SILVA | F99: Via Pública | G99: Masculino | H99: 34746 | I99: Parda | J99: Não disponível | K99: Nada | L99: 4,5 g | M99: 10,1 g | N99: 0 | O99: 0 | P99: 0 | Q99: 0 | R99: Art. 33 | S99: Não | T99: Denúncia. Confissão informal. Preso no momento da sentença | U99: Procedente | V99: Art. 33 | W99: NA | X99: Não | Y99: 5a | Z99: Não | AA99: Não | AB99: Não | AC99: Não cabimento | AD99: 5a | AE99: NA | AF99: NA | AG99: 5a | AH99: NA | AI99: Fechado
A100: 00085592520168260635 | B100: 42958 | C100: Maria Domitila Prado Manssur | D100: 16ª Vara Criminal | E100: ANDRIS ZIVERTS | F100: Via Pública | G100: Masculino | H100: 30548 | I100: Branca | J100: Liso | K100: Cartão bancário. Cadeado. Celular. Chaves. Dinheiro $100,00. Dinheiro R$ 50,00 | L100: 0 | M100: 31 porções. 2464,8 g | N100: 0 | O100: 0 | P100: 0 | Q100: 0 | R100: Art. 33. Art. 35 | S100: Não | T100: Nacionalidade. Denúncia anônima. Preso no momento da sentença | U100: Procedente | V100: Art. 33. Art. 35 | W100: NA | X100: Não | Y100: 5a | Z100: Não | AA100: Não | AB100: Não | AC100: Não | AD100: 5a | AE100: 3a | AF100: NA | AG100: 8a | AH100: NA | AI100: Fechado
...

Sheet TJSP - Apenas p Complementação
A1: NUM_PROCESSO | B1: NME_FORO | C1: NME_VARA | D1: NME_REU | E1: IDADE_REU | F1: TPO_GENERO | G1: DSC_COR
A2: 00003703320178260050 | B2: Foro Central Criminal Barra Funda | C2: 1ª Vara Criminal | D2: PATRICK DE CAMPOS SAPRAGONES CANO | E2: 18 | F2: M | G2: Pardo
A3: 00006579320178260050 | B3: Foro Central Criminal Barra Funda | C3: 1ª Vara Criminal | D3: ALEXANDRE RODRIGUES | E3: 0 | F3: M | G3: Branco
A4: 00007825220178260635 | B4: Foro Central Criminal Barra Funda | C4: 1ª Vara Criminal | D4: ADRIANO ROGERIO RIBEIRO | E4: 19 | F4: M | G4: Preto
A5: 00009201920178260635 | B5: Foro Central Criminal Barra Funda | C5: 1ª Vara Criminal | D5: DILEIA OLIVEIRA DA SILVA | E5: 35 | F5: F | G5: Pardo
A6: 00009201920178260635 | B6: Foro Central Criminal Barra Funda | C6: 1ª Vara Criminal | D6: LUIZ FELIPE DE MIRANDA SANTOS | E6: 23 | F6: M | G6: Pardo
A7: 00011299420178260050 | B7: Foro Central Criminal Barra Funda | C7: 1ª Vara Criminal | D7: FERNANDO RIBEIRO CREMASCO | E7: 42 | F7: M | G7: Branco
A8: 00011299420178260050 | B8: Foro Central Criminal Barra Funda | C8: 1ª Vara Criminal | D8: JURANDIR JEREMIAS | E8: 41 | F8: M | G8: Pardo
A9: 00011470920178260635 | B9: Foro Central Criminal Barra Funda | C9: 1ª Vara Criminal | D9: MAURICIO DA SILVA MORAIS (Matrícula SAP 354340-2) | E9: 31 | F9: M | G9: Pardo
A10: 00011470920178260635 | B10: Foro Central Criminal Barra Funda | C10: 1ª Vara Criminal | D10: ROBSON LUIZ DOS SANTOS | E10: 26 | F10: M | G10: Pardo
A11: 00011647920168260635 | B11: Foro Central Criminal Barra Funda | C11: 1ª Vara Criminal | D11: VAGNER FELIX DO NASCIMENTO | E11: 24 | F11: M | G11: NULL
A12: 00011647920168260635 | B12: Foro Central Criminal Barra Funda | C12: 1ª Vara Criminal | D12: KAIQUE HUMBERTO DA SILVA | E12: 20 | F12: M | G12: NULL
A13: 00012632420178260050 | B13: Foro Central Criminal Barra Funda | C13: 1ª Vara Criminal | D13: JOSE BEZERRA DA SILVA | E13: 31 | F13: M | G13: Pardo
... A63: 00315544120168260050 | B63: Foro Central Criminal Barra Funda | C63: 1ª Vara Criminal | D63: klaus dos santos souza | E63: 29 | F63: M | G63: NULL
A64: 00330614720108260050 | B64: Foro Central Criminal Barra Funda | C64: 1ª Vara Criminal | D64: SONIA APARECIDA ROSSI | E64: NULL | F64: F | G64: NULL
A65: 00330614720108260050 | B65: Foro Central Criminal Barra Funda | C65: 1ª Vara Criminal | D65: Sidney da Silva Moreira | E65: NULL | F65: M | G65: Branco
A66: 00330614720108260050 | B66: Foro Central Criminal Barra Funda | C66: 1ª Vara Criminal | D66: RENATO ALEXANDRE JUNIOR | E66: NULL | F66: M | G66: NULL
A67: 00330614720108260050 | B67: Foro Central Criminal Barra Funda | C67: 1ª Vara Criminal | D67: VANDO FRANCISCO SCALEZE | E67: 34 | F67: M | G67: NULL
A68: 00330614720108260050 | B68: Foro Central Criminal Barra Funda | C68: 1ª Vara Criminal | D68: EDNEY FERREIRA MARQUES | E68: 30 | F68: M | G68: NULL
A69: 00330614720108260050 | B69: Foro Central Criminal Barra Funda | C69: 1ª Vara Criminal | D69: FERNANDO OLIVEIRA DAS NEVES | E69: 33 | F69: M | G69: Pardo
A70: 00330614720108260050 | B70: Foro Central Criminal Barra Funda | C70: 1ª Vara Criminal | D70: RODRIGO UBIRAJARA DE GOUVEA | E70: NULL | F70: M | G70: NULL
A71: 00330614720108260050 | B71: Foro Central Criminal Barra Funda | C71: 1ª Vara Criminal | D71: CLEBER PILLA DOS SANTOS | E71: NULL | F71: M | G71: NULL
A72: 00330614720108260050 | B72: Foro Central Criminal Barra Funda | C72: 1ª Vara Criminal | D72: RAFAEL CHAVES FRIAS | E72: 28 | F72: M | G72: NULL
A73: 00382047020178260050 | B73: Foro Central Criminal Barra Funda | C73: 1ª Vara Criminal | D73: CICERO DOS SANTOS SILVA | E73: 20 | F73: M | G73: Pardo
A74: 00385660920168260050 | B74: Foro Central Criminal Barra Funda | C74: 1ª Vara Criminal | D74: MARCOS PEDROSO DOS SANTOS | E74: 27 | F74: M | G74: Branco
A75: 00403765820128260050 | B75: Foro Central Criminal Barra Funda | C75: 1ª Vara Criminal | D75: JAILTON DOS SANTOS SOARES | E75: 32 | F75: M | G75: Pardo
A76: 00405254920158260050 | B76: Foro Central Criminal Barra Funda | C76: 1ª Vara Criminal | D76: TIAGO FERREIRA ALVES | E76: 26 | F76: M | G76: Pardo
A77: 00427942720168260050 | B77: Foro Central Criminal Barra Funda | C77: 1ª Vara Criminal | D77: anderson carlos gomes da silva | E77: 21 | F77: M | G77: NULL
A78: 00427942720168260050 | B78: Foro Central Criminal Barra Funda | C78: 1ª Vara Criminal | D78: rodrigo cordeiro da silva | E78: 34 | F78: M | G78: NULL
A79: 00433092820178260050 | B79: Foro Central Criminal Barra Funda | C79: 1ª Vara Criminal | D79: LUCIANO JOSE DA SILVA SANTOS | E79: 38 | F79: M | G79: Branco
A80: 00455414720168260050 | B80: Foro Central Criminal Barra Funda | C80: 1ª Vara Criminal | D80: CIRO DA ROCHA NUNES DOS SANTOS | E80: 25 | F80: M | G80: Branco
A81: 00460013420168260050 | B81: Foro Central Criminal Barra Funda | C81: 1ª Vara Criminal | D81: DONVANE SANTOS RIBEIRO | E81: 22 | F81: M | G81: Pardo
A82: 00471633020178260050 | B82: Foro Central Criminal Barra Funda | C82: 1ª Vara Criminal | D82: LEONARDO CARDOSO VIEIRA | E82: 31 | F82: M | G82: Branco
A83: 00471633020178260050 | B83: Foro Central Criminal Barra Funda | C83: 1ª Vara Criminal | D83: TATIANE BECKER DOS SANTOS | E83: 21 | F83: F | G83: Branco
... A202: 00522061620158260050 | B202: Foro Central Criminal Barra Funda | C202: 10ª Vara Criminal | D202: MARCOS ANTONIO GONCALVES DOS SANTOS | E202: 18 | F202: M | G202: Pardo
A203: 00532926120118260050 | B203: Foro Central Criminal Barra Funda | C203: 10ª Vara Criminal | D203: ANDRE RICARDO CARDOSO SANTANA | E203: NULL | F203: M | G203: NULL
A204: 00534374420168260050 | B204: Foro Central Criminal Barra Funda | C204: 10ª Vara Criminal | D204: ARNALDO ALVES CARDOSO | E204: 54 | F204: M | G204: Preto
A205: 00539637920148260050 | B205: Foro Central Criminal Barra Funda | C205: 10ª Vara Criminal | D205: Jefferson Ribeiro da Silva | E205: 25 | F205: M | G205: Branco
A206: 00550596120168260050 | B206: Foro Central Criminal Barra Funda | C206: 10ª Vara Criminal | D206: BRUNO APARECIDO MORAIS DE SA | E206: 22 | F206: M | G206: Branco
A207: 00557204020168260050 | B207: Foro Central Criminal Barra Funda | C207: 10ª Vara Criminal | D207: ERIK BATISTA FARIA | E207: 33 | F207: M | G207: Pardo
A208: 00570122620178260050 | B208: Foro Central Criminal Barra Funda | C208: 10ª Vara Criminal | D208: PAULO ROBERTO PROMECIA | E208: 36 | F208: M | G208: Branco
A209: 00585264820168260050 | B209: Foro Central Criminal Barra Funda | C209: 10ª Vara Criminal | D209: DOUGLAS NASCIMENTO LABOREDO | E209: 19 | F209: M | G209: Branco
A210: 00602577920168260050 | B210: Foro Central Criminal Barra Funda | C210: 10ª Vara Criminal | D210: RIOSO VILLARROEL VEIZAGA | E210: 25 | F210: M | G210: Branco
A211: 00608068920168260050 | B211: Foro Central Criminal Barra Funda | C211: 10ª Vara Criminal | D211: BRUNO ROSSATO DE SOUZA | E211: 20 | F211: M | G211: Pardo
A212: 00617932820168260050 | B212: Foro Central Criminal Barra Funda | C212: 10ª Vara Criminal | D212: THIAGO APARECIDO DA SILVA | E212: 26 | F212: M | G212: Pardo
A213: 00633781820168260050 | B213: Foro Central Criminal Barra Funda | C213: 10ª Vara Criminal | D213: EMERSON LUIZ DA SILVA PEREIRA | E213: 28 | F213: M | G213: Pardo
A214: 00649259320168260050 | B214: Foro Central Criminal Barra Funda | C214: 10ª Vara Criminal | D214: WYGOR GREGORIO DA SILVA | E214: 20 | F214: M | G214: Branco
A215: 00653814320168260050 | B215: Foro Central Criminal Barra Funda | C215: 10ª Vara Criminal | D215: ELIANE RODRIGUES PEREIRA DA SILVA (ou ELIANE RODRIGES MAIA) | E215: 37 | F215: F | G215: Pardo
... A287: 00438864020168260050 | B287: Foro Central Criminal Barra Funda | C287: 11ª Vara Criminal | D287: ALDEMIR DE OLIVEIRA | E287: 21 | F287: M | G287: Branco
A288: 00455080420098260050 | B288: Foro Central Criminal Barra Funda | C288: 11ª Vara Criminal | D288: Diego Ribeiro da Silva | E288: NULL | F288: M | G288: Branco
A289: 00455080420098260050 | B289: Foro Central Criminal Barra Funda | C289: 11ª Vara Criminal | D289: Fernando Pereira Lacerda | E289: NULL | F289: M | G289: Branco
A290: 00467979320148260050 | B290: Foro Central Criminal Barra Funda | C290: 11ª Vara Criminal | D290: CLEVTOM CARVALHO DA SILVA | E290: 27 | F290: M | G290: Branco
A291: 00475741020168260050 | B291: Foro Central Criminal Barra Funda | C291: 11ª Vara Criminal | D291: VERISSIMO OLIVEIRA DE SOUZA FILHO | E291: 29 | F291: M | G291: Pardo
A292: 00529801220168260050 | B292: Foro Central Criminal Barra Funda | C292: 11ª Vara Criminal | D292: DENISE RODRIGUES DE ARAUJO | E292: 49 | F292: F | G292: Branco
A293: 00562443720168260050 | B293: Foro Central Criminal Barra Funda | C293: 11ª Vara Criminal | D293: CARLOS ALBERTO MALANZUK | E293: 52 | F293: M | G293: Branco
A294: 00567700420168260050 | B294: Foro Central Criminal Barra Funda | C294: 11ª Vara Criminal | D294: ANDERSON ALBERTO DE OLIVEIRA | E294: 34 | F294: M | G294: Pardo
A295: 00573653720158260050 | B295: Foro Central Criminal Barra Funda | C295: 11ª Vara Criminal | D295: PAULO ROBERTO KIILER | E295: 29 | F295: M | G295: Branco
A296: 00579038120168260050 | B296: Foro Central Criminal Barra Funda | C296: 11ª Vara Criminal | D296: MAURICIO VIEIRA DE MACEDO | E296: 19 | F296: M | G296: Branco
A297: 00582952120168260050 | B297: Foro Central Criminal Barra Funda | C297: 11ª Vara Criminal | D297: RUTEMBERG DA SILVA | E297: 35 | F297: M | G297: Pardo
A298: 00603946120168260050 | B298: Foro Central Criminal Barra Funda | C298: 11ª Vara Criminal | D298: ANTONIO GERALDO DE SOUZA | E298: 55 | F298: M | G298: Branco
A299: 00607549320168260050 | B299: Foro Central Criminal Barra Funda | C299: 11ª Vara Criminal | D299: ADEMIR LAMEU DA SILVA | E299: 26 | F299: M | G299: Branco
A300: 00643687220178260050 | B300: Foro Central Criminal Barra Funda | C300: 11ª Vara Criminal | D300: BRUNA TOMAZ DA CONCEICAO | E300: 31 | F300: F | G300: Branco
A301: 00648384520138260050 | B301: Foro Central Criminal Barra Funda | C301: 11ª Vara Criminal | D301: JONATAN BRANDÃO MELO | E301: 19 | F301: M | G301: Pardo
... A341: 00993946820168260050 | B341: Foro Central Criminal Barra Funda | C341: 11ª Vara Criminal | D341: RODNEY DO NASCIMENTO LEITE | E341: 26 | F341: M | G341: Preto
A342: 01000207320058260050 | B342: Foro Central Criminal Barra Funda | C342: 11ª Vara Criminal | D342: Antonio Carlos Pinheiro | E342: NULL | F342: M | G342: Branco
A343: 01000207320058260050 | B343: Foro Central Criminal Barra Funda | C343: 11ª Vara Criminal | D343: Luis Choqueira Vargas | E343: NULL | F343: M | G343: Pardo
A344: 01000207320058260050 | B344: Foro Central Criminal Barra Funda | C344: 11ª Vara Criminal | D344: Juan Carlos Talamas | E344: NULL | F344: M | G344: Branco
A345: 01000207320058260050 | B345: Foro Central Criminal Barra Funda | C345: 11ª Vara Criminal | D345: José Antonio Cucolo | E345: NULL | F345: M | G345: Branco
A346: 01000207320058260050 | B346: Foro Central Criminal Barra Funda | C346: 11ª Vara Criminal | D346: Marcelo Arcanjo dos Santos | E346: NULL | F346: M | G346: Pardo
A347: 01008652220168260050 | B347: Foro Central Criminal Barra Funda | C347: 11ª Vara Criminal | D347: LEANDRO RODRIGUES DOS SANTOS PIRES | E347: 22 | F347: M | G347: Branco
A348: 01169952920128260050 | B348: Foro Central Criminal Barra Funda | C348: 11ª Vara Criminal | D348: DOUGLAS TEODORO DAVATZ | E348: -70 | F348: M | G348: Pardo
A349: 00004526420178260050 | B349: Foro Central Criminal Barra Funda | C349: 12ª Vara Criminal | D349: DANIEL DE FRANÇA SOUSA PEREIRA | E349: 27 | F349: M | G349: Branco
A350: 00005443320178260635 | B350: Foro Central Criminal Barra Funda | C350: 12ª Vara Criminal | D350: WILSON RODRIGUES DOS SANTOS | E350: 31 | F350: M | G350: Preto
A351: 00006561120178260050 | B351: Foro Central Criminal Barra Funda | C351: 12ª Vara Criminal | D351: ISAQUE SILVA COELHO | E351: 18 | F351: M | G351: Preto
A352: 00007002120178260635 | B352: Foro Central Criminal Barra Funda | C352: 12ª Vara Criminal | D352: RENAN LUIS DA SILVA | E352: 26 | F352: M | G352: Branco
A353: 00007002120178260635 | B353: Foro Central Criminal Barra Funda | C353: 12ª Vara Criminal | D353: BRUNO ROMANO MARQUES | E353: 30 | F353: M | G353: Branco
A354: 00012120420178260635 | B354: Foro Central Criminal Barra Funda | C354: 12ª Vara Criminal | D354: CLAYTON SOUZA SOARES | E354: 22 | F354: M | G354: Preto
A355: 00016433820178260635 | B355: Foro Central Criminal Barra Funda | C355: 12ª Vara Criminal | D355: ÁLVARO PINTO JUNIOR | E355: 53 | F355: M | G355: Branco
A356: 00016433820178260635 | B356: Foro Central Criminal Barra Funda | C356: 12ª Vara Criminal | D356: BRUNO MARCELINO TRINCI | E356: 31 | F356: M | G356: Branco
A357: 00016433820178260635 | B357: Foro Central Criminal Barra Funda | C357: 12ª Vara Criminal | D357: ALEXANDRE TITO AMÂNCIO | E357: 37 | F357: M | G357: Pardo
A358: 00034777620178260635 | B358: Foro Central Criminal Barra Funda | C358: 12ª Vara Criminal | D358: MARCIO ANTONIO TEODORO | E358: 25 | F358: M | G358: Pardo
... A376: 00110329119968260050 | B376: Foro Central Criminal Barra Funda | C376: 12ª Vara Criminal | D376: ROGERIO DA SILVA | E376: 47 | F376: M | G376: Branco
A377: 00110329119968260050 | B377: Foro Central Criminal Barra Funda | C377: 12ª Vara Criminal | D377: PAULO JOSE DA SILVA | E377: NULL | F377: M | G377: Branco
A378: 00119551020168260635 | B378: Foro Central Criminal Barra Funda | C378: 12ª Vara Criminal | D378: ROBSON DE MOURA SILVA | E378: 37 | F378: M | G378: Branco
A379: 00120937420168260635 | B379: Foro Central Criminal Barra Funda | C379: 12ª Vara Criminal | D379: LEANDRO MARTINS DOS SANTOS | E379: 25 | F379: M | G379: Pardo
A380: 00124072020168260635 | B380: Foro Central Criminal Barra Funda | C380: 12ª Vara Criminal | D380: RHAONY ANTONY DAMIÃO | E380: 18 | F380: M | G380: Pardo
A381: 00126359220168260635 | B381: Foro Central Criminal Barra Funda | C381: 12ª Vara Criminal | D381: DIEGO HENRIQUE CARLOS DA SILVA | E381: 19 | F381: M | G381: Branco
A382: 00127009620168260050 | B382: Foro Central Criminal Barra Funda | C382: 12ª Vara Criminal | D382: CLEBER CRISTIANO CORREA | E382: 39 | F382: M | G382: Pardo
A383: 00134283120168260635 | B383: Foro Central Criminal Barra Funda | C383: 12ª Vara Criminal | D383: ANTONIO OSMAR ALVES DA SILVA | E383: 28 | F383: M | G383: Pardo
A384: 00136498620178260050 | B384: Foro Central Criminal Barra Funda | C384: 12ª Vara Criminal | D384: DARIO OLIVEIRA SILVA JUNIOR | E384: 20 | F384: M | G384: Pardo
A385: 00148089820168260050 | B385: Foro Central Criminal Barra Funda | C385: 12ª Vara Criminal | D385: GABRIEL PITTA RIBEIRO | E385: 39 | F385: M | G385: Branco
A386: 00186225020188260050 | B386: Foro Central Criminal Barra Funda | C386: 12ª Vara Criminal | D386: JUCELI PORTO FEITOZA | E386: 42 | F386: F | G386: Pardo
A387: 00197053820178260050 | B387: Foro Central Criminal Barra Funda | C387: 12ª Vara Criminal | D387: GUILHERME NASCIMENTO DIOGO DE LIMA | E387: 19 | F387: M | G387: Pardo
A388: 00208994420158260050 | B388: Foro Central Criminal Barra Funda | C388: 12ª Vara Criminal | D388: YAGO WIRTHMANN STORNIOLI | E388: 22 | F388: M | G388: Branco
A389: 00220285020168260050 | B389: Foro Central Criminal Barra Funda | C389: 12ª Vara Criminal | D389: WILKER CAMARGO FERREIRA | E389: 27 | F389: M | G389: Pardo
... A496: 00085677420178260050 | B496: Foro Central Criminal Barra Funda | C496: 13ª Vara Criminal | D496: EDUARDO HENRIQUE MOREIRA | E496: 30 | F496: M | G496: Pardo
A497: 00085709319988260050 | B497: Foro Central Criminal Barra Funda | C497: 13ª Vara Criminal | D497: WILSON ALVES DA SILVA | E497: NULL | F497: M | G497: Branco
A498: 00086724220178260635 | B498: Foro Central Criminal Barra Funda | C498: 13ª Vara Criminal | D498: HELIO MACIEL BALDRAIA | E498: 20 | F498: M | G498: Pardo
A499: 00093341520178260050 | B499: Foro Central Criminal Barra Funda | C499: 13ª Vara Criminal | D499: RONIELE ALVES CUNHA | E499: 24 | F499: M | G499: Pardo
A500: 00095489420178260635 | B500: Foro Central Criminal Barra Funda | C500: 13ª Vara Criminal | D500: ALEXSANDRO SILVA DE SOUZA | E500: 21 | F500: M | G500: Pardo
...

Sheet BD
A1: ID | B1: Processo | C1: Processo (cont) | D1: DtDisp | E1: Juiz | F1: Sexo Juiz | G1: Vara | H1: Nome | I1: Nome (cont) | J1: Local | K1: Sexo | L1: DN | M1: Idade | N1: Cutis | O1: Cutis (agrup) | P1: Cabelo | Q1: Objetos | R1: Maconha | S1: Maconha (g) | T1: Cocaína | U1: Cocaína (g) | V1: Crack | W1: Crack (g) | X1: Ecstasy | Y1: Ecstasy (g) | Z1: LSD | AA1: LSD (g) | AB1: Outras | AC1: Anabolizantes | AD1: Anorexígenos | AE1: Haxixe | AF1: Skank | AG1: Lança-perfume | AH1: Tolueno | AI1: DenDrog | AJ1: DenOutros | AK1: Aspectos | AL1: Sentença | AM1: Sentença (agrup) | AN1: ResDrogas | AO1: ResOutros | AP1: AvalNegPB | AQ1: PenaBase | AR1: Agravantes33 | AS1: Agravantes33 (agrup) | AT1: Atenuantes33 | AU1: Confissão | AV1: Menoridade | AW1: Nenhum | AX1: NA | AY1: Atenuantes33 (agrup) | AZ1: Aumento33 | BA1: Adolescente | BB1: Arma de fogo | BC1: Interestadual | BD1: Conc. Form. | BE1: Estabelecimento | BF1: Nenhum | BG1: NA | BH1: Aumento33 (agrup) | BI1: §4º | BJ1: §4º (agrupado) | BK1: Pena33 | BL1: Pena33 (meses) | BM1: PenaDrogas | BN1: PenaOutros | BO1: TotPen | BP1: TotPen (meses) | BQ1: Substituição da pena | BR1: Regime inicial | BS1: Regime inicial (agrupado)
A2: 1 | B2: 00316684320178260050 | C2: 1 | D2: 08/06/2017 | E2: Carlos Eduardo Lora Franco | F2: Masculino | G2: 3ª Vara Criminal | H2: Milton Teixeira da Silva | I2: 1 | J2: Comércio e serviços | K2: Masculino | L2: 27624 | M2: 41 | N2: Preta | O2: Negros, pardos e outros | P2: Carapinha | Q2: Bolsa | R2: 0 | S2: 0 | T2: 3 pacotes. 1971,3 g | U2: 1971.3 | V2: 0 | W2: 0 | X2: 0 | Y2: 0 | Z2: 0 | AA2: 0 | AB2: 0 | AC2: Não | AD2: Não | AE2: Não | AF2: Não | AG2: Não | AH2: Não | AI2: Art. 33 | AJ2: Não | AK2: Preso no momento da sentença | AL2: Procedente | AM2: Condenação por tráfico | AN2: Art. 33 | AO2: NA | AP2: Sim. Antecedentes. Natureza. Quantidade | AQ2: 8a | AR2: Reincidência | AS2: Sim | AT2: Não | AU2: Não | AV2: Não | AW2: Sim | AX2: Não | AY2: Não | AZ2: Não | BA2: Não | BB2: Não | BC2: Não | BD2: Não | BE2: Não | BF2: =IF(AZ2="Não","Sim","Não") -> Sim | BG2: =IF(AZ2="NA","Sim","Não") -> Não | BH2: Não | BI2: Não cabimento | BJ2: Não cabimento / Não informado | BK2: 10a | BL2: 120 | BM2: NA | BN2: NA | BO2: 10a | BP2: 120 | BQ2: NA | BR2: Fechado | BS2: NA (Pena Total > 8)
A3: 2 | B3: 00126324020168260635 | C3: 0 | D3: 17/03/2017 | E3: Carlos Eduardo Lora Franco | F3: Masculino | G3: 3ª Vara Criminal | H3: Gabriel Pereira Araújo | I3: 1 | J3: Via Pública | K3: Masculino | L3: 34466 | M3: 22 | N3: Preta | O3: Negros, pardos e outros | P3: Não disponível | Q3: Nada | R3: 80 porções. 148,5 g | S3: 148.5 | T3: 57 porções. 36,6 g | U3: 36.6 | V3: 7 porções. 1,1 g | W3: 1.1 | X3: 0 | Y3: 0 | Z3: 0 | AA3: 0 | AB3: Haxixe. 37 porções. 9,9 g. Skank. 1 porção. 0,9 g | AC3: Não | AD3: Não | AE3: Sim | AF3: Sim | AG3: Não | AH3: Não | AI3: Art. 33. Art. 35 | AJ3: Art. 244-B ECA | AK3: Local de tráfico. Preso no momento da sentença | AL3: Parcialmente procedente | AM3: Condenação por tráfico | AN3: Art. 33 | AO3: Não | AP3: Sim. Natureza. Quantidade. Variedade | AQ3: 7a | AR3: Reincidência | AS3: Sim | AT3: Não | AU3: Não | AV3: Não | AW3: Sim | AX3: Não | AY3: Não | AZ3: Adolescente | BA3: Sim | BB3: Não | BC3: Não | BD3: Não | BE3: Não | BF3: =IF(AZ3="Não","Sim","Não") -> Não | BG3: =IF(AZ3="NA","Sim","Não") -> Não | BH3: Sim | BI3: Não cabimento | BJ3: Não cabimento / Não informado | BK3: 10a 2m 15d | BL3: 122.5 | BM3: NA | BN3: NA | BO3: 10a 2m 15d | BP3: 122.5 | BQ3: NA | BR3: Fechado | BS3: NA (Pena Total > 8)
A4: 3 | B4: 00818385320168260050 | C4: 1 | D4: 24/01/2017 | E4: Adriana Costa | F4: Feminino | G4: 21ª Vara Criminal | H4: JORGE ELIEL PEREIRA DE CASTRO | I4: 1 | J4: Via Pública | K4: Masculino | L4: 33108 | M4: 26 | N4: Parda | O4: Negros, pardos e outros | P4: Não disponível | Q4: Estojo. Dinheiro R$ 20,00 | R4: 35 porções. 56 g | S4: 56 | T4: 43 porções. 15,5 g | U4: 15.5 | V4: 95 porções. 22,6 g | W4: 22.6 | X4: 0 | Y4: 0 | Z4: 0 | AA4: 0 | AB4: 0 | AC4: Não | AD4: Não | AE4: Não | AF4: Não | AG4: Não | AH4: Não | AI4: Art. 33 | AJ4: Art. 244-B ECA | AK4: Preso no momento da sentença. Denúncia | AL4: Parcialmente procedente | AM4: Condenação por tráfico | AN4: Art. 33 | AO4: Não | AP4: Sim. Conduta. Quantidade | AQ4: 6a | AR4: Reincidência | AS4: Sim | AT4: Não | AU4: Não | AV4: Não | AW4: Sim | AX4: Não | AY4: Não | AZ4: Adolescente | BA4: Sim | BB4: Não | BC4: Não | BD4: Não | BE4: Não | BF4: =IF(AZ4="Não","Sim","Não") -> Não | BG4: =IF(AZ4="NA","Sim","Não") -> Não | BH4: Sim | BI4: Não cabimento | BJ4: Não cabimento / Não informado | BK4: 10a 6m | BL4: 126 | BM4: NA | BN4: NA | BO4: 10a 6m | BP4: 126 | BQ4: NA | BR4: Fechado | BS4: NA (Pena Total > 8)
A5: 4 | B5: 00973992020168260050 | C5: 1 | D5: 19/05/2017 | E5: Tamara Priscila Tocci | F5: Feminino | G5: 29ª Vara Criminal | H5: RODOLFO FEITOSA DE PAULA | I5: 1 | J5: Residência | K5: Masculino | L5: 30213 | M5: 34 | N5: Parda | O5: Negros, pardos e outros | P5: Não disponível | Q5: Sacola. Caderno | R5: 1639 porções. 2530 g | S5: 2530 | T5: 1816 porções. 1980 g | U5: 1980 | V5: 3700 porções. 858 g | W5: 858 | X5: 0 | Y5: 0 | Z5: 0 | AA5: 0 | AB5: 0 | AC5: Não | AD5: Não | AE5: Não | AF5: Não | AG5: Não | AH5: Não | AI5: Art. 33 | AJ5: Não | AK5: Confissão informal. Preso no momento da sentença. Investigação | AL5: Procedente | AM5: Condenação por tráfico | AN5: Art. 33 | AO5: NA | AP5: Sim. Antecedentes. Natureza. Quantidade. Variedade | AQ5: 9a 8m 20d | AR5: Reincidência | AS5: Sim | AT5: Não | AU5: Não | AV5: Não | AW5: Sim | AX5: Não | AY5: Não | AZ5: Não | BA5: Não | BB5: Não | BC5: Não | BD5: Não | BE5: Não | BF5: =IF(AZ5="Não","Sim","Não") -> Sim | BG5: =IF(AZ5="NA","Sim","Não") -> Não | BH5: Não | BI5: Não cabimento | BJ5: Não cabimento / Não informado | BK5: 10a 9m 19d | BL5: 129.63333 | BM5: NA | BN5: NA | BO5: 10a 9m 19d | BP5: 129.63333 | BQ5: NA | BR5: Fechado | BS5: NA (Pena Total > 8)
A6: 5 | B6: 00055277520178260635 | C6: 1 | D6: 12/09/2017 | E6: José Roberto Cabral Longaretti | F6: Masculino | G6: 13ª Vara Criminal | H6: CLAUDIO WASHINGTON MENDES DA SILVA | I6: 1 | J6: Residência | K6: Masculino | L6: 33769 | M6: 25 | N6: Preta | O6: Negros, pardos e outros | P6: Outros | Q6: Celular. Dinheiro R$ 15000,00 | R6: 0 | S6: 0 | T6: 0 | U6: 0 | V6: 65 pacotes. 3334,6 g | W6: 3334.6 | X6: 0 | Y6: 0 | Z6: 0 | AA6: 0 | AB6: 0 | AC6: Não | AD6: Não | AE6: Não | AF6: Não | AG6: Não | AH6: Não | AI6: Art. 33 | AJ6: Art. 333 CP | AK6: Confissão informal. Preso no momento da sentença | AL6: Parcialmente procedente | AM6: Condenação por tráfico | AN6: Art. 33 | AO6: Não | AP6: Sim. Quantidade | AQ6: 8a | AR6: Reincidência | AS6: Sim | AT6: Não | AU6: Não | AV6: Não | AW6: Sim | AX6: Não | AY6: Não | AZ6: Adolescente. Arma de fogo | BA6: Sim | BB6: Sim | BC6: Não | BD6: Não | BE6: Não | BF6: =IF(AZ6="Não","Sim","Não") -> Não | BG6: =IF(AZ6="NA","Sim","Não") -> Não | BH6: Sim | BI6: Não cabimento | BJ6: Não cabimento / Não informado | BK6: 11a 2m 12d | BL6: 134.4 | BM6: NA | BN6: NA | BO6: 11a 2m 12d | BP6: 134.4 | BQ6: NA | BR6: Fechado | BS6: NA (Pena Total > 8)
A7: 6 | B7: 00269673920178260050 | C7: 1 | D7: 11/07/2017 | E7: Rafael Henrique Janela Tamai Rocha | F7: Masculino | G7: 22ª Vara Criminal | H7: LUIZ CARLOS FELIX DE SOUZA | I7: 1 | J7: Residência | K7: Masculino | L7: 26835 | M7: 44 | N7: Parda | O7: Negros, pardos e outros | P7: Carapinha | Q7: Veículo. Balança. Papéis | R7: 1 tijolo. 515,68 g | S7: 515.68 | T7: 8 porções. 11 g | U7: 11 | V7: 42 porções. 8,5 g | W7: 8.5 | X7: 0 | Y7: 0 | Z7: 0 | AA7: 0 | AB7: 0 | AC7: Não | AD7: Não | AE7: Não | AF7: Não | AG7: Não | AH7: Não | AI7: Art. 33. Art. 35 | AJ7: Não | AK7: Investigação. Preso no momento da sentença | AL7: Parcialmente procedente | AM7: Condenação por tráfico | AN7: Art. 33 | AO7: NA | AP7: Sim. Antecedentes. Natureza. Quantidade | AQ7: 10a | AR7: Reincidência | AS7: Sim | AT7: Não | AU7: Não | AV7: Não | AW7: Sim | AX7: Não | AY7: Não | AZ7: Não | BA7: Não | BB7: Não | BC7: Não | BD7: Não | BE7: Não | BF7: =IF(AZ7="Não","Sim","Não") -> Sim | BG7: =IF(AZ7="NA","Sim","Não") -> Não | BH7: Não | BI7: Não cabimento | BJ7: Não cabimento / Não informado | BK7: 12a 6m | BL7: 150 | BM7: NA | BN7: NA | BO7: 12a 6m | BP7: 150 | BQ7: NA | BR7: Fechado | BS7: NA (Pena Total > 8)
A8: 7 | B8: 00970683820168260050 | C8: 1 | D8: 08/02/2017 | E8: Carla de Oliveira Pinto Ferrari | F8: Feminino | G8: 20ª Vara Criminal | H8: MARIA CRISTINA DA SILVA | I8: 1 | J8: Via Pública | K8: Feminino | L8: 34880 | M8: 21 | N8: Parda | O8: Negros, pardos e outros | P8: Não disponível | Q8: Bolsa. Dinheiro R$ 41,30 | R8: 0 | S8: 0 | T8: 0 | U8: 0 | V8: 51 porções. 12,5 g | W8: 12.5 | X8: 0 | Y8: 0 | Z8: 0 | AA8: 0 | AB8: 0 | AC8: Não | AD8: Não | AE8: Não | AF8: Não | AG8: Não | AH8: Não | AI8: Art. 33 | AJ8: Não | AK8: Preso no momento da sentença. Local de tráfico. Atitude suspeita | AL8: Procedente | AM8: Condenação por tráfico | AN8: Art. 33 | AO8: NA | AP8: Sim. Antecedentes. Natureza | AQ8: 11a 8m | AR8: Reincidência | AS8: Sim | AT8: Não | AU8: Não | AV8: Não | AW8: Sim | AX8: Não | AY8: Não | AZ8: Não | BA8: Não | BB8: Não | BC8: Não | BD8: Não | BE8: Não | BF8: =IF(AZ8="Não","Sim","Não") -> Sim | BG8: =IF(AZ8="NA","Sim","Não") -> Não | BH8: Não | BI8: Não cabimento | BJ8: Não cabimento / Não informado | BK8: 15a | BL8: 180 | BM8: NA | BN8: NA | BO8: 15a | BP8: 180 | BQ8: NA | BR8: Fechado | BS8: NA (Pena Total > 8)
A9: 8 | B9: 00554602620178260050 | C9: 0 | D9: 05/12/2017 | E9: Maria Paula Cassone Rossi | F9: Feminino | G9: 9ª Vara Criminal | H9: JONATHAN HENRIQUE DO NASCIMENTO | I9: 1 | J9: Via Pública | K9: Masculino | L9: 32973 | M9: 27 | N9: Parda | O9: Negros, pardos e outros | P9: Não disponível | Q9: Dinheiro R$ 55,00 | R9: 0 | S9: 0 | T9: 0 | U9: 0 | V9: 0 | W9: 0 | X9: 0 | Y9: 0 | Z9: 0 | AA9: 0 | AB9: 0 | AC9: Não | AD9: Não | AE9: Não | AF9: Não | AG9: Não | AH9: Não | AI9: Art. 33. Art. 35 | AJ9: Não | AK9: Local de tráfico | AL9: Parcialmente procedente | AM9: Condenação por tráfico | AN9: Art. 33 | AO9: NA | AP9: Sim. Variedade | AQ9: 5a 10m | AR9: Não | AS9: Não | AT9: Não | AU9: Não | AV9: Não | AW9: Sim | AX9: Não | AY9: Não | AZ9: Não | BA9: Não | BB9: Não | BC9: Não | BD9: Não | BE9: Não | BF9: =IF(AZ9="Não","Sim","Não") -> Sim | BG9: =IF(AZ9="NA","Sim","Não") -> Não | BH9: Não | BI9: Sim total | BJ9: Sim (total ou parcial) | BK9: 1a 11m 10d | BL9: 23.333333 | BM9: NA | BN9: NA | BO9: 1a 11m 10d | BP9: 23.333333 | BQ9: Não | BR9: Aberto | BS9: Aberto
A10: 9 | B10: 00663684520178260050 | C10: 1 | D10: 09/10/2017 | E10: Klaus Marouelli Arroyo | F10: Masculino | G10: 23ª Vara Criminal | H10: ICARO VITOR PEREIRA DE JESUS | I10: 1 | J10: Via Pública | K10: Masculino | L10: 32304 | M10: 29 | N10: Parda | O10: Negros, pardos e outros | P10: Não disponível | Q10: Estojo. Celular. Dinheiro R$ 15,00 | R10: 15 porções. 29 g | S10: 29 | T10: 11 porções. 13,2 g | U10: 13.2 | V10: 0 | W10: 0 | X10: 0 | Y10: 0 | Z10: 0 | AA10: 0 | AB10: 0 | AC10: Não | AD10: Não | AE10: Não | AF10: Não | AG10: Não | AH10: Não | AI10: Art. 33 | AJ10: Não | AK10: Confissão informal. Confissão. Local de tráfico | AL10: Procedente | AM10: Condenação por tráfico | AN10: Art. 33 | AO10: NA | AP10: Não | AQ10: 5a | AR10: Não | AS10: Não | AT10: Não | AU10: Não | AV10: Não | AW10: Sim | AX10: Não | AY10: Não | AZ10: Adolescente | BA10: Sim | BB10: Não | BC10: Não | BD10: Não | BE10: Não | BF10: =IF(AZ10="Não","Sim","Não") -> Não | BG10: =IF(AZ10="NA","Sim","Não") -> Não | BH10: Sim | BI10: Sim total | BJ10: Sim (total ou parcial) | BK10: 1a 11m 10d | BL10: 23.333333 | BM10: NA | BN10: NA | BO10: 1a 11m 10d | BP10: 23.333333 | BQ10: Não | BR10: Fechado | BS10: Fechado
A11: 10 | B11: 00583559120168260050 | C11: 1 | D11: 01/03/2017 | E11: Renata William Rached Catelli | F11: Feminino | G11: 21ª Vara Criminal | H11: THAIS HONDA SILVA | I11: 1 | J11: Via Pública | K11: Feminino | L11: 34740 | M11: 22 | N11: Parda | O11: Negros, pardos e outros | P11: Não disponível | Q11: Celular | R11: 0 | S11: 0 | T11: 7 porções. 2,6 g | U11: 2.6 | V11: 0 | W11: 0 | X11: 0 | Y11: 0 | Z11: 0 | AA11: 0 | AB11: 0 | AC11: Não | AD11: Não | AE11: Não | AF11: Não | AG11: Não | AH11: Não | AI11: Art. 33. Art. 35 | AJ11: Não | AK11: Local de tráfico. Denúncia anônima | AL11: Parcialmente procedente | AM11: Condenação por tráfico | AN11: Art. 33 | AO11: NA | AP11: Não | AQ11: 5a | AR11: Não | AS11: Não | AT11: Não | AU11: Não | AV11: Não | AW11: Sim | AX11: Não | AY11: Não | AZ11: Adolescente | BA11: Sim | BB11: Não | BC11: Não | BD11: Não | BE11: Não | BF11: =IF(AZ11="Não","Sim","Não") -> Não | BG11: =IF(AZ11="NA","Sim","Não") -> Não | BH11: Sim | BI11: Sim total | BJ11: Sim (total ou parcial) | BK11: 1a 11m 10d | BL11: 23.333333 | BM11: NA | BN11: NA | BO11: 1a 11m 10d | BP11: 23.333333 | BQ11: Não | BR11: Fechado | BS11: Fechado
A12: 11 | B12: 00763926920168260050 | C12: 1 | D12: 30/05/2017 | E12: CRISTINA ESCHER | F12: Feminino | G12: 4ª Vara Criminal | H12: EVERTON GOMES TIMOTEO | I12: 1 | J12: Via Pública | K12: Masculino | L12: 35423 | M12: 20 | N12: Parda | O12: Negros, pardos e outros | P12: Não disponível | Q12: Celular. Dinheiro R$ 80,00 | R12: 60 porções. 108,2 g | S12: 108.2 | T12: 78 porções. 63,8 g | U12: 63.8 | V12: 0 | W12: 0 | X12: 0 | Y12: 0 | Z12: 0 | AA12: 0 | AB12: Lança-perfume. 8 frascos. 44 ml | AC12: Não | AD12: Não | AE12: Não | AF12: Não | AG12: Sim | AH12: Não | AI12: Art. 33 | AJ12: Não | AK12: Preso no momento da sentença. Confissão informal | AL12: Procedente | AM12: Condenação por tráfico | AN12: Art. 33 | AO12: NA | AP12: Não | AQ12: 5a | AR12: Não | AS12: Não | AT12: Não | AU12: Não | AV12: Não | AW12: Sim | AX12: Não | AY12: Não | AZ12: Estabelecimento | BA12: Não | BB12: Não | BC12: Não | BD12: Não | BE12: Sim | BF12: =IF(AZ12="Não","Sim","Não") -> Não | BG12: =IF(AZ12="NA","Sim","Não") -> Não | BH12: Sim | BI12: Sim total | BJ12: Sim (total ou parcial) | BK12: 1a 11m 10d | BL12: 23.333333 | BM12: NA | BN12: NA | BO12: 1a 11m 10d | BP12: 23.333333 | BQ12: Não | BR12: Fechado | BS12: Fechado
A13: 12 | B13: 01036245620168260050 | C13: 1 | D13: 04/08/2017 | E13: Patrícia Álvares Cruz | F13: Feminino | G13: 9ª Vara Criminal | H13: FLÁVIO COUTINHO GOMES | I13: 1 | J13: Restaurante e afins | K13: Masculino | L13: 31567 | M13: 31 | N13: Parda | O13: Negros, pardos e outros | P13: Carapinha | Q13: Dinheiro R$ 9,00 | R13: 9 porções. 36,1 g | S13: 36.1 | T13: 9 porções. 6,8 g | U13: 6.8 | V13: 0 | W13: 0 | X13: 0 | Y13: 0 | Z13: 0 | AA13: 0 | AB13: 0 | AC13: Não | AD13: Não | AE13: Não | AF13: Não | AG13: Não | AH13: Não | AI13: Art. 33 | AJ13: Não | AK13: Local de tráfico. Preso no momento da sentença | AL13: Procedente | AM13: Condenação por tráfico | AN13: Art. 33 | AO13: NA | AP13: Sim. Variedade | AQ13: 5a 10m | AR13: Não | AS13: Não | AT13: Não | AU13: Não | AV13: Não | AW13: Sim | AX13: Não | AY13: Não | AZ13: Não | BA13: Não | BB13: Não | BC13: Não | BD13: Não | BE13: Não | BF13: =IF(AZ13="Não","Sim","Não") -> Sim | BG13: =IF(AZ13="NA","Sim","Não") -> Não | BH13: Não | BI13: Sim total | BJ13: Sim (total ou parcial) | BK13: 1a 11m 10d | BL13: 23.333333 | BM13: NA | BN13: NA | BO13: 1a 11m 10d | BP13: 23.333333 | BQ13: Não | BR13: Aberto | BS13: Aberto
A14: 13 | B14: 00292905120168260050 | C14: 1 | D14: 43017 | E14: Edison Tetsuzo Namba | F14: Masculino | G14: 16ª Vara Criminal | H14: MARILENE PINHEIRO DA ROCHA | I14: 1 | J14: Repartição Pública | K14: Feminino | L14: 25190 | M14: 48 | N14: Branca | O14: Branco e amarelo | P14: Liso | Q14: Chinelo | R14: 1 porção. 25,2 g | S14: 25.2 | T14: 0 | U14: 0 | V14: 18 porções. 7 g | W14: 7 | X14: 0 | Y14: 0 | Z14: 0 | AA14: 0 | AB14: 0 | AC14: Não | AD14: Não | AE14: Não | AF14: Não | AG14: Não | AH14: Não | AI14: Art. 33. Art. 35 | AJ14: Não | AK14: Revista Vexatória. Confissão informal | AL14: Parcialmente Procedente | AM14: Condenação por tráfico | AN14: Art. 33 | AO14: NA | AP14: Não | AQ14: 5a | AR14: Não | AS14: Não | AT14: Não | AU14: Não | AV14: Não | AW14: Sim | AX14: Não | AY14: Não | AZ14: Estabelecimento | BA14: Não | BB14: Não | BC14: Não | BD14: Não | BE14: Sim | BF14: =IF(AZ14="Não","Sim","Não") -> Não | BG14: =IF(AZ14="NA","Sim","Não") -> Não | BH14: Sim | BI14: Sim total | BJ14: Sim (total ou parcial) | BK14: 1a 11m 10d | BL14: 23.333333 | BM14: NA | BN14: NA | BO14: 1a 11m 10d | BP14: 23.333333 | BQ14: Sim | BR14: NA | BS14: NA
A15: 14 | B15: 00607505620168260050 | C15: 1 | D15: 17/03/2017 | E15: Tatiana Vieira Guerra | F15: Feminino | G15: 32ª Vara Criminal | H15: WILLEN ALVES RIBEIRO | I15: 1 | J15: Via Pública | K15: Masculino | L15: 35816 | M15: 19 | N15: Branca | O15: Branco e amarelo | P15: Outros | Q15: Dinheiro R$ 39,00 | R15: 19 porções. 24,3 g | S15: 24.3 | T15: 27 porções. 37,5 g | U15: 37.5 | V15: 20 porções. 20,5 g | W15: 20.5 | X15: 0 | Y15: 0 | Z15: 0 | AA15: 0 | AB15: 0 | AC15: Não | AD15: Não | AE15: Não | AF15: Não | AG15: Não | AH15: Não | AI15: Art. 33 | AJ15: Art. 244-B ECA | AK15: Preso no momento da sentença. Local de tráfico | AL15: Parcialmente procedente | AM15: Condenação por tráfico | AN15: Art. 33 | AO15: Não | AP15: Não | AQ15: 5a | AR15: Não | AS15: Não | AT15: Não | AU15: Não | AV15: Não | AW15: Sim | AX15: Não | AY15: Não | AZ15: Adolescente | BA15: Sim | BB15: Não | BC15: Não | BD15: Não | BE15: Não | BF15: =IF(AZ15="Não","Sim","Não") -> Não | BG15: =IF(AZ15="NA","Sim","Não") -> Não | BH15: Sim | BI15: Sim total | BJ15: Sim (total ou parcial) | BK15: 1a 11m 10d | BL15: 23.333333 | BM15: NA | BN15: NA | BO15: 1a 11m 10d | BP15: 23.333333 | BQ15: Sim | BR15: NA | BS15: NA
A16: 15 | B16: 00945836520168260050 | C16: 0 | D16: 20/03/2017 | E16: Paulo Eduardo Balbone Costa | F16: Masculino | G16: 7ª Vara Criminal | H16: MULLER DA SILVA BORGES | I16: 1 | J16: Via Pública | K16: Masculino | L16: 34440 | M16: 22 | N16: Parda | O16: Negros, pardos e outros | P16: Não disponível | Q16: Dinheiro R$ 280,00 | R16: 11 porções. 15,5 g | S16: 15.5 | T16: 71 porções. 45,6 g | U16: 45.6 | V16: 25 porções. 4,3 g | W16: 4.3 | X16: 0 | Y16: 0 | Z16: 0 | AA16: 0 | AB16: Lança-perfume. 5 frascos. 32,5 ml | AC16: Não | AD16: Não | AE16: Não | AF16: Não | AG16: Sim | AH16: Não | AI16: Art. 33. Art. 35 | AJ16: Não | AK16: Atitude suspeita. Preso no momento da sentença | AL16: Parcialmente procedente | AM16: Condenação por tráfico | AN16: Art. 33 | AO16: NA | AP16: Não | AQ16: 5a | AR16: Não | AS16: Não | AT16: Não | AU16: Não | AV16: Não | AW16: Sim | AX16: Não | AY16: Não | AZ16: Adolescente | BA16: Sim | BB16: Não | BC16: Não | BD16: Não | BE16: Não | BF16: =IF(AZ16="Não","Sim","Não") -> Não | BG16: =IF(AZ16="NA","Sim","Não") -> Não | BH16: Sim | BI16: Sim total | BJ16: Sim (total ou parcial) | BK16: 1a 11m 10d | BL16: 23.333333 | BM16: NA | BN16: NA | BO16: 1a 11m 10d | BP16: 23.333333 | BQ16: Sim | BR16: NA | BS16: NA
A17: 16 | B17: 00493201020168260050 | C17: 1 | D17: 03/04/2017 | E17: José Fernandes Freitas Neto | F17: Masculino | G17: 6ª Vara Criminal | H17: WESLEY DA SILVA COELHO | I17: 1 | J17: Via Pública | K17: Masculino | L17: 34539 | M17: 22 | N17: Branca | O17: Branco e amarelo | P17: Não disponível | Q17: Celular | R17: 520 porções. 1635 g | S17: 1635 | T17: 147 porções. 94,1 g | U17: 94.1 | V17: 496 porções. 215,4 g | W17: 215.4 | X17: 0 | Y17: 0 | Z17: 0 | AA17: 0 | AB17: 0 | AC17: Não | AD17: Não | AE17: Não | AF17: Não | AG17: Não | AH17: Não | AI17: Art. 33 | AJ17: Não | AK17: Confissão informal. Preso no momento da sentença | AL17: Procedente | AM17: Condenação por tráfico | AN17: Art. 33 | AO17: NA | AP17: Sim. Quantidade | AQ17: 5a 10m | AR17: Não | AS17: Não | AT17: Não | AU17: Não | AV17: Não | AW17: Sim | AX17: Não | AY17: Não | AZ17: Não | BA17: Não | BB17: Não | BC17: Não | BD17: Não | BE17: Não | BF17: =IF(AZ17="Não","Sim","Não") -> Sim | BG17: =IF(AZ17="NA","Sim","Não") -> Não | BH17: Não | BI17: Sim total | BJ17: Sim (total ou parcial) | BK17: 1a 11m 10d | BL17: 23.333333 | BM17: NA | BN17: NA | BO17: 1a 11m 10d | BP17: 23.333333 | BQ17: Não | BR17: Semiaberto | BS17: Semiaberto
A18: 17 | B18: 00770379420168260050 | C18: 0 | D18: 27/09/2017 | E18: Fátima Vilas Boas Cruz | F18: Feminino | G18: 17ª Vara Criminal | H18: ERICK SANTOS DE SOUZA | I18: 1 | J18: Via Pública | K18: Masculino | L18: 35908 | M18: 19 | N18: Branca | O18: Branco e amarelo | P18: Não disponível | Q18: Dinheiro R$ 200,00 | R18: 0 | S18: 0 | T18: 0 | U18: 0 | V18: 0 | W18: 0 | X18: 0 | Y18: 0 | Z18: 0 | AA18: 0 | AB18: 0 | AC18: Não | AD18: Não | AE18: Não | AF18: Não | AG18: Não | AH18: Não | AI18: Art. 33 | AJ18: Não | AK18: Local de tráfico | AL18: Procedente | AM18: Condenação por tráfico | AN18: Art. 33 | AO18: NA | AP18: Não | AQ18: 5a | AR18: Não | AS18: Não | AT18: Não | AU18: Não | AV18: Não | AW18: Sim | AX18: Não | AY18: Não | AZ18: Não | BA18: Não | BB18: Não | BC18: Não | BD18: Não | BE18: Não | BF18: =IF(AZ18="Não","Sim","Não") -> Sim | BG18: =IF(AZ18="NA","Sim","Não") -> Não | BH18: Não | BI18: Sim total | BJ18: Sim (total ou parcial) | BK18: 1a 8m | BL18: 20 | BM18: NA | BN18: NA | BO18: 1a 8m | BP18: 20 | BQ18: Sim | BR18: NA | BS18: NA
A19: 18 | B19: 00125146420168260635 | C19: 1 | D19: 01/08/2017 | E19: CRISTINA ESCHER | F19: Feminino | G19: 4ª Vara Criminal | H19: ALYSSON MARQUES DUTRA | I19: 1 | J19: Via Pública | K19: Masculino | L19: 35011 | M19: 21 | N19: Branca | O19: Branco e amarelo | P19: Não disponível | Q19: Caderno | R19: 1 sacola. 842,4 g | S19: 842.4 | T19: 0 | U19: 0 | V19: 0 | W19: 0 | X19: 0 | Y19: 0 | Z19: 0 | AA19: 0 | AB19: 0 | AC19: Não | AD19: Não | AE19: Não | AF19: Não | AG19: Não | AH19: Não | AI19: Art. 33 | AJ19: Não | AK19: Preso no momento da sentença. Atitude suspeita | AL19: Procedente | AM19: Condenação por tráfico | AN19: Art. 33 | AO19: NA | AP19: Não | AQ19: 5a | AR19: Não | AS19: Não | AT19: Não | AU19: Não | AV19: Não | AW19: Sim | AX19: Não | AY19: Não | AZ19: Não | BA19: Não | BB19: Não | BC19: Não | BD19: Não | BE19: Não | BF19: =IF(AZ19="Não","Sim","Não") -> Sim | BG19: =IF(AZ19="NA","Sim","Não") -> Não | BH19: Não | BI19: Sim total | BJ19: Sim (total ou parcial) | BK19: 1a 8m | BL19: 20 | BM19: NA | BN19: NA | BO19: 1a 8m | BP19: 20 | BQ19: Não | BR19: Semiaberto | BS19: Semiaberto
A20: 19 | B20: 00447582120178260050 | C20: 1 | D20: 09/08/2017 | E20: TERESA DE ALMEIDA RIBEIRO MAGALHAES | F20: Feminino | G20: 18ª Vara Criminal | H20: ISRAEL APARECIDO BALTAZAR | I20: 1 | J20: Via Pública | K20: Masculino | L20: 27849 | M20: 41 | N20: Parda | O20: Negros, pardos e outros | P20: Não disponível | Q20: Dinheiro R$ 30,00 | R20: 10 porções. 17,6 g | S20: 17.6 | T20: 0 | U20: 0 | V20: 0 | W20: 0 | X20: 0 | Y20: 0 | Z20: 0 | AA20: 0 | AB20: 0 | AC20: Não | AD20: Não | AE20: Não | AF20: Não | AG20: Não | AH20: Não | AI20: Art. 33 | AJ20: Não | AK20: Preso no momento da sentença. Local de tráfico | AL20: Procedente | AM20: Condenação por tráfico | AN20: Art. 33 | AO20: NA | AP20: Não | AQ20: 5a | AR20: Não | AS20: Não | AT20: Não | AU20: Não | AV20: Não | AW20: Sim | AX20: Não | AY20: Não | AZ20: Não | BA20: Não | BB20: Não | BC20: Não | BD20: Não | BE20: Não | BF20: =IF(AZ20="Não","Sim","Não") -> Sim | BG20: =IF(AZ20="NA","Sim","Não") -> Não | BH20: Não | BI20: Sim total | BJ20: Sim (total ou parcial) | BK20: 1a 8m | BL20: 20 | BM20: NA | BN20: NA | BO20: 1a 8m | BP20: 20 | BQ20: Sim | BR20: NA | BS20: NA
A21: 20 | B21: 00885193920168260050 | C21: 1 | D21: 42888 | E21: Giovana Furtado de Oliveira | F21: Feminino | G21: 24ª Vara Criminal | H21: GERSON DE JESUS SIMOES | I21: 1 | J21: Via Pública | K21: Masculino | L21: 35604 | M21: 19 | N21: Preta | O21: Negros, pardos e outros | P21: Não disponível | Q21: Dinheiro R$ 40,00 | R21: 16 porções. 64,3 g | S21: 64.3 | T21: 0 | U21: 0 | V21: 0 | W21: 0 | X21: 0 | Y21: 0 | Z21: 0 | AA21: 0 | AB21: 0 | AC21: Não | AD21: Não | AE21: Não | AF21: Não | AG21: Não | AH21: Não | AI21: Art. 33 | AJ21: Não | AK21: Confissão informal | AL21: Procedente | AM21: Condenação por tráfico | AN21: Art. 33 | AO21: NA | AP21: Não | AQ21: 5a | AR21: Não | AS21: Não | AT21: Não | AU21: Não | AV21: Não | AW21: Sim | AX21: Não | AY21: Não | AZ21: Não | BA21: Não | BB21: Não | BC21: Não | BD21: Não | BE21: Não | BF21: =IF(AZ21="Não","Sim","Não") -> Sim | BG21: =IF(AZ21="NA","Sim","Não") -> Não | BH21: Não | BI21: Sim total | BJ21: Sim (total ou parcial) | BK21: 1a 8m | BL21: 20 | BM21: NA | BN21: NA | BO21: 1a 8m | BP21: 20 | BQ21: Sim | BR21: NA | BS21: NA
A22: 21 | B22: 00316927120178260050 | C22: 1 | D22: 17/08/2017 | E22: Carla de Oliveira Pinto Ferrari | F22: Feminino | G22: 20ª Vara Criminal | H22: DANIEL ALESSANDRO BEZERRA | I22: 1 | J22: Via Pública | K22: Masculino | L22: 35651 | M22: 20 | N22: Branca | O22: Branco e amarelo | P22: Encaracolado | Q22: Dinheiro R$ 90,00 | R22: 17 porções. 66,4 g | S22: 66.4 | T22: 0 | U22: 0 | V22: 0 | W22: 0 | X22: 0 | Y22: 0 | Z22: 0 | AA22: 0 | AB22: 0 | AC22: Não | AD22: Não | AE22: Não | AF22: Não | AG22: Não | AH22: Não | AI22: Art. 33 | AJ22: Não | AK22: Local de tráfico. Confissão informal | AL22: Procedente | AM22: Condenação por tráfico | AN22: Art. 33 | AO22: NA | AP22: Não | AQ22: 5a | AR22: Não | AS22: Não | AT22: Não | AU22: Não | AV22: Não | AW22: Sim | AX22: Não | AY22: Não | AZ22: Não | BA22: Não | BB22: Não | BC22: Não | BD22: Não | BE22: Não | BF22: =IF(AZ22="Não","Sim","Não") -> Sim | BG22: =IF(AZ22="NA","Sim","Não") -> Não | BH22: Não | BI22: Sim total | BJ22: Sim (total ou parcial) | BK22: 1a 8m | BL22: 20 | BM22: NA | BN22: NA | BO22: 1a 8m | BP22: 20 | BQ22: Não | BR22: Fechado | BS22: Fechado
A23: 22 | B23: 00216280220178260050 | C23: 1 | D23: 23/05/2017 | E23: Cecilia Pinheiro da Fonseca | F23: Feminino | G23: 3ª Vara Criminal | H23: ANTONIO RODRIGUES DE LIMA | I23: 1 | J23: Residência | K23: Masculino | L23: 24436 | M23: 50 | N23: Branca | O23: Branco e amarelo | P23: Não disponível | Q23: Coldre. Arma de fogo. Munição. Caderno. Dinheiro R$ 15938,35 | R23: 201 porções. 3 tijolos. 728,2 g (total) | S23: 728.2 | T23: 0 | U23: 0 | V23: 0 | W23: 0 | X23: 0 | Y23: 0 | Z23: 0 | AA23: 0 | AB23: 0 | AC23: Não | AD23: Não | AE23: Não | AF23: Não | AG23: Não | AH23: Não | AI23: Art. 33 | AJ23: Art. 16 L10826 | AK23: Preso no momento da sentença. Atitude suspeita | AL23: Procedente | AM23: Condenação por tráfico | AN23: Art. 33 | AO23: Art. 16 L10826 (4 vezes) | AP23: Não | AQ23: 5a | AR23: Não | AS23: Não | AT23: Não | AU23: Não | AV23: Não | AW23: Sim | AX23: Não | AY23: Não | AZ23: Não | BA23: Não | BB23: Não | BC23: Não | BD23: Não | BE23: Não | BF23: =IF(AZ23="Não","Sim","Não") -> Sim | BG23: =IF(AZ23="NA","Sim","Não") -> Não | BH23: Não | BI23: Sim total | BJ23: Sim (total ou parcial) | BK23: 1a 8m | BL23: 20 | BM23: NA | BN23: 12a | BO23: 13a 8m | BP23: 164 | BQ23: NA | BR23: Fechado | BS23: NA (Pena Total > 8)
A24: 23 | B24: 00810028020168260050 | C24: 1 | D24: 03/08/2017 | E24: Antonio de Oliveira Angrisani Filho | F24: Masculino | G24: 27ª Vara Criminal | H24: FRANCISCO ANDERSON DA SILVA | I24: 1 | J24: Via Pública | K24: Masculino | L24: 35984 | M24: 19 | N24: Parda | O24: Negros, pardos e outros | P24: Não disponível | Q24: Dinheiro R$ 92,00 | R24: 27 porções. 47,7 g | S24: 47.7 | T24: 0 | U24: 0 | V24: 0 | W24: 0 | X24: 0 | Y24: 0 | Z24: 0 | AA24: 0 | AB24: 0 | AC24: Não | AD24: Não | AE24: Não | AF24: Não | AG24: Não | AH24: Não | AI24: Art. 33 | AJ24: Não | AK24: Local de tráfico. Confissão | AL24: Procedente | AM24: Condenação por tráfico | AN24: Art. 33 | AO24: NA | AP24: Não | AQ24: 5a | AR24: Não | AS24: Não | AT24: Não | AU24: Não | AV24: Não | AW24: Sim | AX24: Não | AY24: Não | AZ24: Não | BA24: Não | BB24: Não | BC24: Não | BD24: Não | BE24: Não | BF24: =IF(AZ24="Não","Sim","Não") -> Sim | BG24: =IF(AZ24="NA","Sim","Não") -> Não | BH24: Não | BI24: Sim total | BJ24: Sim (total ou parcial) | BK24: 1a 8m | BL24: 20 | BM24: NA | BN24: NA | BO24: 1a 8m | BP24: 20 | BQ24: Não | BR24: Aberto | BS24: Aberto
A25: 24 | B25: 00025180820178260635 | C25: 1 | D25: 42893 | E25: Erica Regina Colmenero Coimbra | F25: Feminino | G25: 2ª Vara Criminal | H25: JUNIOR EDOGHOTU | I25: 1 | J25: Via Pública | K25: Masculino | L25: 30297 | M25: 34 | N25: Preta | O25: Negros, pardos e outros | P25: Não disponível | Q25: Dinheiro R$ 159,75 | R25: 29 porções. 86,1 g | S25: 86.1 | T25: 0 | U25: 0 | V25: 0 | W25: 0 | X25: 0 | Y25: 0 | Z25: 0 | AA25: 0 | AB25: 0 | AC25: Não | AD25: Não | AE25: Não | AF25: Não | AG25: Não | AH25: Não | AI25: Art. 33 | AJ25: Não | AK25: Nacionalidade. Preso no momento da sentença. Local de tráfico | AL25: Procedente | AM25: Condenação por tráfico | AN25: Art. 33 | AO25: NA | AP25: Não | AQ25: 5a | AR25: Não | AS25: Não | AT25: Não | AU25: Não | AV25: Não | AW25: Sim | AX25: Não | AY25: Não | AZ25: Não | BA25: Não | BB25: Não | BC25: Não | BD25: Não | BE25: Não | BF25: =IF(AZ25="Não","Sim","Não") -> Sim | BG25: =IF(AZ25="NA","Sim","Não") -> Não | BH25: Não | BI25: Sim total | BJ25: Sim (total ou parcial) | BK25: 1a 8m | BL25: 20 | BM25: NA | BN25: NA | BO25: 1a 8m | BP25: 20 | BQ25: Não | BR25: Fechado | BS25: Fechado
A26: 25 | B26: 00717920520168260050 | C26: 1 | D26: 26/05/2017 | E26: Tatiana Vieira Guerra | F26: Feminino | G26: 27ª Vara Criminal | H26: EMERSON APARECIDO CIPRIANO DE BRITO | I26: 1 | J26: Via Pública | K26: Masculino | L26: 29032 | M26: 37 | N26: Preta | O26: Negros, pardos e outros | P26: Carapinha | Q26: Nada | R26: 32 porções. 51,7 g | S26: 51.7 | T26: 0 | U26: 0 | V26: 0 | W26: 0 | X26: 0 | Y26: 0 | Z26: 0 | AA26: 0 | AB26: 0 | AC26: Não | AD26: Não | AE26: Não | AF26: Não | AG26: Não | AH26: Não | AI26: Art. 33 | AJ26: Não | AK26: Local de tráfico. Preso no momento da sentença | AL26: Procedente | AM26: Condenação por tráfico | AN26: Art. 33 | AO26: NA | AP26: Não | AQ26: 5a | AR26: Não | AS26: Não | AT26: Não | AU26: Não | AV26: Não | AW26: Sim | AX26: Não | AY26: Não | AZ26: Não | BA26: Não | BB26: Não | BC26: Não | BD26: Não | BE26: Não | BF26: =IF(AZ26="Não","Sim","Não") -> Sim | BG26: =IF(AZ26="NA","Sim","Não") -> Não | BH26: Não | BI26: Sim total | BJ26: Sim (total ou parcial) | BK26: 1a 8m | BL26: 20 | BM26: NA | BN26: NA | BO26: 1a 8m | BP26: 20 | BQ26: Não | BR26: Aberto | BS26: Aberto
A27: 26 | B27: 00011202620178260635 | C27: 1 | D27: 42871 | E27: Luciane Jabur Mouchaloite Figueiredo | F27: Feminino | G27: 21ª Vara Criminal | H27: IAGO FERREIRA LOBO | I27: 1 | J27: Via Pública | K27: Masculino | L27: 35825 | M27: 19 | N27: Branca | O27: Branco e amarelo | P27: Carapinha | Q27: Dinheiro R$ 10,00 | R27: 4 porções. 8,5 g | S27: 8.5 | T27: 0 | U27: 0 | V27: 0 | W27: 0 | X27: 0 | Y27: 0 | Z27: 0 | AA27: 0 | AB27: 0 | AC27: Não | AD27: Não | AE27: Não | AF27: Não | AG27: Não | AH27: Não | AI27: Art. 33 | AJ27: Não | AK27: Local de tráfico. Confissão informal. Confissão. Preso no momento da sentença. Denúncia | AL27: Procedente | AM27: Condenação por tráfico | AN27: Art. 33 | AO27: NA | AP27: Não | AQ27: 5a | AR27: Não | AS27: Não | AT27: Não | AU27: Não | AV27: Não | AW27: Sim | AX27: Não | AY27: Não | AZ27: Não | BA27: Não | BB27: Não | BC27: Não | BD27: Não | BE27: Não | BF27: =IF(AZ27="Não","Sim","Não") -> Sim | BG27: =IF(AZ27="NA","Sim","Não") -> Não | BH27: Não | BI27: Sim total | BJ27: Sim (total ou parcial) | BK27: 1a 8m | BL27: 20 | BM27: NA | BN27: NA | BO27: 1a 8m | BP27: 20 | BQ27: Não | BR27: Semiaberto | BS27: Semiaberto
A28: 27 | B28: 00265875020168260050 | C28: 1 | D28: 26/10/2017 | E28: Tatiana Saes Valverde Ormeleze | F28: Feminino | G28: 21ª Vara Criminal | H28: TIAGO ALVES DA SILVA SANTOS | I28: 1 | J28: Via Pública | K28: Masculino | L28: 32978 | M28: 27 | N28: Parda | O28: Negros, pardos e outros | P28: Carapinha | Q28: Lata. Celular. Dinheiro R$ 20,00 | R28: 40 g | S28: 40 | T28: 0 | U28: 0 | V28: 0 | W28: 0 | X28: 0 | Y28: 0 | Z28: 0 | AA28: 0 | AB28: 0 | AC28: Não | AD28: Não | AE28: Não | AF28: Não | AG28: Não | AH28: Não | AI28: Art. 33 | AJ28: Não | AK28: Não há | AL28: Procedente | AM28: Condenação por tráfico | AN28: Art. 33 | AO28: NA | AP28: Não | AQ28: 5a | AR28: Não | AS28: Não | AT28: Não | AU28: Não | AV28: Não | AW28: Sim | AX28: Não | AY28: Não | AZ28: Não | BA28: Não | BB28: Não | BC28: Não | BD28: Não | BE28: Não | BF28: =IF(AZ28="Não","Sim","Não") -> Sim | BG28: =IF(AZ28="NA","Sim","Não") -> Não | BH28: Não | BI28: Sim total | BJ28: Sim (total ou parcial) | BK28: 1a 8m | BL28: 20 | BM28: NA | BN28: NA | BO28: 1a 8m | BP28: 20 | BQ28: Não | BR28: Aberto | BS28: Aberto
A29: 28 | B29: 00064847620178260635 | C29: 1 | D29: 19/10/2017 | E29: LEYLA MARIA DA SILVA LACAZ | F29: Feminino | G29: 14ª Vara Criminal | H29: ALEANDRO SANTOS DE MELO | I29: 1 | J29: Via Pública | K29: Masculino | L29: 34042 | M29: 24 | N29: Branca | O29: Branco e amarelo | P29: Encaracolado | Q29: Veículo | R29: 44 porções. 150 g | S29: 150 | T29: 0 | U29: 0 | V29: 0 | W29: 0 | X29: 0 | Y29: 0 | Z29: 0 | AA29: 0 | AB29: 0 | AC29: Não | AD29: Não | AE29: Não | AF29: Não | AG29: Não | AH29: Não | AI29: Art. 33 | AJ29: Não | AK29: Confissão. Denúncia | AL29: Procedente | AM29: Condenação por tráfico | AN29: Art. 33 | AO29: NA | AP29: Não | AQ29: 5a | AR29: Não | AS29: Não | AT29: Não | AU29: Não | AV29: Não | AW29: Sim | AX29: Não | AY29: Não | AZ29: Não | BA29: Não | BB29: Não | BC29: Não | BD29: Não | BE29: Não | BF29: =IF(AZ29="Não","Sim","Não") -> Sim | BG29: =IF(AZ29="NA","Sim","Não") -> Não | BH29: Não | BI29: Sim total | BJ29: Sim (total ou parcial) | BK29: 1a 8m | BL29: 20 | BM29: NA | BN29: NA | BO29: 1a 8m | BP29: 20 | BQ29: Não | BR29: Aberto | BS29: Aberto
A30: 29 | B30: 00064847620178260635 | C30: 0 | D30: 19/10/2017 | E30: LEYLA MARIA DA SILVA LACAZ | F30: Feminino | G30: 14ª Vara Criminal | H30: GILSON DE SOUZA MARTINS | I30: 1 | J30: Via Pública | K30: Masculino | L30: 32828 | M30: 27 | N30: Branca | O30: Branco e amarelo | P30: Liso | Q30: Veículo | R30: 44 porções. 150 g | S30: 150 | T30: 0 | U30: 0 | V30: 0 | W30: 0 | X30: 0 | Y30: 0 | Z30: 0 | AA30: 0 | AB30: 0 | AC30: Não | AD30: Não | AE30: Não | AF30: Não | AG30: Não | AH30: Não | AI30: Art. 33 | AJ30: Não | AK30: Confissão. Denúncia | AL30: Procedente | AM30: Condenação por tráfico | AN30: Art. 33 | AO30: NA | AP30: Não | AQ30: 5a | AR30: Não | AS30: Não | AT30: Não | AU30: Não | AV30: Não | AW30: Sim | AX30: Não | AY30: Não | AZ30: Não | BA30: Não | BB30: Não | BC30: Não | BD30: Não | BE30: Não | BF30: =IF(AZ30="Não","Sim","Não") -> Sim | BG30: =IF(AZ30="NA","Sim","Não") -> Não | BH30: Não | BI30: Sim total | BJ30: Sim (total ou parcial) | BK30: 1a 8m | BL30: 20 | BM30: NA | BN30: NA | BO30: 1a 8m | BP30: 20 | BQ30: Não | BR30: Aberto | BS30: Aberto
A31: 30 | B31: 00275320320178260050 | C31: 1 | D31: 28/08/2017 | E31: Waldir Calciolari | F31: Masculino | G31: 25ª Vara Criminal | H31: GUSTAVO ALVES | I31: 1 | J31: Residência | K31: Masculino | L31: 34245 | M31: 23 | N31: Branca | O31: Branco e amarelo | P31: Liso | Q31: Veículo. Dichavador. Balança. Celular. Pote. Dinheiro R$ 462,00 | R31: 44 porções. 2 tijolos. 1034,7 g (total) | S31: 1034.7 | T31: 0 | U31: 0 | V31: 0 | W31: 0 | X31: 0 | Y31: 0 | Z31: 0 | AA31: 0 | AB31: 0 | AC31: Não | AD31: Não | AE31: Não | AF31: Não | AG31: Não | AH31: Não | AI31: Art. 33. Art. 35 | AJ31: Não | AK31: Não há | AL31: Parcialmente procedente | AM31: Condenação por tráfico | AN31: Art. 33 | AO31: NA | AP31: Não | AQ31: 5a | AR31: Não | AS31: Não | AT31: Não | AU31: Não | AV31: Não | AW31: Sim | AX31: Não | AY31: Não | AZ31: Não | BA31: Não | BB31: Não | BC31: Não | BD31: Não | BE31: Não | BF31: =IF(AZ31="Não","Sim","Não") -> Sim | BG31: =IF(AZ31="NA","Sim","Não") -> Não | BH31: Não | BI31: Sim total | BJ31: Sim (total ou parcial) | BK31: 1a 8m | BL31: 20 | BM31: NA | BN31: NA | BO31: 1a 8m | BP31: 20 | BQ31: Não | BR31: Aberto | BS31: Aberto
A32: 31 | B32: 00275320320178260050 | C32: 0 | D32: 28/08/2017 | E32: Waldir Calciolari | F32: Masculino | G32: 25ª Vara Criminal | H32: LARISSA EVELYN PEREIA SIQUEIRA | I32: 1 | J32: Residência | K32: Feminino | L32: 35782 | M32: 19 | N32: Parda | O32: Negros, pardos e outros | P32: Liso | Q32: Veículo. Dichavador. Balança. Celular. Pote. Dinheiro R$ 462,00 | R32: 44 porções. 2 tijolos. 1034,7 g (total) | S32: 1034.7 | T32: 0 | U32: 0 | V32: 0 | W32: 0 | X32: 0 | Y32: 0 | Z32: 0 | AA32: 0 | AB32: 0 | AC32: Não | AD32: Não | AE32: Não | AF32: Não | AG32: Não | AH32: Não | AI32: Art. 33. Art. 35 | AJ32: Não | AK32: Não há | AL32: Parcialmente procedente | AM32: Condenação por tráfico | AN32: Art. 33 | AO32: NA | AP32: Não | AQ32: 5a | AR32: Não | AS32: Não | AT32: Não | AU32: Não | AV32: Não | AW32: Sim | AX32: Não | AY32: Não | AZ32: Não | BA32: Não | BB32: Não | BC32: Não | BD32: Não | BE32: Não | BF32: =IF(AZ32="Não","Sim","Não") -> Sim | BG32: =IF(AZ32="NA","Sim","Não") -> Não | BH32: Não | BI32: Sim total | BJ32: Sim (total ou parcial) | BK32: 1a 8m | BL32: 20 | BM32: NA | BN32: NA | BO32: 1a 8m | BP32: 20 | BQ32: Não | BR32: Aberto | BS32: Aberto
A33: 32 | B33: 00193936220178260050 | C33: 1 | D33: 05/09/2017 | E33: TERESA DE ALMEIDA RIBEIRO MAGALHAES | F33: Feminino | G33: 18ª Vara Criminal | H33: UELDER SACRAMENTO SANTOS | I33: 1 | J33: Via Pública | K33: Masculino | L33: 34757 | M33: 22 | N33: Parda | O33: Negros, pardos e outros | P33: Carapinha | Q33: Dinheiro R$ 69,00 | R33: 6 porções. 21,1 g | S33: 21.1 | T33: 0 | U33: 0 | V33: 0 | W33: 0 | X33: 0 | Y33: 0 | Z33: 0 | AA33: 0 | AB33: 0 | AC33: Não | AD33: Não | AE33: Não | AF33: Não | AG33: Não | AH33: Não | AI33: Art. 33 | AJ33: Não | AK33: Denúncia | AL33: Procedente | AM33: Condenação por tráfico | AN33: Art. 33 | AO33: NA | AP33: Não | AQ33: 5a | AR33: Não | AS33: Não | AT33: Não | AU33: Não | AV33: Não | AW33: Sim | AX33: Não | AY33: Não | AZ33: Não | BA33: Não | BB33: Não | BC33: Não | BD33: Não | BE33: Não | BF33: =IF(AZ33="Não","Sim","Não") -> Sim | BG33: =IF(AZ33="NA","Sim","Não") -> Não | BH33: Não | BI33: Sim total | BJ33: Sim (total ou parcial) | BK33: 1a 8m | BL33: 20 | BM33: NA | BN33: NA | BO33: 1a 8m | BP33: 20 | BQ33: Sim | BR33: NA | BS33: NA
A34: 33 | B34: 00022793820168260635 | C34: 1 | D34: 08/05/2017 | E34: Carla de Oliveira Pinto Ferrari | F34: Feminino | G34: 20ª Vara Criminal | H34: JOHN GWAKZING | I34: 1 | J34: Restaurante e afins | K34: Masculino | L34: 32802 | M34: 27 | N34: Preta | O34: Negros, pardos e outros | P34: Não disponível | Q34: Dinheiro R$ 70,00 | R34: 8 porções. 18,3 g | S34: 18.3 | T34: 0 | U34: 0 | V34: 0 | W34: 0 | X34: 0 | Y34: 0 | Z34: 0 | AA34: 0 | AB34: 0 | AC34: Não | AD34: Não | AE34: Não | AF34: Não | AG34: Não | AH34: Não | AI34: Art. 33 | AJ34: Não | AK34: Nacionalidade. Local de tráfico | AL34: Procedente | AM34: Condenação por tráfico | AN34: Art. 33 | AO34: NA | AP34: Não | AQ34: 5a | AR34: Não | AS34: Não | AT34: Não | AU34: Não | AV34: Não | AW34: Sim | AX34: Não | AY34: Não | AZ34: Não | BA34: Não | BB34: Não | BC34: Não | BD34: Não | BE34: Não | BF34: =IF(AZ34="Não","Sim","Não") -> Sim | BG34: =IF(AZ34="NA","Sim","Não") -> Não | BH34: Não | BI34: Sim total | BJ34: Sim (total ou parcial) | BK34: 1a 8m | BL34: 20 | BM34: NA | BN34: NA | BO34: 1a 8m | BP34: 20 | BQ34: Não | BR34: Fechado | BS34: Fechado
A35: 34 | B35: 00129087120168260635 | C35: 1 | D35: 42937 | E35: Fernanda Galizia Noriega | F35: Feminino | G35: 28ª Vara Criminal | H35: MAYARA MARCELINO SANTA RITA | I35: 1 | J35: Via Pública | K35: Feminino | L35: 35074 | M35: 21 | N35: Parda | O35: Negros, pardos e outros | P35: Outros | Q35: Bolsa. Celular. Dinheiro R$ 73,00 | R35: 86 porções. 106,1 g | S35: 106.1 | T35: 0 | U35: 0 | V35: 0 | W35: 0 | X35: 0 | Y35: 0 | Z35: 0 | AA35: 0 | AB35: 0 | AC35: Não | AD35: Não | AE35: Não | AF35: Não | AG35: Não | AH35: Não | AI35: Art. 33 | AJ35: Não | AK35: Local de tráfico. Confissão | AL35: Procedente | AM35: Condenação por tráfico | AN35: Art. 33 | AO35: NA | AP35: Não | AQ35: 5a | AR35: Não | AS35: Não | AT35: Não | AU35: Não | AV35: Não | AW35: Sim | AX35: Não | AY35: Não | AZ35: Não | BA35: Não | BB35: Não | BC35: Não | BD35: Não | BE35: Não | BF35: =IF(AZ35="Não","Sim","Não") -> Sim | BG35: =IF(AZ35="NA","Sim","Não") -> Não | BH35: Não | BI35: Sim total | BJ35: Sim (total ou parcial) | BK35: 1a 8m | BL35: 20 | BM35: NA | BN35: NA | BO35: 1a 8m | BP35: 20 | BQ35: Sim | BR35: NA | BS35: NA
A36: 35 | B36: 00959450520168260050 | C36: 1 | D36: 30/05/2017 | E36: MARCO ANTONIO MARTIN VARGAS | F36: Masculino | G36: 32ª Vara Criminal | H36: CAIQUE MATIAS DOS SANTOS | I36: 1 | J36: Via Pública | K36: Masculino | L36: 34902 | M36: 21 | N36: Branca | O36: Branco e amarelo | P36: Liso | Q36: Dinheiro R$ 30,00 | R36: 0 | S36: 0 | T36: 10 porções. 7,3 g | U36: 7.3 | V36: 0 | W36: 0 | X36: 0 | Y36: 0 | Z36: 0 | AA36: 0 | AB36: 0 | AC36: Não | AD36: Não | AE36: Não | AF36: Não | AG36: Não | AH36: Não | AI36: Art. 33 | AJ36: Não | AK36: Local de tráfico. Denúncia anônima | AL36: Procedente | AM36: Condenação por tráfico | AN36: Art. 33 | AO36: NA | AP36: Não | AQ36: 5a | AR36: Não | AS36: Não | AT36: Não | AU36: Não | AV36: Não | AW36: Sim | AX36: Não | AY36: Não | AZ36: Não | BA36: Não | BB36: Não | BC36: Não | BD36: Não | BE36: Não | BF36: =IF(AZ36="Não","Sim","Não") -> Sim | BG36: =IF(AZ36="NA","Sim","Não") -> Não | BH36: Não | BI36: Sim total | BJ36: Sim (total ou parcial) | BK36: 1a 8m | BL36: 20 | BM36: NA | BN36: NA | BO36: 1a 8m | BP36: 20 | BQ36: Sim | BR36: NA | BS36: NA
A37: 36 | B37: 00356275620168260050 | C37: 1 | D37: 29/03/2017 | E37: José Fernandes Freitas Neto | F37: Masculino | G37: 6ª Vara Criminal | H37: LUIZ HENRIQUE DE OLIVEIRA ALMEIDA | I37: 1 | J37: Via Pública | K37: Masculino | L37: 35345 | M37: 20 | N37: Parda | O37: Negros, pardos e outros | P37: Carapinha | Q37: Estojo. Dinheiro R$ 63,00 | R37: 0 | S37: 0 | T37: 109 porções. 44,3 g | U37: 44.3 | V37: 0 | W37: 0 | X37: 0 | Y37: 0 | Z37: 0 | AA37: 0 | AB37: 0 | AC37: Não | AD37: Não | AE37: Não | AF37: Não | AG37: Não | AH37: Não | AI37: Art. 33. Art. 35 | AJ37: Não | AK37: Local de tráfico. Confissão informal. Confissão | AL37: Parcialmente procedente | AM37: Condenação por tráfico | AN37: Art. 33 | AO37: NA | AP37: Não | AQ37: 5a | AR37: Não | AS37: Não | AT37: Não | AU37: Não | AV37: Não | AW37: Sim | AX37: Não | AY37: Não | AZ37: Não | BA37: Não | BB37: Não | BC37: Não | BD37: Não | BE37: Não | BF37: =IF(AZ37="Não","Sim","Não") -> Sim | BG37: =IF(AZ37="NA","Sim","Não") -> Não | BH37: Não | BI37: Sim total | BJ37: Sim (total ou parcial) | BK37: 1a 8m | BL37: 20 | BM37: NA | BN37: NA | BO37: 1a 8m | BP37: 20 | BQ37: Não | BR37: Aberto | BS37: Aberto
A38: 37 | B38: 00356275620168260050 | C38: 0 | D38: 29/03/2017 | E38: José Fernandes Freitas Neto | F38: Masculino | G38: 6ª Vara Criminal | H38: MELISSA FERNANDES OLIVEIRA PEREIRA | I38: 1 | J38: Via Pública | K38: Feminino | L38: 34211 | M38: 23 | N38: Branca | O38: Branco e amarelo | P38: Liso | Q38: Estojo. Dinheiro R$ 63,00 | R38: 0 | S38: 0 | T38: 109 porções. 44,3 g | U38: 44.3 | V38: 0 | W38: 0 | X38: 0 | Y38: 0 | Z38: 0 | AA38: 0 | AB38: 0 | AC38: Não | AD38: Não | AE38: Não | AF38: Não | AG38: Não | AH38: Não | AI38: Art. 33. Art. 35 | AJ38: Não | AK38: Local de tráfico. Confissão informal. Confissão | AL38: Parcialmente procedente | AM38: Condenação por tráfico | AN38: Art. 33 | AO38: NA | AP38: Não | AQ38: 5a | AR38: Não | AS38: Não | AT38: Não | AU38: Não | AV38: Não | AW38: Sim | AX38: Não | AY38: Não | AZ38: Não | BA38: Não | BB38: Não | BC38: Não | BD38: Não | BE38: Não | BF38: =IF(AZ38="Não","Sim","Não") -> Sim | BG38: =IF(AZ38="NA","Sim","Não") -> Não | BH38: Não | BI38: Sim total | BJ38: Sim (total ou parcial) | BK38: 1a 8m | BL38: 20 | BM38: NA | BN38: NA | BO38: 1a 8m | BP38: 20 | BQ38: Não | BR38: Aberto | BS38: Aberto
A39: 38 | B39: 00118000720168260635 | C39: 1 | D39: 03/07/2017 | E39: José Fernandes Freitas Neto | F39: Masculino | G39: 6ª Vara Criminal | H39: DAVID RIBEIRO | I39: 1 | J39: Área não ocupada | K39: Masculino | L39: 32199 | M39: 29 | N39: Parda | O39: Negros, pardos e outros | P39: Carapinha | Q39: Dinheiro R$ 33,00 | R39: 18 porções. 44,6 g | S39: 44.6 | T39: 11 porções. 6,2 g | U39: 6.2 | V39: 0 | W39: 0 | X39: 0 | Y39: 0 | Z39: 0 | AA39: 0 | AB39: 0 | AC39: Não | AD39: Não | AE39: Não | AF39: Não | AG39: Não | AH39: Não | AI39: Art. 33 | AJ39: Não | AK39: Local de tráfico. Denúncia. Confissão informal. Confissão. Preso no momento da sentença | AL39: Procedente | AM39: Condenação por tráfico | AN39: Art. 33 | AO39: NA | AP39: Sim. Antecedentes | AQ39: Não expresso | AR39: Não | AS39: Não | AT39: Confissão | AU39: Sim | AV39: Não | AW39: Não | AX39: Não | AY39: Sim | AZ39: Não | BA39: Não | BB39: Não | BC39: Não | BD39: Não | BE39: Não | BF39: =IF(AZ39="Não","Sim","Não") -> Sim | BG39: =IF(AZ39="NA","Sim","Não") -> Não | BH39: Não | BI39: Sim total | BJ39: Sim (total ou parcial) | BK39: 1a 8m | BL39: 20 | BM39: NA | BN39: NA | BO39: 1a 8m | BP39: 20 | BQ39: Não | BR39: Aberto | BS39: Aberto
A40: 39 | B40: 00832380520168260050 | C40: 1 | D40: 14/12/2017 | E40: Edison Tetsuzo Namba | F40: Masculino | G40: 31ª Vara Criminal | H40: LUIS FERNANDO SALES SANTOS | I40: 1 | J40: Via Pública | K40: Masculino | L40: 35904 | M40: 19 | N40: Branca | O40: Branco e amarelo | P40: Não disponível | Q40: Celular. Dinheiro R$ 7,00 | R40: 9 porções. 16,7 g | S40: 16.7 | T40: 11 porções. 8,1 g | U40: 8.1 | V40: 0 | W40: 0 | X40: 0 | Y40: 0 | Z40: 0 | AA40: 0 | AB40: 0 | AC40: Não | AD40: Não | AE40: Não | AF40: Não | AG40: Não | AH40: Não | AI40: Art. 33 | AJ40: Não | AK40: Confissão. Atitude suspeita. Confissão informal. Local de tráfico. Preso no momento da sentença | AL40: Procedente | AM40: Condenação por tráfico | AN40: Art. 33 | AO40: NA | AP40: Não | AQ40: 5a | AR40: Não | AS40: Não | AT40: Não | AU40: Não | AV40: Não | AW40: Sim | AX40: Não | AY40: Não | AZ40: Não | BA40: Não | BB40: Não | BC40: Não | BD40: Não | BE40: Não | BF40: =IF(AZ40="Não","Sim","Não") -> Sim | BG40: =IF(AZ40="NA","Sim","Não") -> Não | BH40: Não | BI40: Sim total | BJ40: Sim (total ou parcial) | BK40: 1a 8m | BL40: 20 | BM40: NA | BN40: NA | BO40: 1a 8m | BP40: 20 | BQ40: Não | BR40: Aberto | BS40: Aberto
A41: 40 | B41: 00181715920178260050 | C41: 0 | D41: 26/09/2017 | E41: Carla de Oliveira Pinto Ferrari | F41: Feminino | G41: 20ª Vara Criminal | H41: JEFFERSON OLIVEIRA LEITE | I41: 1 | J41: Via Pública | K41: Masculino | L41: 36055 | M41: 19 | N41: Branca | O41: Branco e amarelo | P41: Ondulado | Q41: Dinheiro R$ 33,00 | R41: 5 porções. 6,6 g | S41: 6.6 | T41: 119 porções. 95,1 g | U41: 95.1 | V41: 0 | W41: 0 | X41: 0 | Y41: 0 | Z41: 0 | AA41: 0 | AB41: Lança-perfume. 2 frascos. 22 ml | AC41: Não | AD41: Não | AE41: Não | AF41: Não | AG41: Sim | AH41: Não | AI41: Art. 33. Art. 35 | AJ41: Não | AK41: Confissão. Local de tráfico | AL41: Parcialmente procedente | AM41: Condenação por tráfico | AN41: Art. 33 | AO41: NA | AP41: Sim. Natureza | AQ41: 5a 10m | AR41: Não | AS41: Não | AT41: Confissão. Menoridade | AU41: Sim | AV41: Sim | AW41: Não | AX41: Não | AY41: Sim | AZ41: Não | BA41: Não | BB41: Não | BC41: Não | BD41: Não | BE41: Não | BF41: =IF(AZ41="Não","Sim","Não") -> Sim | BG41: =IF(AZ41="NA","Sim","Não") -> Não | BH41: Não | BI41: Sim total | BJ41: Sim (total ou parcial) | BK41: 1a 8m | BL41: 20 | BM41: NA | BN41: NA | BO41: 1a 8m | BP41: 20 | BQ41: Não | BR41: Aberto | BS41: Aberto
A42: 41 | B42: 00181715920178260050 | C42: 1 | D42: 26/09/2017 | E42: Carla de Oliveira Pinto Ferrari | F42: Feminino | G42: 20ª Vara Criminal | H42: NATALÍCIO GONÇALVES DE AZEVEDO | I42: 1 | J42: Via Pública | K42: Masculino | L42: 32985 | M42: 27 | N42: Parda | O42: Negros, pardos e outros | P42: Ondulado | Q42: Dinheiro R$ 33,00 | R42: 5 porções. 6,6 g | S42: 6.6 | T42: 119 porções. 95,1 g | U42: 95.1 | V42: 0 | W42: 0 | X42: 0 | Y42: 0 | Z42: 0 | AA42: 0 | AB42: Lança-perfume. 2 frascos. 22 ml | AC42: Não | AD42: Não | AE42: Não | AF42: Não | AG42: Sim | AH42: Não | AI42: Art. 33. Art. 35 | AJ42: Não | AK42: Confissão. Local de tráfico | AL42: Parcialmente procedente | AM42: Condenação por tráfico | AN42: Art. 33 | AO42: NA | AP42: Sim. Natureza | AQ42: 5a 10m | AR42: Não | AS42: Não | AT42: Confissão | AU42: Sim | AV42: Não | AW42: Não | AX42: Não | AY42: Sim | AZ42: Não | BA42: Não | BB42: Não | BC42: Não | BD42: Não | BE42: Não | BF42: =IF(AZ42="Não","Sim","Não") -> Sim | BG42: =IF(AZ42="NA","Sim","Não") -> Não | BH42: Não | BI42: Sim total | BJ42: Sim (total ou parcial) | BK42: 1a 8m | BL42: 20 | BM42: NA | BN42: NA | BO42: 1a 8m | BP42: 20 | BQ42: Não | BR42: Aberto | BS42: Aberto
A43: 42 | B43: 00912876920158260050 | C43: 1 | D43: 42909 | E43: Fernando Cesar Carrari | F43: Masculino | G43: 26ª Vara Criminal | H43: VINICIUS LIMA FERREIRA DA SILVA | I43: 1 | J43: Via Pública | K43: Masculino | L43: 34695 | M43: 22 | N43: Branca | O43: Branco e amarelo | P43: Carapinha | Q43: Dinheiro R$ 130,00 | R43: 0 | S43: 0 | T43: 12 porções. 9,2 g | U43: 9.2 | V43: 0 | W43: 0 | X43: 0 | Y43: 0 | Z43: 0 | AA43: 0 | AB43: 0 | AC43: Não | AD43: Não | AE43: Não | AF43: Não | AG43: Não | AH43: Não | AI43: Art. 33 | AJ43: Não | AK43: Atitude suspeita. Confissão informal. Local de tráfico. Preso no momento da sentença | AL43: Procedente | AM43: Condenação por tráfico | AN43: Art. 33 | AO43: NA | AP43: Não | AQ43: 5a | AR43: Não | AS43: Não | AT43: Não | AU43: Não | AV43: Não | AW43: Sim | AX43: Não | AY43: Não | AZ43: Não | BA43: Não | BB43: Não | BC43: Não | BD43: Não | BE43: Não | BF43: =IF(AZ43="Não","Sim","Não") -> Sim | BG43: =IF(AZ43="NA","Sim","Não") -> Não | BH43: Não | BI43: Sim total | BJ43: Sim (total ou parcial) | BK43: 1a 8m | BL43: 20 | BM43: NA | BN43: NA | BO43: 1a 8m | BP43: 20 | BQ43: Não | BR43: Fechado | BS43: Fechado
A44: 43 | B44: 00634812520168260050 | C44: 1 | D44: 12/04/2017 | E44: Isaura Cristina Barreira | F44: Feminino | G44: 30ª Vara Criminal | H44: CEZAR LUIZ DE PAULA SILVA | I44: 1 | J44: Via Pública | K44: Masculino | L44: 32249 | M44: 29 | N44: Preta | O44: Negros, pardos e outros | P44: Carapinha | Q44: Celular. Dinheiro R$ 308,00 | R44: 123 porções. 267,7 g | S44: 267.7 | T44: 152 porções. 55,2 g | U44: 55.2 | V44: 0 | W44: 0 | X44: 0 | Y44: 0 | Z44: 0 | AA44: 0 | AB44: 0 | AC44: Não | AD44: Não | AE44: Não | AF44: Não | AG44: Não | AH44: Não | AI44: Art. 33 | AJ44: Não | AK44: Local de tráfico | AL44: Procedente | AM44: Condenação por tráfico | AN44: Art. 33 | AO44: NA | AP44: Não | AQ44: 5a | AR44: Não | AS44: Não | AT44: Não | AU44: Não | AV44: Não | AW44: Sim | AX44: Não | AY44: Não | AZ44: Não | BA44: Não | BB44: Não | BC44: Não | BD44: Não | BE44: Não | BF44: =IF(AZ44="Não","Sim","Não") -> Sim | BG44: =IF(AZ44="NA","Sim","Não") -> Não | BH44: Não | BI44: Sim total | BJ44: Sim (total ou parcial) | BK44: 1a 8m | BL44: 20 | BM44: NA | BN44: NA | BO44: 1a 8m | BP44: 20 | BQ44: Não | BR44: Aberto | BS44: Aberto
A45: 44 | B45: 00101026320168260635 | C45: 1 | D45: 42937 | E45: Fernando Cesar Carrari | F45: Masculino | G45: 26ª Vara Criminal | H45: LEONARDO MATHEUS DE CARVALHO | I45: 1 | J45: Via Pública | K45: Masculino | L45: 35959 | M45: 19 | N45: Branca | O45: Branco e amarelo | P45: Carapinha | Q45: Dinheiro R$ 119,00 | R45: 8 porções. 12,4 g | S45: 12.4 | T45: 17 porções. 4,7 g | U45: 4.7 | V45: 0 | W45: 0 | X45: 0 | Y45: 0 | Z45: 0 | AA45: 0 | AB45: 0 | AC45: Não | AD45: Não | AE45: Não | AF45: Não | AG45: Não | AH45: Não | AI45: Art. 33 | AJ45: Não | AK45: Denúncia anônima. Local de tráfico. Confissão informal. Preso no momento da sentença | AL45: Procedente | AM45: Condenação por tráfico | AN45: Art. 33 | AO45: NA | AP45: Não | AQ45: 5a | AR45: Não | AS45: Não | AT45: Não | AU45: Não | AV45: Não | AW45: Sim | AX45: Não | AY45: Não | AZ45: Não | BA45: Não | BB45: Não | BC45: Não | BD45: Não | BE45: Não | BF45: =IF(AZ45="Não","Sim","Não") -> Sim | BG45: =IF(AZ45="NA","Sim","Não") -> Não | BH45: Não | BI45: Sim total | BJ45: Sim (total ou parcial) | BK45: 1a 8m | BL45: 20 | BM45: NA | BN45: NA | BO45: 1a 8m | BP45: 20 | BQ45: Não | BR45: Fechado | BS45: Fechado
A46: 45 | B46: 01058494920168260050 | C46: 1 | D46: 22/08/2017 | E46: ALESSANDRA TEIXEIRA MIGUEL | F46: Feminino | G46: 32ª Vara Criminal | H46: VALTER ALVES SANTOS | I46: 1 | J46: Via Pública | K46: Masculino | L46: 32392 | M46: 28 | N46: Parda | O46: Negros, pardos e outros | P46: Carapinha | Q46: Dinheiro R$ 15,00 | R46: 26 porções. 56,1 g | S46: 56.1 | T46: 2 porções. 0,7 g | U46: 0.7 | V46: 0 | W46: 0 | X46: 0 | Y46: 0 | Z46: 0 | AA46: 0 | AB46: 0 | AC46: Não | AD46: Não | AE46: Não | AF46: Não | AG46: Não | AH46: Não | AI46: Art. 33 | AJ46: Não | AK46: Local de tráfico. Confissão informal. Atitude suspeita | AL46: Procedente | AM46: Condenação por tráfico | AN46: Art. 33 | AO46: NA | AP46: Não | AQ46: 5a | AR46: Não | AS46: Não | AT46: Não | AU46: Não | AV46: Não | AW46: Sim | AX46: Não | AY46: Não | AZ46: Não | BA46: Não | BB46: Não | BC46: Não | BD46: Não | BE46: Não | BF46: =IF(AZ46="Não","Sim","Não") -> Sim | BG46: =IF(AZ46="NA","Sim","Não") -> Não | BH46: Não | BI46: Sim total | BJ46: Sim (total ou parcial) | BK46: 1a 8m | BL46: 20 | BM46: NA | BN46: NA | BO46: 1a 8m | BP46: 20 | BQ46: Sim | BR46: NA | BS46: NA
A47: 46 | B47: 00174033620178260050 | C47: 1 | D47: 26/04/2017 | E47: Pedro Luiz Fernandes Nery Rafael | F47: Masculino | G47: 5ª Vara Criminal | H47: IVAN DOS SANTOS FERMINO | I47: 1 | J47: Via Pública | K47: Masculino | L47: 32264 | M47: 29 | N47: Parda | O47: Negros, pardos e outros | P47: Não disponível | Q47: Sacola. Celular | R47: 4 porções. 183,9 g | S47: 183.9 | T47: 2 porções. 198,9 g | U47: 198.9 | V47: 0 | W47: 0 | X47: 0 | Y47: 0 | Z47: 0 | AA47: 0 | AB47: 0 | AC47: Não | AD47: Não | AE47: Não | AF47: Não | AG47: Não | AH47: Não | AI47: Art. 33 | AJ47: Não | AK47: Preso no momento da sentença.Confissão informal. Confissão | AL47: Procedente | AM47: Condenação por tráfico | AN47: Art. 33 | AO47: NA | AP47: Sim. Quantidade. Variedade | AQ47: 6a 3m | AR47: Não | AS47: Não | AT47: Confissão | AU47: Sim | AV47: Não | AW47: Não | AX47: Não | AY47: Sim | AZ47: Não | BA47: Não | BB47: Não | BC47: Não | BD47: Não | BE47: Não | BF47: =IF(AZ47="Não","Sim","Não") -> Sim | BG47: =IF(AZ47="NA","Sim","Não") -> Não | BH47: Não | BI47: Sim total | BJ47: Sim (total ou parcial) | BK47: 1a 8m | BL47: 20 | BM47: NA | BN47: NA | BO47: 1a 8m | BP47: 20 | BQ47: Sim | BR47: NA | BS47: NA
A48: 47 | B48: 00075442120168260635 | C48: 1 | D48: 20/01/2017 | E48: Erica Regina Colmenero Coimbra | F48: Feminino | G48: 2ª Vara Criminal | H48: FERNANDO DE SOUZA OLIVEIRA | I48: 1 | J48: Via Pública | K48: Masculino | L48: 35006 | M48: 21 | N48: Preta | O48: Negros, pardos e outros | P48: Carapinha | Q48: Veículo. Pochete. Celular. Dinheiro R$ 2000,00 | R48: 0 | S48: 0 | T48: 204 porções. 165 g | U48: 165 | V48: 0 | W48: 0 | X48: 0 | Y48: 0 | Z48: 0 | AA48: 0 | AB48: 0 | AC48: Não | AD48: Não | AE48: Não | AF48: Não | AG48: Não | AH48: Não | AI48: Art. 33 | AJ48: Art. 333 CP | AK48: Confissão informal. Preso no momento da sentença | AL48: Parcialmente procedente | AM48: Condenação por tráfico | AN48: Art. 33 | AO48: Não | AP48: Não | AQ48: 5a | AR48: Não | AS48: Não | AT48: Não | AU48: Não | AV48: Não | AW48: Sim | AX48: Não | AY48: Não | AZ48: Não | BA48: Não | BB48: Não | BC48: Não | BD48: Não | BE48: Não | BF48: =IF(AZ48="Não","Sim","Não") -> Sim | BG48: =IF(AZ48="NA","Sim","Não") -> Não | BH48: Não | BI48: Sim total | BJ48: Sim (total ou parcial) | BK48: 1a 8m | BL48: 20 | BM48: NA | BN48: NA | BO48: 1a 8m | BP48: 20 | BQ48: Não | BR48: Fechado | BS48: Fechado
A49: 48 | B49: 00075442120168260635 | C49: 0 | D49: 20/01/2017 | E49: Erica Regina Colmenero Coimbra | F49: Feminino | G49: 2ª Vara Criminal | H49: FELIPE RODRIGO JACO | I49: 1 | J49: Via Pública | K49: Masculino | L49: 33137 | M49: 26 | N49: Branca | O49: Branco e amarelo | P49: Liso | Q49: Veículo. Pochete. Celular. Dinheiro R$ 2000,00 | R49: 0 | S49: 0 | T49: 204 porções. 165 g | U49: 165 | V49: 0 | W49: 0 | X49: 0 | Y49: 0 | Z49: 0 | AA49: 0 | AB49: 0 | AC49: Não | AD49: Não | AE49: Não | AF49: Não | AG49: Não | AH49: Não | AI49: Art. 33 | AJ49: Art. 333 CP | AK49: Confissão informal. Preso no momento da sentença | AL49: Procedente | AM49: Condenação por tráfico | AN49: Art. 33 | AO49: Art. 333 CP | AP49: Não | AQ49: 5a | AR49: Não | AS49: Não | AT49: Não | AU49: Não | AV49: Não | AW49: Sim | AX49: Não | AY49: Não | AZ49: Não | BA49: Não | BB49: Não | BC49: Não | BD49: Não | BE49: Não | BF49: =IF(AZ49="Não","Sim","Não") -> Sim | BG49: =IF(AZ49="NA","Sim","Não") -> Não | BH49: Não | BI49: Sim total | BJ49: Sim (total ou parcial) | BK49: 1a 8m | BL49: 20 | BM49: NA | BN49: 2a | BO49: 3a 8m | BP49: 44 | BQ49: Não | BR49: Fechado | BS49: Fechado
A50: 49 | B50: 00048551320168260050 | C50: 1 | D50: 42942 | E50: Augusto Antonini | F50: Masculino | G50: 28ª Vara Criminal | H50: CLAUDINEIA ARAUJO DE CARVALHO | I50: 1 | J50: Via Pública | K50: Feminino | L50: 31929 | M50: 30 | N50: Parda | O50: Negros, pardos e outros | P50: Carapinha | Q50: Dinheiro R$21,20 | R50: 31 porções. 54,3 g | S50: 54.3 | T50: 23 porções. 12,2 g | U50: 12.2 | V50: 0 | W50: 0 | X50: 0 | Y50: 0 | Z50: 0 | AA50: 0 | AB50: 0 | AC50: Não | AD50: Não | AE50: Não | AF50: Não | AG50: Não | AH50: Não | AI50: Art. 33 | AJ50: Não | AK50: Não há | AL50: Procedente | AM50: Condenação por tráfico | AN50: Art. 33 | AO50: NA | AP50: Não | AQ50: 5a | AR50: Não | AS50: Não | AT50: Não | AU50: Não | AV50: Não | AW50: Sim | AX50: Não | AY50: Não | AZ50: Não | BA50: Não | BB50: Não | BC50: Não | BD50: Não | BE50: Não | BF50: =IF(AZ50="Não","Sim","Não") -> Sim | BG50: =IF(AZ50="NA","Sim","Não") -> Não | BH50: Não | BI50: Sim total | BJ50: Sim (total ou parcial) | BK50: 1a 8m | BL50: 20 | BM50: NA | BN50: NA | BO50: 1a 8m | BP50: 20 | BQ50: Não | BR50: Fechado | BS50: Fechado
A51: 50 | B51: 00317021820178260050 | C51: 1 | D51: 31/07/2017 | E51: Edison Tetsuzo Namba | F51: Masculino | G51: 31ª Vara Criminal | H51: IGOR OLIVEIRA DE SOUZA | I51: 1 | J51: Residência | K51: Masculino | L51: 36224 | M51: 18 | N51: Parda | O51: Negros, pardos e outros | P51: Não disponível | Q51: Sacola. Similuco de arma de fogo. Maquina de cartão. Violão. Bateria. Estojo. Celular | R51: 17 porções. 47 g | S51: 47 | T51: 23 porções. 22 g | U51: 22 | V51: 0 | W51: 0 | X51: 0 | Y51: 0 | Z51: 0 | AA51: 0 | AB51: 0 | AC51: Não | AD51: Não | AE51: Não | AF51: Não | AG51: Não | AH51: Não | AI51: Art. 33 | AJ51: Art. 180 CP | AK51: Local de tráfico. Denúncia anônima. Confissão informal | AL51: Procedente | AM51: Condenação por tráfico | AN51: Art. 33 | AO51: Art. 180 CP | AP51: Não | AQ51: 5a | AR51: Não | AS51: Não | AT51: Não | AU51: Não | AV51: Não | AW51: Sim | AX51: Não | AY51: Não | AZ51: Não | BA51: Não | BB51: Não | BC51: Não | BD51: Não | BE51: Não | BF51: =IF(AZ51="Não","Sim","Não") -> Sim | BG51: =IF(AZ51="NA","Sim","Não") -> Não | BH51: Não | BI51: Sim total | BJ51: Sim (total ou parcial) | BK51: 1a 8m | BL51: 20 | BM51: NA | BN51: 1a | BO51: 2a 8m | BP51: 32 | BQ51: Sim | BR51: NA | BS51: NA
A52: 51 | B52: 00433509220178260050 | C52: 1 | D52: 01/11/2017 | E52: ANDRE LUIZ DA SILVA DA CUNHA | F52: Masculino | G52: 32ª Vara Criminal | H52: LUCAS GOMES PEREIRA | I52: 1 | J52: Residência | K52: Masculino | L52: 35398 | M52: 20 | N52: Preta | O52: Negros, pardos e outros | P52: Não disponível | Q52: Caderno. Dinheiro R$ 212,00 | R52: 10 porções. 19,3 g | S52: 19.3 | T52: 235 porções. 45,4 g | U52: 45.4 | V52: 0 | W52: 0 | X52: 0 | Y52: 0 | Z52: 0 | AA52: 0 | AB52: 0 | AC52: Não | AD52: Não | AE52: Não | AF52: Não | AG52: Não | AH52: Não | AI52: Art. 33 | AJ52: Não | AK52: Local de tráfico. Confissão informal. Denúncia anônima | AL52: Procedente | AM52: Condenação por tráfico | AN52: Art. 33 | AO52: NA | AP52: Não | AQ52: 5a | AR52: Não | AS52: Não | AT52: Não | AU52: Não | AV52: Não | AW52: Sim | AX52: Não | AY52: Não | AZ52: Não | BA52: Não | BB52: Não | BC52: Não | BD52: Não | BE52: Não | BF52: =IF(AZ52="Não","Sim","Não") -> Sim | BG52: =IF(AZ52="NA","Sim","Não") -> Não | BH52: Não | BI52: Sim total | BJ52: Sim (total ou parcial) | BK52: 1a 8m | BL52: 20 | BM52: NA | BN52: NA | BO52: 1a 8m | BP52: 20 | BQ52: Sim | BR52: NA | BS52: NA
A53: 52 | B53: 00067969520168260050 | C53: 1 | D53: 05/05/2017 | E53: MARCO ANTONIO MARTIN VARGAS | F53: Masculino | G53: 32ª Vara Criminal | H53: VINICIUS FABIANO GARCIA | I53: 1 | J53: Via Pública | K53: Masculino | L53: 34564 | M53: 22 | N53: Parda | O53: Negros, pardos e outros | P53: Encaracolado | Q53: Dinheiro R$ 40,00 | R53: 0 | S53: 0 | T53: 24 porções. 23,2 g | U53: 23.2 | V53: 0 | W53: 0 | X53: 0 | Y53: 0 | Z53: 0 | AA53: 0 | AB53: 0 | AC53: Não | AD53: Não | AE53: Não | AF53: Não | AG53: Não | AH53: Não | AI53: Art. 33 | AJ53: Não | AK53: Local de tráfico. Confissão. Preso no momento da sentença. Atitude suspeita | AL53: Procedente | AM53: Condenação por tráfico | AN53: Art. 33 | AO53: NA | AP53: Não | AQ53: 5a | AR53: Não | AS53: Não | AT53: Não | AU53: Não | AV53: Não | AW53: Sim | AX53: Não | AY53: Não | AZ53: Não | BA53: Não | BB53: Não | BC53: Não | BD53: Não | BE53: Não | BF53: =IF(AZ53="Não","Sim","Não") -> Sim | BG53: =IF(AZ53="NA","Sim","Não") -> Não | BH53: Não | BI53: Sim total | BJ53: Sim (total ou parcial) | BK53: 1a 8m | BL53: 20 | BM53: NA | BN53: NA | BO53: 1a 8m | BP53: 20 | BQ53: Sim | BR53: NA | BS53: NA
A54: 53 | B54: 00084787620168260635 | C54: 1 | D54: 42772 | E54: Fernanda Galizia Noriega | F54: Feminino | G54: 28ª Vara Criminal | H54: MATHEUS HENRIQUE DA SILVA | I54: 1 | J54: Via Pública | K54: Masculino | L54: 35169 | M54: 20 | N54: Parda | O54: Negros, pardos e outros | P54: Não disponível | Q54: Dinheiro R$ 70,00 | R54: 4 porções. 8 g | S54: 8 | T54: 26 porções. 8,2 g | U54: 8.2 | V54: 0 | W54: 0 | X54: 0 | Y54: 0 | Z54: 0 | AA54: 0 | AB54: 0 | AC54: Não | AD54: Não | AE54: Não | AF54: Não | AG54: Não | AH54: Não | AI54: Art. 33 | AJ54: Não | AK54: Local de tráfico. Preso no momento da sentença. Atitude suspeita. Confissão informal | AL54: Procedente | AM54: Condenação por tráfico | AN54: Art. 33 | AO54: NA | AP54: Não | AQ54: 5a | AR54: Não | AS54: Não | AT54: Não | AU54: Não | AV54: Não | AW54: Sim | AX54: Não | AY54: Não | AZ54: Não | BA54: Não | BB54: Não | BC54: Não | BD54: Não | BE54: Não | BF54: =IF(AZ54="Não","Sim","Não") -> Sim | BG54: =IF(AZ54="NA","Sim","Não") -> Não | BH54: Não | BI54: Sim total | BJ54: Sim (total ou parcial) | BK54: 1a 8m | BL54: 20 | BM54: NA | BN54: NA | BO54: 1a 8m | BP54: 20 | BQ54: Não | BR54: Fechado | BS54: Fechado
A55: 54 | B55: 00934274220168260050 | C55: 1 | D55: 12/07/2017 | E55: Marcos Fleury Silveira de Alvarenga | F55: Masculino | G55: 12ª Vara Criminal | H55: GUILHERME HENRIQUE DA SILVA ROCHA | I55: 1 | J55: Via Pública | K55: Masculino | L55: 33304 | M55: 26 | N55: Parda | O55: Negros, pardos e outros | P55: Não disponível | Q55: Celular. Dinheiro R$ 172,00 | R55: 29 porções. 51,4 g | S55: 51.4 | T55: 28 porções. 22 g | U55: 22 | V55: 0 | W55: 0 | X55: 0 | Y55: 0 | Z55: 0 | AA55: 0 | AB55: 0 | AC55: Não | AD55: Não | AE55: Não | AF55: Não | AG55: Não | AH55: Não | AI55: Art. 33 | AJ55: Não | AK55: Confissão. Preso no momento da sentença. Atitude suspeita | AL55: Procedente | AM55: Condenação por tráfico | AN55: Art. 33 | AO55: NA | AP55: Não | AQ55: 5a | AR55: Não | AS55: Não | AT55: Não | AU55: Não | AV55: Não | AW55: Sim | AX55: Não | AY55: Não | AZ55: Não | BA55: Não | BB55: Não | BC55: Não | BD55: Não | BE55: Não | BF55: =IF(AZ55="Não","Sim","Não") -> Sim | BG55: =IF(AZ55="NA","Sim","Não") -> Não | BH55: Não | BI55: Sim total | BJ55: Sim (total ou parcial) | BK55: 1a 8m | BL55: 20 | BM55: NA | BN55: NA | BO55: 1a 8m | BP55: 20 | BQ55: Não | BR55: Aberto | BS55: Aberto
A56: 55 | B56: 00934274220168260050 | C56: 0 | D56: 12/07/2017 | E56: Marcos Fleury Silveira de Alvarenga | F56: Masculino | G56: 12ª Vara Criminal | H56: WESLEY MARTINS DE OLIVEIRA | I56: 1 | J56: Via Pública | K56: Masculino | L56: 33968 | M56: 24 | N56: Parda | O56: Negros, pardos e outros | P56: Não disponível | Q56: Celular. Dinheiro R$ 172,00 | R56: 29 porções. 51,4 g | S56: 51.4 | T56: 28 porções. 22 g | U56: 22 | V56: 0 | W56: 0 | X56: 0 | Y56: 0 | Z56: 0 | AA56: 0 | AB56: 0 | AC56: Não | AD56: Não | AE56: Não | AF56: Não | AG56: Não | AH56: Não | AI56: Art. 33 | AJ56: Não | AK56: Confissão. Preso no momento da sentença. Atitude suspeita | AL56: Procedente | AM56: Condenação por tráfico | AN56: Art. 33 | AO56: NA | AP56: Não | AQ56: 5a | AR56: Não | AS56: Não | AT56: Não | AU56: Não | AV56: Não | AW56: Sim | AX56: Não | AY56: Não | AZ56: Não | BA56: Não | BB56: Não | BC56: Não | BD56: Não | BE56: Não | BF56: =IF(AZ56="Não","Sim","Não") -> Sim | BG56: =IF(AZ56="NA","Sim","Não") -> Não | BH56: Não | BI56: Sim total | BJ56: Sim (total ou parcial) | BK56: 1a 8m | BL56: 20 | BM56: NA | BN56: NA | BO56: 1a 8m | BP56: 20 | BQ56: Não | BR56: Aberto | BS56: Aberto
A57: 56 | B57: 00037661820178260050 | C57: 1 | D57: 27/06/2017 | E57: CRISTINA ESCHER | F57: Feminino | G57: 4ª Vara Criminal | H57: RENAN DA SILVA PRESENTE | I57: 1 | J57: Via Pública | K57: Masculino | L57: 35233 | M57: 21 | N57: Parda | O57: Negros, pardos e outros | P57: Encaracolado | Q57: Estojo. Dinheiro R$ 88,00 | R57: 0 | S57: 0 | T57: 29 porções. 21,1 g | U57: 21.1 | V57: 0 | W57: 0 | X57: 0 | Y57: 0 | Z57: 0 | AA57: 0 | AB57: 0 | AC57: Não | AD57: Não | AE57: Não | AF57: Não | AG57: Não | AH57: Não | AI57: Art. 33 | AJ57: Não | AK57: Preso no momento da sentença | AL57: Procedente | AM57: Condenação por tráfico | AN57: Art. 33 | AO57: NA | AP57: Não | AQ57: 5a | AR57: Não | AS57: Não | AT57: Não | AU57: Não | AV57: Não | AW57: Sim | AX57: Não | AY57: Não | AZ57: Não | BA57: Não | BB57: Não | BC57: Não | BD57: Não | BE57: Não | BF57: =IF(AZ57="Não","Sim","Não") -> Sim | BG57: =IF(AZ57="NA","Sim","Não") -> Não | BH57: Não | BI57: Sim total | BJ57: Sim (total ou parcial) | BK57: 1a 8m | BL57: 20 | BM57: NA | BN57: NA | BO57: 1a 8m | BP57: 20 | BQ57: Não | BR57: Fechado | BS57: Fechado
A58: 57 | B58: 00534677920168260050 | C58: 1 | D58: 16/03/2017 | E58: Paulo Eduardo Balbone Costa | F58: Masculino | G58: 7ª Vara Criminal | H58: DANIEL MITA DE OLIVEIRA | I58: 1 | J58: Via Pública | K58: Masculino | L58: 34163 | M58: 23 | N58: Parda | O58: Negros, pardos e outros | P58: Liso | Q58: Celular | R58: 0 | S58: 0 | T58: 29 porções. 7,1 g | U58: 7.1 | V58: 0 | W58: 0 | X58: 0 | Y58: 0 | Z58: 0 | AA58: 0 | AB58: 0 | AC58: Não | AD58: Não | AE58: Não | AF58: Não | AG58: Não | AH58: Não | AI58: Art. 33 | AJ58: Não | AK58: Local de tráfico | AL58: Procedente | AM58: Condenação por tráfico | AN58: Art. 33 | AO58: NA | AP58: Não | AQ58: 5a | AR58: Não | AS58: Não | AT58: Não | AU58: Não | AV58: Não | AW58: Sim | AX58: Não | AY58: Não | AZ58: Não | BA58: Não | BB58: Não | BC58: Não | BD58: Não | BE58: Não | BF58: =IF(AZ58="Não","Sim","Não") -> Sim | BG58: =IF(AZ58="NA","Sim","Não") -> Não | BH58: Não | BI58: Sim total | BJ58: Sim (total ou parcial) | BK58: 1a 8m | BL58: 20 | BM58: NA | BN58: NA | BO58: 1a 8m | BP58: 20 | BQ58: Sim | BR58: NA | BS58: NA
A59: 58 | B59: 00534677920168260050 | C59: 0 | D59: 16/03/2017 | E59: Paulo Eduardo Balbone Costa | F59: Masculino | G59: 7ª Vara Criminal | H59: TALITA MITA DE OLIVEIRA | I59: 1 | J59: Via Pública | K59: Feminino | L59: 35297 | M59: 20 | N59: Parda | O59: Negros, pardos e outros | P59: Liso | Q59: Nada | R59: 0 | S59: 0 | T59: 29 porções. 7,1 g | U59: 7.1 | V59: 0 | W59: 0 | X59: 0 | Y59: 0 | Z59: 0 | AA59: 0 | AB59: 0 | AC59: Não | AD59: Não | AE59: Não | AF59: Não | AG59: Não | AH59: Não | AI59: Art. 33 | AJ59: Não | AK59: Local de tráfico. Confissão informal. Confissão | AL59: Procedente | AM59: Condenação por tráfico | AN59: Art. 33 | AO59: NA | AP59: Não | AQ59: 5a | AR59: Não | AS59: Não | AT59: Não | AU59: Não | AV59: Não | AW59: Sim | AX59: Não | AY59: Não | AZ59: Não | BA59: Não | BB59: Não | BC59: Não | BD59: Não | BE59: Não | BF59: =IF(AZ59="Não","Sim","Não") -> Sim | BG59: =IF(AZ59="NA","Sim","Não") -> Não | BH59: Não | BI59: Sim total | BJ59: Sim (total ou parcial) | BK59: 1a 8m | BL59: 20 | BM59: NA | BN59: NA | BO59: 1a 8m | BP59: 20 | BQ59: Sim | BR59: NA | BS59: NA
A60: 59 | B60: 00002386420178260635 | C60: 1 | D60: 03/05/2017 | E60: Tamara Priscila Tocci | F60: Feminino | G60: 29ª Vara Criminal | H60: ANDRÉ OLIVEIRA QUEIROS | I60: 1 | J60: Residência | K60: Masculino | L60: 34027 | M60: 24 | N60: Branca | O60: Branco e amarelo | P60: Não disponível | Q60: Dinheiro R$ 24,00 | R60: 36 porções. 66,1 g | S60: 66.1 | T60: 30 porções. 25,1 g | U60: 25.1 | V60: 0 | W60: 0 | X60: 0 | Y60: 0 | Z60: 0 | AA60: 0 | AB60: 0 | AC60: Não | AD60: Não | AE60: Não | AF60: Não | AG60: Não | AH60: Não | AI60: Art. 33 | AJ60: Não | AK60: Confissão. Travesti | AL60: Procedente | AM60: Condenação por tráfico | AN60: Art. 33 | AO60: NA | AP60: Sim. Natureza | AQ60: 5a 10m | AR60: Não | AS60: Não | AT60: Confissão | AU60: Sim | AV60: Não | AW60: Não | AX60: Não | AY60: Sim | AZ60: Não | BA60: Não | BB60: Não | BC60: Não | BD60: Não | BE60: Não | BF60: =IF(AZ60="Não","Sim","Não") -> Sim | BG60: =IF(AZ60="NA","Sim","Não") -> Não | BH60: Não | BI60: Sim total | BJ60: Sim (total ou parcial) | BK60: 1a 8m | BL60: 20 | BM60: NA | BN60: NA | BO60: 1a 8m | BP60: 20 | BQ60: Sim | BR60: NA | BS60: NA
A61: 60 | B61: 00357618320168260050 | C61: 1 | D61: 13/09/2017 | E61: Tatiana Saes Valverde Ormeleze | F61: Feminino | G61: 9ª Vara Criminal | H61: DOUGLAS SANTOS DE CAMARGO | I61: 1 | J61: Via Pública | K61: Masculino | L61: 32935 | M61: 27 | N61: Branca | O61: Branco e amarelo | P61: Não disponível | Q61: Dinheiro R$ 22,00 | R61: 19 porções. 32 g | S61: 32 | T61: 33 porções. 11,5 g | U61: 11.5 | V61: 0 | W61: 0 | X61: 0 | Y61: 0 | Z61: 0 | AA61: 0 | AB61: 0 | AC61: Não | AD61: Não | AE61: Não | AF61: Não | AG61: Não | AH61: Não | AI61: Art. 33 | AJ61: Não | AK61: Denúncia anônima | AL61: Procedente | AM61: Condenação por tráfico | AN61: Art. 33 | AO61: NA | AP61: Não | AQ61: 5a | AR61: Não | AS61: Não | AT61: Não | AU61: Não | AV61: Não | AW61: Sim | AX61: Não | AY61: Não | AZ61: Não | BA61: Não | BB61: Não | BC61: Não | BD61: Não | BE61: Não | BF61: =IF(AZ61="Não","Sim","Não") -> Sim | BG61: =IF(AZ61="NA","Sim","Não") -> Não | BH61: Não | BI61: Sim total | BJ61: Sim (total ou parcial) | BK61: 1a 8m | BL61: 20 | BM61: NA | BN61: NA | BO61: 1a 8m | BP61: 20 | BQ61: Não | BR61: Semiaberto | BS61: Semiaberto
A62: 61 | B62: 00857947720168260050 | C62: 1 | D62: 12/01/2017 | E62: Cecilia Pinheiro da Fonseca | F62: Feminino | G62: 3ª Vara Criminal | H62: WESLEY WILLIAM DA COSTA | I62: 1 | J62: Via Pública | K62: Masculino | L62: 35015 | M62: 21 | N62: Parda | O62: Negros, pardos e outros | P62: Ondulado | Q62: Dinheiro R$ 32,00 | R62: 0 | S62: 0 | T62: 34 porções. 19,4 g | U62: 19.4 | V62: 0 | W62: 0 | X62: 0 | Y62: 0 | Z62: 0 | AA62: 0 | AB62: 0 | AC62: Não | AD62: Não | AE62: Não | AF62: Não | AG62: Não | AH62: Não | AI62: Art. 33 | AJ62: Não | AK62: Confissão. Local de tráfico. Preso no momento da sentença | AL62: Procedente | AM62: Condenação por tráfico | AN62: Art. 33 | AO62: NA | AP62: Não | AQ62: 5a | AR62: Não | AS62: Não | AT62: Não | AU62: Não | AV62: Não | AW62: Sim | AX62: Não | AY62: Não | AZ62: Não | BA62: Não | BB62: Não | BC62: Não | BD62: Não | BE62: Não | BF62: =IF(AZ62="Não","Sim","Não") -> Sim | BG62: =IF(AZ62="NA","Sim","Não") -> Não | BH62: Não | BI62: Sim total | BJ62: Sim (total ou parcial) | BK62: 1a 8m | BL62: 20 | BM62: NA | BN62: NA | BO62: 1a 8m | BP62: 20 | BQ62: Não | BR62: Semiaberto | BS62: Semiaberto
A63: 62 | B63: 00114034520168260635 | C63: 1 | D63: 16/08/2017 | E63: Renata William Rached Catelli | F63: Feminino | G63: 21ª Vara Criminal | H63: DANIEL CURRALO | I63: 1 | J63: Via Pública | K63: Masculino | L63: 27582 | M63: 42 | N63: Branca | O63: Branco e amarelo | P63: Ondulado | Q63: Veículo. Estojo. Dinheiro R$ 22,00 | R63: 37 porções. 42,8 g | S63: 42.8 | T63: 361 porções. 72,4 g | U63: 72.4 | V63: 0 | W63: 0 | X63: 0 | Y63: 0 | Z63: 0 | AA63: 0 | AB63: 0 | AC63: Não | AD63: Não | AE63: Não | AF63: Não | AG63: Não | AH63: Não | AI63: Art. 33 | AJ63: Não | AK63: Local de tráfico | AL63: Procedente | AM63: Condenação por tráfico | AN63: Art. 33 | AO63: NA | AP63: Não | AQ63: 5a | AR63: Não | AS63: Não | AT63: Não | AU63: Não | AV63: Não | AW63: Sim | AX63: Não | AY63: Não | AZ63: Não | BA63: Não | BB63: Não | BC63: Não | BD63: Não | BE63: Não | BF63: =IF(AZ63="Não","Sim","Não") -> Sim | BG63: =IF(AZ63="NA","Sim","Não") -> Não | BH63: Não | BI63: Sim total | BJ63: Sim (total ou parcial) | BK63: 1a 8m | BL63: 20 | BM63: NA | BN63: NA | BO63: 1a 8m | BP63: 20 | BQ63: Não | BR63: Fechado | BS63: Fechado
A64: 63 | B64: 00086086620168260635 | C64: 1 | D64: 31/08/2017 | E64: MARIO RUBENS ASSUMPCAO FILHO | F64: Masculino | G64: 30ª Vara Criminal | H64: FILIPE CAMPOS GUIMARÃES | I64: 1 | J64: Via Pública | K64: Masculino | L64: 34180 | M64: 24 | N64: Parda | O64: Negros, pardos e outros | P64: Encaracolado | Q64: Papel. Celular. Dinheiro R$ 1424,00 | R64: 0 | S64: 0 | T64: 44 porções. 39 g | U64: 39 | V64: 0 | W64: 0 | X64: 0 | Y64: 0 | Z64: 0 | AA64: 0 | AB64: 0 | AC64: Não | AD64: Não | AE64: Não | AF64: Não | AG64: Não | AH64: Não | AI64: Art. 33 | AJ64: Não | AK64: Não há | AL64: Procedente | AM64: Condenação por tráfico | AN64: Art. 33 | AO64: NA | AP64: Não | AQ64: 5a | AR64: Não | AS64: Não | AT64: Não | AU64: Não | AV64: Não | AW64: Sim | AX64: Não | AY64: Não | AZ64: Não | BA64: Não | BB64: Não | BC64: Não | BD64: Não | BE64: Não | BF64: =IF(AZ64="Não","Sim","Não") -> Sim | BG64: =IF(AZ64="NA","Sim","Não") -> Não | BH64: Não | BI64: Sim total | BJ64: Sim (total ou parcial) | BK64: 1a 8m | BL64: 20 | BM64: NA | BN64: NA | BO64: 1a 8m | BP64: 20 | BQ64: Sim | BR64: NA | BS64: NA
A65: 64 | B65: 01019001720168260050 | C65: 1 | D65: 04/04/2017 | E65: Marcos Fleury Silveira de Alvarenga | F65: Masculino | G65: 12ª Vara Criminal | H65: JOSÉ ALVES DE SOUSA VIANA | I65: 1 | J65: Residência | K65: Masculino | L65: 30599 | M65: 33 | N65: Branca | O65: Branco e amarelo | P65: Outros | Q65: Prato. Colher. Balança. Celular. Dinheiro R$ 1.276,00 | R65: 0 | S65: 0 | T65: 51 porções. 261,5 g | U65: 261.5 | V65: 0 | W65: 0 | X65: 0 | Y65: 0 | Z65: 0 | AA65: 0 | AB65: 0 | AC65: Não | AD65: Não | AE65: Não | AF65: Não | AG65: Não | AH65: Não | AI65: Art. 33 | AJ65: Não | AK65: Preso no momento da sentença. Mandado | AL65: Procedente | AM65: Condenação por tráfico | AN65: Art. 33 | AO65: NA | AP65: Não | AQ65: 5a | AR65: Não | AS65: Não | AT65: Não | AU65: Não | AV65: Não | AW65: Sim | AX65: Não | AY65: Não | AZ65: Não | BA65: Não | BB65: Não | BC65: Não | BD65: Não | BE65: Não | BF65: =IF(AZ65="Não","Sim","Não") -> Sim | BG65: =IF(AZ65="NA","Sim","Não") -> Não | BH65: Não | BI65: Sim total | BJ65: Sim (total ou parcial) | BK65: 1a 8m | BL65: 20 | BM65: NA | BN65: NA | BO65: 1a 8m | BP65: 20 | BQ65: Não | BR65: Semiaberto | BS65: Semiaberto
A66: 65 | B66: 00684932020168260050 | C66: 1 | D66: 27/10/2017 | E66: Isaura Cristina Barreira | F66: Feminino | G66: 30ª Vara Criminal | H66: ANDERSON CRISTINO VIEIRA DOS SANTOS | I66: 1 | J66: Via Pública | K66: Masculino | L66: 35834 | M66: 19 | N66: Parda | O66: Negros, pardos e outros | P66: Não disponível | Q66: Pochete. Papel. Dinheiro R$ 26,00 | R66: 56 porções. 118,9 g | S66: 118.9 | T66: 55 porções. 24,7 g | U66: 24.7 | V66: 0 | W66: 0 | X66: 0 | Y66: 0 | Z66: 0 | AA66: 0 | AB66: Haxixe. 8 porções. 4,1 g | AC66: Não | AD66: Não | AE66: Sim | AF66: Não | AG66: Não | AH66: Não | AI66: Art. 33 | AJ66: Não | AK66: Confissão. Local de tráfico. Confissão informal | AL66: Procedente | AM66: Condenação por tráfico | AN66: Art. 33 | AO66: NA | AP66: Não | AQ66: 5a | AR66: Não | AS66: Não | AT66: Não | AU66: Não | AV66: Não | AW66: Sim | AX66: Não | AY66: Não | AZ66: Não | BA66: Não | BB66: Não | BC66: Não | BD66: Não | BE66: Não | BF66: =IF(AZ66="Não","Sim","Não") -> Sim | BG66: =IF(AZ66="NA","Sim","Não") -> Não | BH66: Não | BI66: Sim total | BJ66: Sim (total ou parcial) | BK66: 1a 8m | BL66: 20 | BM66: NA | BN66: NA | BO66: 1a 8m | BP66: 20 | BQ66: Não | BR66: Aberto | BS66: Aberto
A67: 66 | B67: 00709927420168260050 | C67: 1 | D67: 11/05/2017 | E67: RICHARD FRANCISCO CHEQUINI | F67: Masculino | G67: 20ª Vara Criminal | H67: MAYLON FERREIRA DE SOUZA | I67: 1 | J67: Via Pública | K67: Masculino | L67: 34845 | M67: 21 | N67: Parda | O67: Negros, pardos e outros | P67: Não disponível | Q67: Dinheiro R$ 14,00 | R67: 0 | S67: 0 | T67: 61 porções. 43,4 g | U67: 43.4 | V67: 0 | W67: 0 | X67: 0 | Y67: 0 | Z67: 0 | AA67: 0 | AB67: 0 | AC67: Não | AD67: Não | AE67: Não | AF67: Não | AG67: Não | AH67: Não | AI67: Art. 33 | AJ67: Não | AK67: Local de tráfico | AL67: Procedente | AM67: Condenação por tráfico | AN67: Art. 33 | AO67: NA | AP67: Não | AQ67: 5a | AR67: Não | AS67: Não | AT67: Não | AU67: Não | AV67: Não | AW67: Sim | AX67: Não | AY67: Não | AZ67: Não | BA67: Não | BB67: Não | BC67: Não | BD67: Não | BE67: Não | BF67: =IF(AZ67="Não","Sim","Não") -> Sim | BG67: =IF(AZ67="NA","Sim","Não") -> Não | BH67: Não | BI67: Sim total | BJ67: Sim (total ou parcial) | BK67: 1a 8m | BL67: 20 | BM67: NA | BN67: NA | BO67: 1a 8m | BP67: 20 | BQ67: Sim | BR67: NA | BS67: NA
A68: 67 | B68: 00033780920178260635 | C68: 1 | D68: 23/08/2017 | E68: Erica Regina Colmenero Coimbra | F68: Feminino | G68: 2ª Vara Criminal | H68: DIEGO SANTANA SODRE | I68: 1 | J68: Via Pública | K68: Masculino | L68: 34820 | M68: 22 | N68: Parda | O68: Negros, pardos e outros | P68: Não disponível | Q68: Pochete. Isqueiro. Celular. Dinheiro R$ 36,00 | R68: 140 porções. 132,7 g | S68: 132.7 | T68: 74 porções. 49,7 g | U68: 49.7 | V68: 0 | W68: 0 | X68: 0 | Y68: 0 | Z68: 0 | AA68: 0 | AB68: Lança-perfume. 21 frascos. 210 ml | AC68: Não | AD68: Não | AE68: Não | AF68: Não | AG68: Sim | AH68: Não | AI68: Art. 33 | AJ68: Não | AK68: Preso no momento da sentença. Confissão informal. Confissão | AL68: Procedente | AM68: Condenação por tráfico | AN68: Art. 33 | AO68: NA | AP68: Não | AQ68: 5a | AR68: Não | AS68: Não | AT68: Não | AU68: Não | AV68: Não | AW68: Sim | AX68: Não | AY68: Não | AZ68: Não | BA68: Não | BB68: Não | BC68: Não | BD68: Não | BE68: Não | BF68: =IF(AZ68="Não","Sim","Não") -> Sim | BG68: =IF(AZ68="NA","Sim","Não") -> Não | BH68: Não | BI68: Sim total | BJ68: Sim (total ou parcial) | BK68: 1a 8m | BL68: 20 | BM68: NA | BN68: NA | BO68: 1a 8m | BP68: 20 | BQ68: Não | BR68: Fechado | BS68: Fechado
A69: 68 | B69: 01058044520168260050 | C69: 1 | D69: 23/08/2017 | E69: Marcello Ovidio Lopes Guimarães | F69: Masculino | G69: 18ª Vara Criminal | H69: MATEUS HUMBERTO DA SILVA | I69: 1 | J69: Via Pública | K69: Masculino | L69: 34849 | M69: 22 | N69: Parda | O69: Negros, pardos e outros | P69: Liso | Q69: Dinheiro R$ 20,00 | R69: 10 porções. 12,5 g | S69: 12.5 | T69: 8 porções. 5 g | U69: 5 | V69: 0 | W69: 0 | X69: 0 | Y69: 0 | Z69: 0 | AA69: 0 | AB69: 0 | AC69: Não | AD69: Não | AE69: Não | AF69: Não | AG69: Não | AH69: Não | AI69: Art. 33 | AJ69: Não | AK69: Confissão informal | AL69: Procedente | AM69: Condenação por tráfico | AN69: Art. 33 | AO69: NA | AP69: Não | AQ69: 5a | AR69: Não | AS69: Não | AT69: Não | AU69: Não | AV69: Não | AW69: Sim | AX69: Não | AY69: Não | AZ69: Não | BA69: Não | BB69: Não | BC69: Não | BD69: Não | BE69: Não | BF69: =IF(AZ69="Não","Sim","Não") -> Sim | BG69: =IF(AZ69="NA","Sim","Não") -> Não | BH69: Não | BI69: Sim total | BJ69: Sim (total ou parcial) | BK69: 1a 8m | BL69: 20 | BM69: NA | BN69: NA | BO69: 1a 8m | BP69: 20 | BQ69: Não | BR69: Aberto | BS69: Aberto
A70: 69 | B70: 00532989220168260050 | C70: 1 | D70: 43040 | E70: Érica Aparecida Ribeiro Lopes e Navarro Rodrigues | F70: Feminino | G70: 26ª Vara Criminal | H70: ERLAN DOS SANTOS RIBEIRO | I70: 1 | J70: Via Pública | K70: Masculino | L70: 35107 | M70: 21 | N70: Preta | O70: Negros, pardos e outros | P70: Carapinha | Q70: Papel. Celular. Dinheiro R$ 49,00 | R70: 20 porções. 29,2 g | S70: 29.2 | T70: 9 porções. 3,1 g | U70: 3.1 | V70: 0 | W70: 0 | X70: 0 | Y70: 0 | Z70: 0 | AA70: 0 | AB70: Lança-perfume. 18 frascos. 90 ml | AC70: Não | AD70: Não | AE70: Não | AF70: Não | AG70: Sim | AH70: Não | AI70: Art. 33 | AJ70: Não | AK70: Denúncia anônima. Confissão informal. Confissão | AL70: Procedente | AM70: Condenação por tráfico | AN70: Art. 33 | AO70: NA | AP70: Não | AQ70: 5a | AR70: Não | AS70: Não | AT70: Não | AU70: Não | AV70: Não | AW70: Sim | AX70: Não | AY70: Não | AZ70: Não | BA70: Não | BB70: Não | BC70: Não | BD70: Não | BE70: Não | BF70: =IF(AZ70="Não","Sim","Não") -> Sim | BG70: =IF(AZ70="NA","Sim","Não") -> Não | BH70: Não | BI70: Sim total | BJ70: Sim (total ou parcial) | BK70: 1a 8m | BL70: 20 | BM70: NA | BN70: NA | BO70: 1a 8m | BP70: 20 | BQ70: Não | BR70: Semiaberto | BS70: Semiaberto
A71: 70 | B71: 00138767620178260050 | C71: 0 | D71: 08/06/2017 | E71: Klaus Marouelli Arroyo | F71: Masculino | G71: 23ª Vara Criminal | H71: GUSTAVO DE CARVALHO ANDRADE | I71: 1 | J71: Via Pública | K71: Masculino | L71: 36181 | M71: 18 | N71: Branca | O71: Branco e amarelo | P71: Não disponível | Q71: Veículo. Caixa. Papéis. Celular | R71: 0 | S71: 0 | T71: 99 porções. 30,3 g | U71: 30.3 | V71: 0 | W71: 0 | X71: 0 | Y71: 0 | Z71: 0 | AA71: 0 | AB71: 0 | AC71: Não | AD71: Não | AE71: Não | AF71: Não | AG71: Não | AH71: Não | AI71: Art. 33. Art. 35 | AJ71: Não | AK71: Preso no momento da sentença. Confissão informal. Confissão | AL71: Parcialmente procedente | AM71: Condenação por tráfico | AN71: Art. 33 | AO71: NA | AP71: Não | AQ71: 5a | AR71: Não | AS71: Não | AT71: Não | AU71: Não | AV71: Não | AW71: Sim | AX71: Não | AY71: Não | AZ71: Não | BA71: Não | BB71: Não | BC71: Não | BD71: Não | BE71: Não | BF71: =IF(AZ71="Não","Sim","Não") -> Sim | BG71: =IF(AZ71="NA","Sim","Não") -> Não | BH71: Não | BI71: Sim total | BJ71: Sim (total ou parcial) | BK71: 1a 8m | BL71: 20 | BM71: NA | BN71: NA | BO71: 1a 8m | BP71: 20 | BQ71: Não | BR71: Fechado | BS71: Fechado
A72: 71 | B72: 00138767620178260050 | C72: 1 | D72: 08/06/2017 | E72: Klaus Marouelli Arroyo | F72: Masculino | G72: 23ª Vara Criminal | H72: MATHEUS ANTÔNIO FERNANDES SILVA | I72: 1 | J72: Via Pública | K72: Masculino | L72: 35594 | M72: 20 | N72: Branca | O72: Branco e amarelo | P72: Não disponível | Q72: Veículo. Caixa. Papéis. Celular | R72: 0 | S72: 0 | T72: 99 porções. 30,3 g | U72: 30.3 | V72: 0 | W72: 0 | X72: 0 | Y72: 0 | Z72: 0 | AA72: 0 | AB72: 0 | AC72: Não | AD72: Não | AE72: Não | AF72: Não | AG72: Não | AH72: Não | AI72: Art. 33. Art. 35 | AJ72: Não | AK72: Preso no momento da sentença. Confissão informal. Confissão | AL72: Parcialmente procedente | AM72: Condenação por tráfico | AN72: Art. 33 | AO72: NA | AP72: Não | AQ72: 5a | AR72: Não | AS72: Não | AT72: Não | AU72: Não | AV72: Não | AW72: Sim | AX72: Não | AY72: Não | AZ72: Não | BA72: Não | BB72: Não | BC72: Não | BD72: Não | BE72: Não | BF72: =IF(AZ72="Não","Sim","Não") -> Sim | BG72: =IF(AZ72="NA","Sim","Não") -> Não | BH72: Não | BI72: Sim total | BJ72: Sim (total ou parcial) | BK72: 1a 8m | BL72: 20 | BM72: NA | BN72: NA | BO72: 1a 8m | BP72: 20 | BQ72: Não | BR72: Fechado | BS72: Fechado
A73: 72 | B73: 00016165520178260635 | C73: 1 | D73: 18/04/2017 | E73: Claudia Carneiro Calbucci Renaux | F73: Feminino | G73: 13ª Vara Criminal | H73: GABRIEL DA SILVA CONCEIÇÃO | I73: 1 | J73: Via Pública | K73: Masculino | L73: 35969 | M73: 18 | N73: Parda | O73: Negros, pardos e outros | P73: Não disponível | Q73: Dinheiro R$ 425,05 | R73: 0 | S73: 0 | T73: 79 porções. 68,5 g | U73: 68.5 | V73: 1 porção. 0,05 g | W73: 0.05 | X73: 0 | Y73: 0 | Z73: 0 | AA73: 0 | AB73: 0 | AC73: Não | AD73: Não | AE73: Não | AF73: Não | AG73: Não | AH73: Não | AI73: Art. 33 | AJ73: Não | AK73: Preso no momento da sentença. Confissão informal | AL73: Procedente | AM73: Condenação por tráfico | AN73: Art. 33 | AO73: NA | AP73: Não | AQ73: 5a | AR73: Não | AS73: Não | AT73: Não | AU73: Não | AV73: Não | AW73: Sim | AX73: Não | AY73: Não | AZ73: Não | BA73: Não | BB73: Não | BC73: Não | BD73: Não | BE73: Não | BF73: =IF(AZ73="Não","Sim","Não") -> Sim | BG73: =IF(AZ73="NA","Sim","Não") -> Não | BH73: Não | BI73: Sim total | BJ73: Sim (total ou parcial) | BK73: 1a 8m | BL73: 20 | BM73: NA | BN73: NA | BO73: 1a 8m | BP73: 20 | BQ73: Sim | BR73: NA | BS73: NA
A74: 73 | B74: 00084502020168260050 | C74: 1 | D74: 09/01/2017 | E74: Maria Paula Cassone Rossi | F74: Feminino | G74: 9ª Vara Criminal | H74: PEDRO RICARDO MOURA BAUER | I74: 1 | J74: Via Pública | K74: Masculino | L74: 35473 | M74: 19 | N74: Parda | O74: Negros, pardos e outros | P74: Não disponível | Q74: Nada | R74: 0 | S74: 0 | T74: 0 | U74: 0 | V74: 100 porções. 11,4 g | W74: 11.4 | X74: 0 | Y74: 0 | Z74: 0 | AA74: 0 | AB74: 0 | AC74: Não | AD74: Não | AE74: Não | AF74: Não | AG74: Não | AH74: Não | AI74: Art. 33 | AJ74: Não | AK74: Local de tráfico. Preso no momento da sentença | AL74: Procedente | AM74: Condenação por tráfico | AN74: Art. 33 | AO74: NA | AP74: Não | AQ74: 5a | AR74: Não | AS74: Não | AT74: Não | AU74: Não | AV74: Não | AW74: Sim | AX74: Não | AY74: Não | AZ74: Não | BA74: Não | BB74: Não | BC74: Não | BD74: Não | BE74: Não | BF74: =IF(AZ74="Não","Sim","Não") -> Sim | BG74: =IF(AZ74="NA","Sim","Não") -> Não | BH74: Não | BI74: Sim total | BJ74: Sim (total ou parcial) | BK74: 1a 8m | BL74: 20 | BM74: NA | BN74: NA | BO74: 1a 8m | BP74: 20 | BQ74: Não | BR74: Aberto | BS74: Aberto
A75: 74 | B75: 00669178920168260050 | C75: 1 | D75: 42921 | E75: Érica Aparecida Ribeiro Lopes e Navarro Rodrigues | F75: Feminino | G75: 26ª Vara Criminal | H75: CLAUDIO CALAZANS BARBOSA | I75: 1 | J75: Via Pública | K75: Masculino | L75: 35026 | M75: 21 | N75: Branca | O75: Branco e amarelo | P75: Encaracolado | Q75: Pochete. Dinheiro R$ 20,00 | R75: 39 porções. 147,5 g | S75: 147.5 | T75: 0 | U75: 0 | V75: 14 porções. 1,8 g | W75: 1.8 | X75: 0 | Y75: 0 | Z75: 0 | AA75: 0 | AB75: 0 | AC75: Não | AD75: Não | AE75: Não | AF75: Não | AG75: Não | AH75: Não | AI75: Art. 33 | AJ75: Não | AK75: Local de tráfico. Atitude suspeita. Confissão informal. Confissão | AL75: Procedente | AM75: Condenação por tráfico | AN75: Art. 33 | AO75: NA | AP75: Não | AQ75: 5a | AR75: Não | AS75: Não | AT75: Não | AU75: Não | AV75: Não | AW75: Sim | AX75: Não | AY75: Não | AZ75: Não | BA75: Não | BB75: Não | BC75: Não | BD75: Não | BE75: Não | BF75: =IF(AZ75="Não","Sim","Não") -> Sim | BG75: =IF(AZ75="NA","Sim","Não") -> Não | BH75: Não | BI75: Sim total | BJ75: Sim (total ou parcial) | BK75: 1a 8m | BL75: 20 | BM75: NA | BN75: NA | BO75: 1a 8m | BP75: 20 | BQ75: Sim | BR75: NA | BS75: NA
A76: 75 | B76: 01070345920158260050 | C76: 1 | D76: 15/03/2017 | E76: José Roberto Cabral Longaretti | F76: Masculino | G76: 13ª Vara Criminal | H76: LUIZ RAFAEL IGNACZUK FRONZA | I76: 1 | J76: Via Pública | K76: Masculino | L76: 32855 | M76: 27 | N76: Branca | O76: Branco e amarelo | P76: Liso | Q76: Nada | R76: 0 | S76: 0 | T76: 0 | U76: 0 | V76: 14 porções. 2,1 g | W76: 2.1 | X76: 0 | Y76: 0 | Z76: 0 | AA76: 0 | AB76: 0 | AC76: Não | AD76: Não | AE76: Não | AF76: Não | AG76: Não | AH76: Não | AI76: Art. 33 | AJ76: Não | AK76: Confissão informal | AL76: Procedente | AM76: Condenação por tráfico | AN76: Art. 33 | AO76: NA | AP76: Não | AQ76: 5a | AR76: Não | AS76: Não | AT76: Não | AU76: Não | AV76: Não | AW76: Sim | AX76: Não | AY76: Não | AZ76: Não | BA76: Não | BB76: Não | BC76: Não | BD76: Não | BE76: Não | BF76: =IF(AZ76="Não","Sim","Não") -> Sim | BG76: =IF(AZ76="NA","Sim","Não") -> Não | BH76: Não | BI76: Sim total | BJ76: Sim (total ou parcial) | BK76: 1a 8m | BL76: 20 | BM76: NA | BN76: NA | BO76: 1a 8m | BP76: 20 | BQ76: Sim | BR76: NA | BS76: NA
A77: 76 | B77: 00512150620168260050 | C77: 1 | D77: 17/03/2017 | E77: Helio Narvaez | F77: Masculino | G77: 8ª Vara Criminal | H77: CRISTIANO EDUARDO PINTO VIEIRA | I77: 1 | J77: Via Pública | K77: Masculino | L77: 35528 | M77: 19 | N77: Preta | O77: Negros, pardos e outros | P77: Carapinha | Q77: Dinheiro R$ 10,00 | R77: 31 porções. 42 g | S77: 42 | T77: 27 porções. 22 g | U77: 22 | V77: 15 porções. 2,5 g | W77: 2.5 | X77: 0 | Y77: 0 | Z77: 0 | AA77: 0 | AB77: Lança-perfume. 3 frascos. 18 ml | AC77: Não | AD77: Não | AE77: Não | AF77: Não | AG77: Sim | AH77: Não | AI77: Art. 33 | AJ77: Não | AK77: Atitude suspeita.Confissão informal | AL77: Procedente | AM77: Condenação por tráfico | AN77: Art. 33 | AO77: NA | AP77: Não | AQ77: 5a | AR77: Não | AS77: Não | AT77: Não | AU77: Não | AV77: Não | AW77: Sim | AX77: Não | AY77: Não | AZ77: Não | BA77: Não | BB77: Não | BC77: Não | BD77: Não | BE77: Não | BF77: =IF(AZ77="Não","Sim","Não") -> Sim | BG77: =IF(AZ77="NA","Sim","Não") -> Não | BH77: Não | BI77: Sim total | BJ77: Sim (total ou parcial) | BK77: 1a 8m | BL77: 20 | BM77: NA | BN77: NA | BO77: 1a 8m | BP77: 20 | BQ77: Sim | BR77: NA | BS77: NA
A78: 77 | B78: 00820914120168260050 | C78: 1 | D78: 24/10/2017 | E78: Eliana Cassales Tosi | F78: Feminino | G78: 30ª Vara Criminal | H78: DALILLA VILAS BOAS MOREIRA | I78: 1 | J78: Via Pública | K78: Feminino | L78: 35613 | M78: 20 | N78: Parda | O78: Negros, pardos e outros | P78: Liso | Q78: Maço de cigarro. Celular. Dinheiro R$ 163,00 | R78: 3 porções. 4,4 g | S78: 4.4 | T78: 4 porções. 1,5 g | U78: 1.5 | V78: 16 porções. 3,0 g | W78: 3 | X78: 0 | Y78: 0 | Z78: 0 | AA78: 0 | AB78: 0 | AC78: Não | AD78: Não | AE78: Não | AF78: Não | AG78: Não | AH78: Não | AI78: Art. 33. Art. 35 | AJ78: Não | AK78: Local de tráfico. Atitude suspeita. Denúncia. Confissão informal | AL78: Parcialmente procedente | AM78: Condenação por tráfico | AN78: Art. 33 | AO78: NA | AP78: Não | AQ78: 5a | AR78: Não | AS78: Não | AT78: Não | AU78: Não | AV78: Não | AW78: Sim | AX78: Não | AY78: Não | AZ78: Não | BA78: Não | BB78: Não | BC78: Não | BD78: Não | BE78: Não | BF78: =IF(AZ78="Não","Sim","Não") -> Sim | BG78: =IF(AZ78="NA","Sim","Não") -> Não | BH78: Não | BI78: Sim total | BJ78: Sim (total ou parcial) | BK78: 1a 8m | BL78: 20 | BM78: NA | BN78: NA | BO78: 1a 8m | BP78: 20 | BQ78: Sim | BR78: NA | BS78: NA
A79: 78 | B79: 00338648320178260050 | C79: 1 | D79: 02/08/2017 | E79: Daniela Martins de Castro Mariani Cavallanti | F79: Feminino | G79: 2ª Vara Criminal | H79: YGOR CAMARA SATELES | I79: 1 | J79: Via Pública | K79: Masculino | L79: 36287 | M79: 18 | N79: Branca | O79: Branco e amarelo | P79: Não disponível | Q79: Sacola | R79: 22 porções. 67,5 g | S79: 67.5 | T79: 33 porções. 18,3 g | U79: 18.3 | V79: 17 porções. 2,4 g | W79: 2.4 | X79: 0 | Y79: 0 | Z79: 0 | AA79: 0 | AB79: 0 | AC79: Não | AD79: Não | AE79: Não | AF79: Não | AG79: Não | AH79: Não | AI79: Art. 33 | AJ79: Art. 329 CP | AK79: Local de tráfico. Preso no momento da sentença | AL79: Parcialmente Procedente | AM79: Condenação por tráfico | AN79: Art. 33 | AO79: Não | AP79: Sim. Consequências. Natureza | AQ79: 6a | AR79: Não | AS79: Não | AT79: Menoridade | AU79: Não | AV79: Sim | AW79: Não | AX79: Não | AY79: Sim | AZ79: Não | BA79: Não | BB79: Não | BC79: Não | BD79: Não | BE79: Não | BF79: =IF(AZ79="Não","Sim","Não") -> Sim | BG79: =IF(AZ79="NA","Sim","Não") -> Não | BH79: Não | BI79: Sim total | BJ79: Sim (total ou parcial) | BK79: 1a 8m | BL79: 20 | BM79: NA | BN79: NA | BO79: 1a 8m | BP79: 20 | BQ79: Não | BR79: Semiaberto | BS79: Semiaberto
A80: 79 | B80: 00026628820178260050 | C80: 1 | D80: 17/08/2017 | E80: MARCO ANTONIO MARTIN VARGAS | F80: Masculino | G80: 32ª Vara Criminal | H80: JONATHAN OLIVEIRA DOS SANTOS | I80: 1 | J80: Via Pública | K80: Masculino | L80: 32975 | M80: 27 | N80: Preta | O80: Negros, pardos e outros | P80: Não disponível | Q80: Dinheiro R$ 24,00 | R80: 14 porções. 32 g | S80: 32 | T80: 41 porções. 30,3 g | U80: 30.3 | V80: 17 porções. 3,7 g | W80: 3.7 | X80: 0 | Y80: 0 | Z80: 0 | AA80: 0 | AB80: 0 | AC80: Não | AD80: Não | AE80: Não | AF80: Não | AG80: Não | AH80: Não | AI80: Art. 33 | AJ80: Não | AK80: Confissão. Local de tráfico. Preso no momento da sentença. Atitude suspeita | AL80: Procedente | AM80: Condenação por tráfico | AN80: Art. 33 | AO80: NA | AP80: Não | AQ80: 5a | AR80: Não | AS80: Não | AT80: Não | AU80: Não | AV80: Não | AW80: Sim | AX80: Não | AY80: Não | AZ80: Não | BA80: Não | BB80: Não | BC80: Não | BD80: Não | BE80: Não | BF80: =IF(AZ80="Não","Sim","Não") -> Sim | BG80: =IF(AZ80="NA","Sim","Não") -> Não | BH80: Não | BI80: Sim total | BJ80: Sim (total ou parcial) | BK80: 1a 8m | BL80: 20 | BM80: NA | BN80: NA | BO80: 1a 8m | BP80: 20 | BQ80: Sim | BR80: NA | BS80: NA
A81: 80 | B81: 00013583920178260540 | C81: 1 | D81: 19/09/2017 | E81: Rafael Henrique Janela Tamai Rocha | F81: Masculino | G81: 22ª Vara Criminal | H81: FERNANDO RAMOS DOS SANTOS | I81: 1 | J81: Via Pública | K81: Masculino | L81: 27854 | M81: 41 | N81: Parda | O81: Negros, pardos e outros | P81: Carapinha | Q81: Dinheiro R$ 157,00 | R81: 34 porções. 58,4 g | S81: 58.4 | T81: 12 porções. 3 g | U81: 3 | V81: 20 porções. 11 g | W81: 11 | X81: 0 | Y81: 0 | Z81: 0 | AA81: 0 | AB81: 0 | AC81: Não | AD81: Não | AE81: Não | AF81: Não | AG81: Não | AH81: Não | AI81: Art. 33 | AJ81: Não | AK81: Local de tráfico. Preso no momento da sentença. Atitude suspeita | AL81: Procedente | AM81: Condenação por tráfico | AN81: Art. 33 | AO81: NA | AP81: Sim. Natureza. Quantidade | AQ81: 6a | AR81: Não | AS81: Não | AT81: Confissão | AU81: Sim | AV81: Não | AW81: Não | AX81: Não | AY81: Sim | AZ81: Não | BA81: Não | BB81: Não | BC81: Não | BD81: Não | BE81: Não | BF81: =IF(AZ81="Não","Sim","Não") -> Sim | BG81: =IF(AZ81="NA","Sim","Não") -> Não | BH81: Não | BI81: Sim total | BJ81: Sim (total ou parcial) | BK81: 1a 8m | BL81: 20 | BM81: NA | BN81: NA | BO81: 1a 8m | BP81: 20 | BQ81: Não | BR81: Aberto | BS81: Aberto
A82: 81 | B82: 00237701320168260050 | C82: 1 | D82: 42879 | E82: Fernanda Galizia Noriega | F82: Feminino | G82: 28ª Vara Criminal | H82: MARCONI DA SILVA | I82: 1 | J82: Via Pública | K82: Masculino | L82: 34646 | M82: 22 | N82: Parda | O82: Negros, pardos e outros | P82: Carapinha | Q82: Dinheiro R$ 10,00 | R82: 15 porções. 17,3 g | S82: 17.3 | T82: 47 porções. 24,3 g | U82: 24.3 | V82: 22 porções. 2,5 g | W82: 2.5 | X82: 0 | Y82: 0 | Z82: 0 | AA82: 0 | AB82: 0 | AC82: Não | AD82: Não | AE82: Não | AF82: Não | AG82: Não | AH82: Não | AI82: Art. 33 | AJ82: Não | AK82: Local de tráfico. Atitude suspeita. Confissão informal | AL82: Procedente | AM82: Condenação por tráfico | AN82: Art. 33 | AO82: NA | AP82: Não | AQ82: 5a | AR82: Não | AS82: Não | AT82: Não | AU82: Não | AV82: Não | AW82: Sim | AX82: Não | AY82: Não | AZ82: Não | BA82: Não | BB82: Não | BC82: Não | BD82: Não | BE82: Não | BF82: =IF(AZ82="Não","Sim","Não") -> Sim | BG82: =IF(AZ82="NA","Sim","Não") -> Não | BH82: Não | BI82: Sim total | BJ82: Sim (total ou parcial) | BK82: 1a 8m | BL82: 20 | BM82: NA | BN82: NA | BO82: 1a 8m | BP82: 20 | BQ82: Não | BR82: Fechado | BS82: Fechado
A83: 82 | B83: 00135849120178260050 | C83: 1 | D83: 43033 | E83: Érica Aparecida Ribeiro Lopes e Navarro Rodrigues | F83: Feminino | G83: 26ª Vara Criminal | H83: VALESKA PESSOA TEIXEIRA | I83: 1 | J83: Via Pública | K83: Feminino | L83: 34319 | M83: 23 | N83: Preta | O83: Negros, pardos e outros | P83: Não disponível | Q83: Celular. Dinheiro R$ 15,00 | R83: 21 porções. 28,2 g | S83: 28.2 | T83: 0 | U83: 0 | V83: 23 porções. 6,2 g | W83: 6.2 | X83: 0 | Y83: 0 | Z83: 0 | AA83: 0 | AB83: 0 | AC83: Não | AD83: Não | AE83: Não | AF83: Não | AG83: Não | AH83: Não | AI83: Art. 33 | AJ83: Não | AK83: Confissão informal. Confissão | AL83: Procedente | AM83: Condenação por tráfico | AN83: Art. 33 | AO83: NA | AP83: Não | AQ83: 5a | AR83: Não | AS83: Não | AT83: Não | AU83: Não | AV83: Não | AW83: Sim | AX83: Não | AY83: Não | AZ83: Não | BA83: Não | BB83: Não | BC83: Não | BD83: Não | BE83: Não | BF83: =IF(AZ83="Não","Sim","Não") -> Sim | BG83: =IF(AZ83="NA","Sim","Não") -> Não | BH83: Não | BI83: Sim total | BJ83: Sim (total ou parcial) | BK83: 1a 8m | BL83: 20 | BM83: NA | BN83: NA | BO83: 1a 8m | BP83: 20 | BQ83: Sim | BR83: NA | BS83: NA
A84: 83 | B84: 00104228820178260050 | C84: 1 | D84: 25/05/2017 | E84: ALESSANDRA TEIXEIRA MIGUEL | F84: Feminino | G84: 32ª Vara Criminal | H84: ROGERIO DOS REIS PALMA | I84: 1 | J84: Via Pública | K84: Masculino | L84: 31841 | M84: 30 | N84: Branca | O84: Branco e amarelo | P84: Não disponível | Q84: Dinheiro R$ 75,00 | R84: 10 porções. 23,5 g | S84: 23.5 | T84: 25 porções. 17,8 g | U84: 17.8 | V84: 23 porções. 7 g | W84: 7 | X84: 0 | Y84: 0 | Z84: 0 | AA84: 0 | AB84: 0 | AC84: Não | AD84: Não | AE84: Não | AF84: Não | AG84: Não | AH84: Não | AI84: Art. 33 | AJ84: Não | AK84: Confissão informal. Local de tráfico. Atitude suspeita | AL84: Procedente | AM84: Condenação por tráfico | AN84: Art. 33 | AO84: NA | AP84: Não | AQ84: 5a | AR84: Não | AS84: Não | AT84: Não | AU84: Não | AV84: Não | AW84: Sim | AX84: Não | AY84: Não | AZ84: Não | BA84: Não | BB84: Não | BC84: Não | BD84: Não | BE84: Não | BF84: =IF(AZ84="Não","Sim","Não") -> Sim | BG84: =IF(AZ84="NA","Sim","Não") -> Não | BH84: Não | BI84: Sim total | BJ84: Sim (total ou parcial) | BK84: 1a 8m | BL84: 20 | BM84: NA | BN84: NA | BO84: 1a 8m | BP84: 20 | BQ84: Sim | BR84: NA | BS84: NA
A85: 84 | B85: 00008224320178260050 | C85: 1 | D85: 12/04/2017 | E85: Waldir Calciolari | F85: Masculino | G85: 25ª Vara Criminal | H85: ANTONIO EVANGELISTA DA SILVA JUNIOR | I85: 1 | J85: Área não ocupada | K85: Masculino | L85: 32919 | M85: 27 | N85: Parda | O85: Negros, pardos e outros | P85: Não disponível | Q85: Dinheiro R$ 78,00 | R85: 32 porções. 52 g | S85: 52 | T85: 29 porções. 22,2 g | U85: 22.2 | V85: 24 porções. 10 g | W85: 10 | X85: 0 | Y85: 0 | Z85: 0 | AA85: 0 | AB85: Haxixe. 4 porções. 2 g | AC85: Não | AD85: Não | AE85: Sim | AF85: Não | AG85: Não | AH85: Não | AI85: Art. 33 | AJ85: Não | AK85: Local de tráfico. Confissão | AL85: Procedente | AM85: Condenação por tráfico | AN85: Art. 33 | AO85: NA | AP85: Não | AQ85: 5a | AR85: Não | AS85: Não | AT85: Não | AU85: Não | AV85: Não | AW85: Sim | AX85: Não | AY85: Não | AZ85: Não | BA85: Não | BB85: Não | BC85: Não | BD85: Não | BE85: Não | BF85: =IF(AZ85="Não","Sim","Não") -> Sim | BG85: =IF(AZ85="NA","Sim","Não") -> Não | BH85: Não | BI85: Sim total | BJ85: Sim (total ou parcial) | BK85: 1a 8m | BL85: 20 | BM85: NA | BN85: NA | BO85: 1a 8m | BP85: 20 | BQ85: Não | BR85: Aberto | BS85: Aberto
A86: 85 | B86: 00755542920168260050 | C86: 1 | D86: 17/10/2017 | E86: Antonio Carlos de Campos Machado Junior | F86: Masculino | G86: 19ª Vara Criminal | H86: JUNIERE CASTRO DA SILVA | I86: 1 | J86: Via Pública | K86: Masculino | L86: 34226 | M86: 24 | N86: Parda | O86: Negros, pardos e outros | P86: Liso | Q86: Pochete. Papéis . Celular. Dinheiro R$ 70,00 | R86: 20 porções. 17,9 g | S86: 17.9 | T86: 33 porções. 16,6 g | U86: 16.6 | V86: 27 porções. 3,95 g | W86: 3.95 | X86: 0 | Y86: 0 | Z86: 0 | AA86: 0 | AB86: 0 | AC86: Não | AD86: Não | AE86: Não | AF86: Não | AG86: Não | AH86: Não | AI86: Art. 33 | AJ86: Não | AK86: Divergências nos relatos dos policiais. Local de tráfico. Confissão informal. Preso no momento da sentença | AL86: Procedente | AM86: Condenação por tráfico | AN86: Art. 33 | AO86: NA | AP86: Não | AQ86: 5a | AR86: Não | AS86: Não | AT86: Não | AU86: Não | AV86: Não | AW86: Sim | AX86: Não | AY86: Não | AZ86: Não | BA86: Não | BB86: Não | BC86: Não | BD86: Não | BE86: Não | BF86: =IF(AZ86="Não","Sim","Não") -> Sim | BG86: =IF(AZ86="NA","Sim","Não") -> Não | BH86: Não | BI86: Sim total | BJ86: Sim (total ou parcial) | BK86: 1a 8m | BL86: 20 | BM86: NA | BN86: NA | BO86: 1a 8m | BP86: 20 | BQ86: Sim | BR86: NA | BS86: NA
A87: 86 | B87: 00033434920178260635 | C87: 1 | D87: 27/06/2017 | E87: FERNANDA ALVES DA ROCHA BRANCO DE OLIVA POLITI | F87: Feminino | G87: 2ª Vara Criminal | H87: GABRIEL DOS REIS OLIVEIRA | I87: 1 | J87: Via Pública | K87: Masculino | L87: 35867 | M87: 19 | N87: Parda | O87: Negros, pardos e outros | P87: Não disponível | Q87: Bolsa. Celular. Dinheiro R$ 20,00 | R87: 55 porções. 109,10 g | S87: 109.1 | T87: 31 porções. 48,1 g | U87: 48.1 | V87: 30 porções. 4,8 g | W87: 4.8 | X87: 0 | Y87: 0 | Z87: 0 | AA87: 0 | AB87: 0 | AC87: Não | AD87: Não | AE87: Não | AF87: Não | AG87: Não | AH87: Não | AI87: Art. 33 | AJ87: Não | AK87: Confissão informal. Local de tráfico. Preso no momento da sentença | AL87: Procedente | AM87: Condenação por tráfico | AN87: Art. 33 | AO87: NA | AP87: Não | AQ87: 5a | AR87: Não | AS87: Não | AT87: Não | AU87: Não | AV87: Não | AW87: Sim | AX87: Não | AY87: Não | AZ87: Não | BA87: Não | BB87: Não | BC87: Não | BD87: Não | BE87: Não | BF87: =IF(AZ87="Não","Sim","Não") -> Sim | BG87: =IF(AZ87="NA","Sim","Não") -> Não | BH87: Não | BI87: Sim total | BJ87: Sim (total ou parcial) | BK87: 1a 8m | BL87: 20 | BM87: NA | BN87: NA | BO87: 1a 8m | BP87: 20 | BQ87: Não | BR87: Fechado | BS87: Fechado
A88: 87 | B88: 00978452320168260050 | C88: 1 | D88: 07/02/2017 | E88: Claudia Carneiro Calbucci Renaux | F88: Feminino | G88: 13ª Vara Criminal | H88: DIEGO DOS SANTOS SOUZA | I88: 1 | J88: Via Pública | K88: Masculino | L88: 34568 | M88: 22 | N88: Parda | O88: Negros, pardos e outros | P88: Carapinha | Q88: Nada | R88: 3 porções. 13,5 g | S88: 13.5 | T88: 0 | U88: 0 | V88: 33 porções. 5,7 g | W88: 5.7 | X88: 0 | Y88: 0 | Z88: 0 | AA88: 0 | AB88: 0 | AC88: Não | AD88: Não | AE88: Não | AF88: Não | AG88: Não | AH88: Não | AI88: Art. 33 | AJ88: Não | AK88: Local de tráfico. Atitude suspeita. Confissão informal | AL88: Procedente | AM88: Condenação por tráfico | AN88: Art. 33 | AO88: NA | AP88: Não | AQ88: 5a | AR88: Não | AS88: Não | AT88: Não | AU88: Não | AV88: Não | AW88: Sim | AX88: Não | AY88: Não | AZ88: Não | BA88: Não | BB88: Não | BC88: Não | BD88: Não | BE88: Não | BF88: =IF(AZ88="Não","Sim","Não") -> Sim | BG88: =IF(AZ88="NA","Sim","Não") -> Não | BH88: Não | BI88: Sim total | BJ88: Sim (total ou parcial) | BK88: 1a 8m | BL88: 20 | BM88: NA | BN88: NA | BO88: 1a 8m | BP88: 20 | BQ88: Sim | BR88: NA | BS88: NA
A89: 88 | B89: 00607549320168260050 | C89: 1 | D89: 21/03/2017 | E89: Vivian Brenner De Oliveira | F89: Feminino | G89: 11ª Vara Criminal | H89: ADEMIR LAMEU DA SILVA | I89: 1 | J89: Via Pública | K89: Masculino | L89: 32784 | M89: 27 | N89: Branca | O89: Branco e amarelo | P89: Encaracolado | Q89: Dinheiro R$ 30,00 | R89: 0 | S89: 0 | T89: 8 porções. 5,5 g | U89: 5.5 | V89: 35 porções. 13,6 g | W89: 13.6 | X89: 0 | Y89: 0 | Z89: 0 | AA89: 0 | AB89: 0 | AC89: Não | AD89: Não | AE89: Não | AF89: Não | AG89: Não | AH89: Não | AI89: Art. 33 | AJ89: Não | AK89: Local de tráfico. Confissão informal | AL89: Procedente | AM89: Condenação por tráfico | AN89: Art. 33 | AO89: NA | AP89: Não | AQ89: 5a | AR89: Não | AS89: Não | AT89: Não | AU89: Não | AV89: Não | AW89: Sim | AX89: Não | AY89: Não | AZ89: Não | BA89: Não | BB89: Não | BC89: Não | BD89: Não | BE89: Não | BF89: =IF(AZ89="Não","Sim","Não") -> Sim | BG89: =IF(AZ89="NA","Sim","Não") -> Não | BH89: Não | BI89: Sim total | BJ89: Sim (total ou parcial) | BK89: 1a 8m | BL89: 20 | BM89: NA | BN89: NA | BO89: 1a 8m | BP89: 20 | BQ89: Não | BR89: Fechado | BS89: Fechado
A90: 89 | B90: 00410526420168260050 | C90: 1 | D90: 05/06/2017 | E90: Isaura Cristina Barreira | F90: Feminino | G90: 30ª Vara Criminal | H90: MATHEUS URIAS VIEIRA | I90: 1 | J90: Via Pública | K90: Masculino | L90: 35730 | M90: 19 | N90: Branca | O90: Branco e amarelo | P90: Encaracolado | Q90: Dinheiro R$ 7,00 | R90: 0 | S90: 0 | T90: 0 | U90: 0 | V90: 39 porções. 17,1 g | W90: 17.1 | X90: 0 | Y90: 0 | Z90: 0 | AA90: 0 | AB90: 0 | AC90: Não | AD90: Não | AE90: Não | AF90: Não | AG90: Não | AH90: Não | AI90: Art. 33 | AJ90: Não | AK90: Local de tráfico | AL90: Procedente | AM90: Condenação por tráfico | AN90: Art. 33 | AO90: NA | AP90: Não | AQ90: 5a | AR90: Não | AS90: Não | AT90: Não | AU90: Não | AV90: Não | AW90: Sim | AX90: Não | AY90: Não | AZ90: Não | BA90: Não | BB90: Não | BC90: Não | BD90: Não | BE90: Não | BF90: =IF(AZ90="Não","Sim","Não") -> Sim | BG90: =IF(AZ90="NA","Sim","Não") -> Não | BH90: Não | BI90: Sim total | BJ90: Sim (total ou parcial) | BK90: 1a 8m | BL90: 20 | BM90: NA | BN90: NA | BO90: 1a 8m | BP90: 20 | BQ90: Não | BR90: Aberto | BS90: Aberto
A91: 90 | B91: 00954782620168260050 | C91: 1 | D91: 22/03/2017 | E91: Luciane Jabur Mouchaloite Figueiredo | F91: Feminino | G91: 21ª Vara Criminal | H91: ERICK SANTANA SOARES RAMOS | I91: 1 | J91: Via Pública | K91: Masculino | L91: 34854 | M91: 21 | N91: Parda | O91: Negros, pardos e outros | P91: Outros | Q91: Bolsa. Dinheiro R$ 20,00 | R91: 318 porções. 549,1 g | S91: 549.1 | T91: 53 porções. 110 g | U91: 110 | V91: 403 porções. 317 g | W91: 317 | X91: 0 | Y91: 0 | Z91: 0 | AA91: 0 | AB91: Lança-perfume. 65 frascos. 2560 ml | AC91: Não | AD91: Não | AE91: Não | AF91: Não | AG91: Sim | AH91: Não | AI91: Art. 33. Art. 35 | AJ91: Não | AK91: Local de tráfico. Confissão informal. Confissão. Preso no momento da sentença. Denúncia | AL91: Parcialmente procedente | AM91: Condenação por tráfico | AN91: Art. 33 | AO91: NA | AP91: Não | AQ91: 5a | AR91: Não | AS91: Não | AT91: Não | AU91: Não | AV91: Não | AW91: Sim | AX91: Não | AY91: Não | AZ91: Não | BA91: Não | BB91: Não | BC91: Não | BD91: Não | BE91: Não | BF91: =IF(AZ91="Não","Sim","Não") -> Sim | BG91: =IF(AZ91="NA","Sim","Não") -> Não | BH91: Não | BI91: Sim total | BJ91: Sim (total ou parcial) | BK91: 1a 8m | BL91: 20 | BM91: NA | BN91: NA | BO91: 1a 8m | BP91: 20 | BQ91: Não | BR91: Fechado | BS91: Fechado
A92: 91 | B92: 00954782620168260050 | C92: 0 | D92: 22/03/2017 | E92: Luciane Jabur Mouchaloite Figueiredo | F92: Feminino | G92: 21ª Vara Criminal | H92: JOSÉ RINALDO DOS SANTOS | I92: 1 | J92: Via Pública | K92: Masculino | L92: 33541 | M92: 25 | N92: Parda | O92: Negros, pardos e outros | P92: Encaracolado | Q92: Bolsa. Dinheiro R$ 20,00 | R92: 318 porções. 549,1 g | S92: 549.1 | T92: 53 porções. 110 g | U92: 110 | V92: 403 porções. 317 g | W92: 317 | X92: 0 | Y92: 0 | Z92: 0 | AA92: 0 | AB92: Lança-perfume. 65 frascos. 2560 ml | AC92: Não | AD92: Não | AE92: Não | AF92: Não | AG92: Sim | AH92: Não | AI92: Art. 33. Art. 35 | AJ92: Não | AK92: Local de tráfico. Confissão informal. Confissão. Preso no momento da sentença. Denúncia | AL92: Parcialmente procedente | AM92: Condenação por tráfico | AN92: Art. 33 | AO92: NA | AP92: Não | AQ92: 5a | AR92: Não | AS92: Não | AT92: Não | AU92: Não | AV92: Não | AW92: Sim | AX92: Não | AY92: Não | AZ92: Não | BA92: Não | BB92: Não | BC92: Não | BD92: Não | BE92: Não | BF92: =IF(AZ92="Não","Sim","Não") -> Sim | BG92: =IF(AZ92="NA","Sim","Não") -> Não | BH92: Não | BI92: Sim total | BJ92: Sim (total ou parcial) | BK92: 1a 8m | BL92: 20 | BM92: NA | BN92: NA | BO92: 1a 8m | BP92: 20 | BQ92: Não | BR92: Fechado | BS92: Fechado
A93: 92 | B93: 00386180520168260050 | C93: 1 | D93: 42976 | E93: Fernanda Galizia Noriega | F93: Feminino | G93: 28ª Vara Criminal | H93: ALEXANDRE MENDES DE PAULO | I93: 1 | J93: Via Pública | K93: Masculino | L93: 31657 | M93: 31 | N93: Parda | O93: Negros, pardos e outros | P93: Não disponível | Q93: Dinheiro R$ 90,00 | R93: 24 porções. 40 g | S93: 40 | T93: 9 porções. 8 g | U93: 8 | V93: 41 porções. 6 g | W93: 6 | X93: 0 | Y93: 0 | Z93: 0 | AA93: 0 | AB93: 0 | AC93: Não | AD93: Não | AE93: Não | AF93: Não | AG93: Não | AH93: Não | AI93: Art. 33 | AJ93: Não | AK93: Local de tráfico. Atitude suspeita. Confissão informal | AL93: Procedente | AM93: Condenação por tráfico | AN93: Art. 33 | AO93: NA | AP93: Não | AQ93: 5a | AR93: Não | AS93: Não | AT93: Não | AU93: Não | AV93: Não | AW93: Sim | AX93: Não | AY93: Não | AZ93: Não | BA93: Não | BB93: Não | BC93: Não | BD93: Não | BE93: Não | BF93: =IF(AZ93="Não","Sim","Não") -> Sim | BG93: =IF(AZ93="NA","Sim","Não") -> Não | BH93: Não | BI93: Sim total | BJ93: Sim (total ou parcial) | BK93: 1a 8m | BL93: 20 | BM93: NA | BN93: NA | BO93: 1a 8m | BP93: 20 | BQ93: Não | BR93: Fechado | BS93: Fechado
A94: 93 | B94: 00306822620168260050 | C94: 1 | D94: 06/04/2017 | E94: Fátima Vilas Boas Cruz | F94: Feminino | G94: 17ª Vara Criminal | H94: WESLEY FERREIRA SOUZA | I94: 1 | J94: Via Pública | K94: Masculino | L94: 35339 | M94: 20 | N94: Outros | O94: Negros, pardos e outros | P94: Não disponível | Q94: Pochete. Dinheiro R$ 15,00 | R94: 0 | S94: 0 | T94: 8 porções. 3,1 g | U94: 3.1 | V94: 48 porções. 9,9 g | W94: 9.9 | X94: 0 | Y94: 0 | Z94: 0 | AA94: 0 | AB94: 0 | AC94: Não | AD94: Não | AE94: Não | AF94: Não | AG94: Não | AH94: Não | AI94: Art. 33 | AJ94: Não | AK94: Confissão informal. Local de tráfico | AL94: Procedente | AM94: Condenação por tráfico | AN94: Art. 33 | AO94: NA | AP94: Não | AQ94: 5a | AR94: Não | AS94: Não | AT94: Não | AU94: Não | AV94: Não | AW94: Sim | AX94: Não | AY94: Não | AZ94: Não | BA94: Não | BB94: Não | BC94: Não | BD94: Não | BE94: Não | BF94: =IF(AZ94="Não","Sim","Não") -> Sim | BG94: =IF(AZ94="NA","Sim","Não") -> Não | BH94: Não | BI94: Sim total | BJ94: Sim (total ou parcial) | BK94: 1a 8m | BL94: 20 | BM94: NA | BN94: NA | BO94: 1a 8m | BP94: 20 | BQ94: Sim | BR94: NA | BS94: NA
A95: 94 | B95: 00918044020168260050 | C95: 1 | D95: 10/03/2017 | E95: Daniela Martins de Castro Mariani Cavallanti | F95: Feminino | G95: 2ª Vara Criminal | H95: MARCOS ANTONIO ARAUJO DO NASCIMENTO | I95: 1 | J95: Via Pública | K95: Masculino | L95: 34963 | M95: 21 | N95: Branca | O95: Branco e amarelo | P95: Liso | Q95: Porta-moeda. Dinheiro R$ 10,00 | R95: 36 porções. 66,10 g | S95: 66.1 | T95: 5 porções. 3,5 g | U95: 33.5 | V95: 49 porções. 6,4 g | W95: 6.4 | X95: 0 | Y95: 0 | Z95: 0 | AA95: 0 | AB95: 0 | AC95: Não | AD95: Não | AE95: Não | AF95: Não | AG95: Não | AH95: Não | AI95: Art. 33 | AJ95: Não | AK95: Confissão. Local de tráfico. Preso no momento da sentença. Denúncia | AL95: Procedente | AM95: Condenação por tráfico | AN95: Art. 33 | AO95: NA | AP95: Sim. Consequências. Natureza. Quantidade | AQ95: 6a | AR95: Não | AS95: Não | AT95: Confissão | AU95: Sim | AV95: Não | AW95: Não | AX95: Não | AY95: Sim | AZ95: Não | BA95: Não | BB95: Não | BC95: Não | BD95: Não | BE95: Não | BF95: =IF(AZ95="Não","Sim","Não") -> Sim | BG95: =IF(AZ95="NA","Sim","Não") -> Não | BH95: Não | BI95: Sim total | BJ95: Sim (total ou parcial) | BK95: 1a 8m | BL95: 20 | BM95: NA | BN95: NA | BO95: 1a 8m | BP95: 20 | BQ95: Não | BR95: Aberto | BS95: Aberto
A96: 95 | B96: 00900592520168260050 | C96: 1 | D96: 08/06/2017 | E96: Carlos Eduardo Oliveira de Alencar | F96: Masculino | G96: 31ª Vara Criminal | H96: LUIZ OTAVIO RAMOS DE OLIVEIRA JUNIOR | I96: 1 | J96: Via Pública | K96: Masculino | L96: 33401 | M96: 26 | N96: Preta | O96: Negros, pardos e outros | P96: Não disponível | Q96: Nada | R96: 4 porções. 12,2 g | S96: 12.2 | T96: 8 porções. 5,8 g | U96: 5.8 | V96: 6 porções. 4,2 g | W96: 4.2 | X96: 0 | Y96: 0 | Z96: 0 | AA96: 0 | AB96: 0 | AC96: Não | AD96: Não | AE96: Não | AF96: Não | AG96: Não | AH96: Não | AI96: Art. 33 | AJ96: Não | AK96: Não há | AL96: Procedente | AM96: Condenação por tráfico | AN96: Art. 33 | AO96: NA | AP96: Não | AQ96: 5a | AR96: Não | AS96: Não | AT96: Não | AU96: Não | AV96: Não | AW96: Sim | AX96: Não | AY96: Não | AZ96: Não | BA96: Não | BB96: Não | BC96: Não | BD96: Não | BE96: Não | BF96: =IF(AZ96="Não","Sim","Não") -> Sim | BG96: =IF(AZ96="NA","Sim","Não") -> Não | BH96: Não | BI96: Sim total | BJ96: Sim (total ou parcial) | BK96: 1a 8m | BL96: 20 | BM96: NA | BN96: NA | BO96: 1a 8m | BP96: 20 | BQ96: Não | BR96: Fechado | BS96: Fechado
A97: 96 | B97: 00894418020168260050 | C97: 1 | D97: 42976 | E97: Érica Aparecida Ribeiro Lopes e Navarro Rodrigues | F97: Feminino | G97: 26ª Vara Criminal | H97: JOSIVAN DA SILVA FELIX NOGUEIRA | I97: 1 | J97: Via Pública | K97: Masculino | L97: 34081 | M97: 24 | N97: Parda | O97: Negros, pardos e outros | P97: Não disponível | Q97: Nada | R97: 10 porções. 12 g | S97: 12 | T97: 128 porções. 47,8 g | U97: 47.8 | V97: 65 porções. 4,1 g | W97: 4.1 | X97: 0 | Y97: 0 | Z97: 0 | AA97: 0 | AB97: 0 | AC97: Não | AD97: Não | AE97: Não | AF97: Não | AG97: Não | AH97: Não | AI97: Art. 33 | AJ97: Não | AK97: Atitude suspeita. Confissão informal. Preso no momento da sentença | AL97: Procedente | AM97: Condenação por tráfico | AN97: Art. 33 | AO97: NA | AP97: Não | AQ97: 5a | AR97: Não | AS97: Não | AT97: Não | AU97: Não | AV97: Não | AW97: Sim | AX97: Não | AY97: Não | AZ97: Não | BA97: Não | BB97: Não | BC97: Não | BD97: Não | BE97: Não | BF97: =IF(AZ97="Não","Sim","Não") -> Sim | BG97: =IF(AZ97="NA","Sim","Não") -> Não | BH97: Não | BI97: Sim total | BJ97: Sim (total ou parcial) | BK97: 1a 8m | BL97: 20 | BM97: NA | BN97: NA | BO97: 1a 8m | BP97: 20 | BQ97: Não | BR97: Fechado | BS97: Fechado
A98: 97 | B98: 00295769220178260050 | C98: 1 | D98: 05/10/2017 | E98: ALESSANDRA TEIXEIRA MIGUEL | F98: Feminino | G98: 32ª Vara Criminal | H98: EMERSON SILVA SANTOS | I98: 1 | J98: Via Pública | K98: Masculino | L98: 34570 | M98: 23 | N98: Parda | O98: Negros, pardos e outros | P98: Não disponível | Q98: Dinheiro R$ 10,00 | R98: 11 porções. 29,2 g | S98: 29.2 | T98: 35 porções. 17,8 g | U98: 17.8 | V98: 8 porções. 1 g | W98: 1 | X98: 0 | Y98: 0 | Z98: 0 | AA98: 0 | AB98: 0 | AC98: Não | AD98: Não | AE98: Não | AF98: Não | AG98: Não | AH98: Não | AI98: Art. 33 | AJ98: Não | AK98: Local de tráfico. Atitude suspeita | AL98: Procedente | AM98: Condenação por tráfico | AN98: Art. 33 | AO98: NA | AP98: Não | AQ98: 5a | AR98: Não | AS98: Não | AT98: Não | AU98: Não | AV98: Não | AW98: Sim | AX98: Não | AY98: Não | AZ98: Não | BA98: Não | BB98: Não | BC98: Não | BD98: Não | BE98: Não | BF98: =IF(AZ98="Não","Sim","Não") -> Sim | BG98: =IF(AZ98="NA","Sim","Não") -> Não | BH98: Não | BI98: Sim total | BJ98: Sim (total ou parcial) | BK98: 1a 8m | BL98: 20 | BM98: NA | BN98: NA | BO98: 1a 8m | BP98: 20 | BQ98: Sim | BR98: NA | BS98: NA
A99: 98 | B99: 00567796320168260050 | C99: 1 | D99: 42853 | E99: Augusto Antonini | F99: Masculino | G99: 28ª Vara Criminal | H99: ALAN CARLOS HENGLER DA SILVA | I99: 1 | J99: Via Pública | K99: Masculino | L99: 35310 | M99: 20 | N99: Preta | O99: Negros, pardos e outros | P99: Carapinha | Q99: Dinheiro R$ 10,00 | R99: 26 porções. 20g | S99: 20 | T99: 81 porções. 138 g | U99: 138 | V99: 82 porções. 48 g | W99: 48 | X99: 0 | Y99: 0 | Z99: 0 | AA99: 0 | AB99: 0 | AC99: Não | AD99: Não | AE99: Não | AF99: Não | AG99: Não | AH99: Não | AI99: Art. 33 | AJ99: Não | AK99: Denúncia anônima. Confissão informal. Confissão. Preso no momento da sentença | AL99: Procedente | AM99: Condenação por tráfico | AN99: Art. 33 | AO99: NA | AP99: Não | AQ99: 5a | AR99: Não | AS99: Não | AT99: Não | AU99: Não | AV99: Não | AW99: Sim | AX99: Não | AY99: Não | AZ99: Não | BA99: Não | BB99: Não | BC99: Não | BD99: Não | BE99: Não | BF99: =IF(AZ99="Não","Sim","Não") -> Sim | BG99: =IF(AZ99="NA","Sim","Não") -> Não | BH99: Não | BI99: Sim total | BJ99: Sim (total ou parcial) | BK99: 1a 8m | BL99: 20 | BM99: NA | BN99: NA | BO99: 1a 8m | BP99: 20 | BQ99: Não | BR99: Fechado | BS99: Fechado
A100: 99 | B100: 00567796320168260050 | C100: 0 | D100: 42853 | E100: Augusto Antonini | F100: Masculino | G100: 28ª Vara Criminal | H100: TIAGO GUEBARA DA SILVA | I100: 1 | J100: Via Pública | K100: Masculino | L100: 35937 | M100: 18 | N100: Preta | O100: Negros, pardos e outros | P100: Carapinha | Q100: Nada | R100: 26 porções. 20g | S100: 20 | T100: 81 porções. 138 g | U100: 138 | V100: 82 porções. 48 g | W100: 48 | X100: 0 | Y100: 0 | Z100: 0 | AA100: 0 | AB100: 0 | AC100: Não | AD100: Não | AE100: Não | AF100: Não | AG100: Não | AH100: Não | AI100: Art. 33 | AJ100: Não | AK100: Denúncia anônima. Confissão informal. Confissão. Preso no momento da sentença | AL100: Procedente | AM100: Condenação por tráfico | AN100: Art. 33 | AO100: NA | AP100: Não | AQ100: 5a | AR100: Não | AS100: Não | AT100: Não | AU100: Não | AV100: Não | AW100: Sim | AX100: Não | AY100: Não | AZ100: Não | BA100: Não | BB100: Não | BC100: Não | BD100: Não | BE100: Não | BF100: =IF(AZ100="Não","Sim","Não") -> Sim | BG100: =IF(AZ100="NA","Sim","Não") -> Não | BH100: Não | BI100: Sim total | BJ100: Sim (total ou parcial) | BK100: 1a 8m | BL100: 20 | BM100: NA | BN100: NA | BO100: 1a 8m | BP100: 20 | BQ100: Não | BR100: Fechado | BS100: Fechado
...

Sheet Objetivos
B3: 1. Título provisório: Gênero e Raça no Sentenciamento de Tráfico de Drogas na cidade de São Paulo.
B5: 2. Tema de pesquisa: Disparidades no sentenciamento decorrente de fatores extralegais, baseados em estereótipos criminais de gênero e raça, incutidos no imaginário dos/as operadores do sistema de justiça.
B7: 3. Objetivo: O objetivo é descobrir se gênero e raça são variáveis fortemente correlacionadas com a severidade da sentença dos crimes de tráfico, mesmo controlados os fatores esperados e previstos legalmente.
B9: 4. Questões de pesquisa:
B10: (i) Há disparidade de gênero e raça, pensados em grupos etários, (individual e conjuntamente consideradas) nas decisões judiciais de (1) tipo de sentença; (2) aplicação de tráfico privilegiado; (3) substituição da pena; (4) regime inicial de cumprimento da pena; (5) quantidade da pena restritiva de liberdade aplicada para o art. 33; e (6) quantidade da pena restritiva de liberdade total?
B11: (ii) Há disparidade de gênero e raça, pensados em grupos etários, (individual e conjuntamente consideradas) nessas decisões judiciais associada à Vara Criminal?
B12: (iii) Há disparidade de gênero e raça, pensados em grupos etários, do réu (individual e conjuntamente consideradas) nessas decisões judiciais associada ao juiz sentenciante?
B13: (iv) Há essas disparidades nas referidas decisões judiciais quando os fatores legais (quantidade da droga, natureza da droga, variedade, personalidade, conduta, consequências, antecedentes, reincidência, agravantes, atenuantes, aumento, §4º, etc) são levados em consideração?
B15: 5. Hipóteses:
B16: i) Os fatores legais serão preponderantes para as decisões de encarceramento e quantidade de pena aplicada.
B17: ii) Haverá interação entre gênero e raça tal que mulheres serão menos propensas a ser encarceradas e receberão sentenças menores do que os homens em cada grupo racial. Além disso, as diferenças entre homens e mulheres serão maiores para pessoas negras do que para brancas.
B18: iii) Haverá diferenças entre os grupos raciais por gênero tal que homens brancos terão menor probabilidade de ser encarcerados e receberão sentenças menores do que os negros. Isso também será verdade para mulheres, com brancas possuindo menor probabilidade de ser encarceradas e menores sentenças do que as negras.
... B21: vi) Determinadas varas ou juízes apresentarão efeitos mais ou menos pronunciados de disparidades de gênero, raça e idade no sentenciamento por tráfico de drogas.

Sheet Descritivo
B2: Qtde processos
B3: =SUM(BD!C:C) -> 352
B5: Data de disponibilização do processo
B6: De | C6: =SMALL(BD!D:D,1) -> 42753
B7: Até | C7: =LARGE(BD!D:D,1) -> 43379
B9: Row Labels | C9: Contagem de Juiz
B10: Klaus Marouelli Arroyo | C10: 12
B11: Carlos Eduardo Lora Franco | C11: 11
B12: Antonio de Oliveira Angrisani Filho | C12: 10
B13: Roseane Cristina de Aguiar Almeida | C13: 10
B14: MARIA PRISCILLA ERNANDES VEIGA OLIVEIRA | C14: 10
B15: Paulo Eduardo Balbone Costa | C15: 10
B16: Rafael Henrique Janela Tamai Rocha | C16: 10
B17: Edison Tetsuzo Namba | C17: 10
B18: TERESA DE ALMEIDA RIBEIRO MAGALHAES | C18: 10
B19: Helio Narvaez | C19: 10
B20: José Roberto Cabral Longaretti | C20: 10
B21: Waldir Calciolari | C21: 9
... B88: Grand Total | C88: 420
B90: Row Labels | C90: Contagem de Vara
B91: 32ª Vara Criminal | C91: 22
B92: 3ª Vara Criminal | C92: 20
B93: 22ª Vara Criminal | C93: 17
B94: 13ª Vara Criminal | C94: 17
B95: 18ª Vara Criminal | C95: 17
B96: 30ª Vara Criminal | C96: 16
B97: 20ª Vara Criminal | C97: 16
B98: 4ª Vara Criminal | C98: 15
B99: 23ª Vara Criminal | C99: 15
B100: 17ª Vara Criminal | C100: 15
B101: 25ª Vara Criminal | C101: 15
B102: 16ª Vara Criminal | C102: 15
... B123: Grand Total | C123: 420
B125: Qtde réus
B126: =SUM(BD!I:I) -> 419
B128: Row Labels | C128: Contagem de Local
B129: Via Pública | C129: 337
B130: Residência | C130: 41
B131: Favela - Viela | C131: 13
B132: Restaurante e afins | C132: 7
B133: Comércio e serviços | C133: 7
B134: Área não ocupada | C134: 6
B135: Terminal/Estação | C135: 3
B136: Invasão/Ocupação | C136: 3
B137: Repartição Pública | C137: 2
B138: Estádio | C138: 1
B139: Grand Total | C139: 420
B141: Row Labels | C141: Contagem de Sexo | E141: Gênero | F141: Qtde | G141: (%)
B142: Feminino | C142: 41 | E142: =B142 -> Feminino | F142: =C142 -> 41 | G142: =F142/GETPIVOTDATA("Sexo",$B$141) -> 0.097619048
B143: Masculino | C143: 379 | E143: =B143 -> Masculino | F143: =C143 -> 379 | G143: =F143/GETPIVOTDATA("Sexo",$B$141) -> 0.90238095
B144: Grand Total | C144: 420 | E144: Total | F144: =C144 -> 420 | G144: =F144/GETPIVOTDATA("Sexo",$B$141) -> 1
B146: Row Labels | C146: Count of ID | E146: Gênero do Juiz | F146: Qtde | G146: (%)
B147: Feminino | C147: 213 | E147: =B147 -> Feminino | F147: =C147 -> 213 | G147: =F147/GETPIVOTDATA("Sexo",$B$141) -> 0.50714286
B148: Masculino | C148: 207 | E148: =B148 -> Masculino | F148: =C148 -> 207 | G148: =F148/GETPIVOTDATA("Sexo",$B$141) -> 0.49285714
B149: Grand Total | C149: 420 | E149: Total | F149: =C149 -> 420 | G149: =F149/GETPIVOTDATA("Sexo",$B$141) -> 1
B151: Row Labels | C151: Contagem de Cutis | E151: Raça | F151: Qtde | G151: (%)
B152: Parda | C152: 215 | E152: =B152 -> Parda | F152: =C152 -> 215 | G152: =F152/GETPIVOTDATA("Sexo",$B$141) -> 0.51190476
B153: Branca | C153: 138 | E153: =B153 -> Branca | F153: =C153 -> 138 | G153: =F153/GETPIVOTDATA("Sexo",$B$141) -> 0.32857143
B154: Preta | C154: 62 | E154: =B154 -> Preta | F154: =C154 -> 62 | G154: =F154/GETPIVOTDATA("Sexo",$B$141) -> 0.14761905
B155: Outros | C155: 3 | E155: =B155 -> Outros | F155: =C155 -> 3 | G155: =F155/GETPIVOTDATA("Sexo",$B$141) -> 0.0071428571
